Workbook
Name \a: [1]期末提出!#REF!
Name ______Ro2: #REF!
Name ______Vo2: #REF!
Name ______Vo3: #REF!
Name _____Ro2: #REF!
Name _____Vo2: #REF!
Name _____Vo3: #REF!
Name ____Ro2: #REF!
Name ____Vo2: #REF!
Name ____Vo3: #REF!
Name ___DEL1: #REF!
Name ___DEL2: #REF!
Name ___DEL3: #REF!
Name ___DS10: [2]list!$M$23:$M$39
Name ___PRT1: #REF!
Name ___PRT2: #REF!
Name ___PRT3: #REF!
Name ___Ro2: #REF!
Name ___Vo2: #REF!
Name ___Vo3: #REF!
Name __DEL1: #REF!
Name __DEL2: #REF!
Name __DEL3: #REF!
Name __DS10: [2]list!$M$23:$M$39
Name __PRT1: #REF!
Name __PRT2: #REF!
Name __PRT3: #REF!
Name __Ro2: #REF!
Name __Vo2: #REF!
Name __Vo3: #REF!
Name _DAT1: #REF!
Name _DAT10: #REF!
Name _DAT11: #REF!
Name _DAT12: #REF!
Name _DAT13: #REF!
Name _DAT14: #REF!
Name _DAT15: #REF!
Name _DAT16: #REF!
Name _DAT17: #REF!
Name _DAT18: #REF!
Name _DAT19: #REF!
Name _DAT2: #REF!
Name _DAT20: #REF!
Name _DAT21: #REF!
Name _DAT22: #REF!
Name _DAT23: #REF!
Name _DAT24: #REF!
Name _DAT25: #REF!
Name _DAT26: #REF!
Name _DAT27: #REF!
Name _DAT28: #REF!
Name _DAT29: #REF!
Name _DAT3: #REF!
Name _DAT4: #REF!
Name _DAT5: #REF!
Name _DAT6: #REF!
Name _DAT7: #REF!
Name _DAT8: #REF!
Name _DAT9: #REF!
Name _DEL1: #REF!

Sheet 進度確認表(New)
N1: 対報告書 未完成件数 | P1: =COUNTIF(AG7:AG2090,"CLOSE")-COUNTIF(AH7:AH1090,"CLOSE")&" 件" -> -51 件 | R1: 対報告書 達成目標 | T1: =ROUNDDOWN(COUNTIF(AH7:AH624,"CLOSE")/COUNTIF(AH7:AH624,"CLOSE"),1) -> 1 | V1: 點檢日 ：未實施 實施內容 ：未實施 預定日 ：7月中旬（Wizus→AN100素地替中） 對策内容 ： ・鍊條及軸承上給油。 ・油管硬化疑慮，汰換新管預定。 實施完成日：○月○日 定期管理 ：工事日給油；點檢：製造:1回/半年，設技: 1回/年。 | Z1: YF 未完成 | AA1: CF 未完成 | AB1: EF 未完成 | AC1: JF 未完成 | AD1: KF 未完成 | AE1: TAS 未完成 | AF1: OFF切 未完成
A2: ADT設備異常、改善、横展開進度確認表 | K2: 【設備ロス削減チーム Link】 | Z2: =COUNTIF(Z7:Z1090,"未") -> 3 | AA2: =COUNTIF(AA7:AA1090,"未") -> 4 | AB2: =COUNTIF(AB7:AB1090,"未") -> 3 | AC2: =COUNTIF(AC7:AC1090,"未") -> 3 | AD2: =COUNTIF(AD7:AD1090,"未") -> 2 | AE2: =COUNTIF(AE7:AE1090,"未") -> 0 | AF2: =COUNTIF(AF7:AF1090,"未") -> 0
Z3: ='横展開率 (舊)'!D4 -> #DIV/0! | AA3: ='横展開率 (舊)'!L4 -> #DIV/0! | AB3: ='横展開率 (舊)'!T4 -> #DIV/0! | AC3: ='横展開率 (舊)'!D26 -> #DIV/0! | AD3: ='横展開率 (舊)'!L26 -> #DIV/0! | AE3: ='横展開率 (舊)'!D50 -> #DIV/0! | AF3: 1
H5: 報告対象 | I5: 中文 報告 | J5: 關聯 資料 | N5: 初回/ 再發 | O5: 停止 時間 (MIN) | P5: LOSS (m2) | Q5: 機會損失 (m2) | R5: 横展開必要LINE | Z5: 各LINE横展開進度 | AG5: 最終結果
A6: 編號№ | B6: 日付 | C6: 場所 （1） | D6: 場所 （2） | E6: 擔當者 | F6: 種別 | G6: 設備名 | H6: 報告対象 | I6: 中文 報告 | J6: 關聯 資料 | K6: 内容 | L6: 原因調査 | M6: 對策内容 | N6: 初回/ 再發 | O6: 停止 時間 (MIN) | P6: LOSS (m2) | Q6: 機會損失 (m2) | R6: YF | S6: CF | T6: EF | U6: JF | V6: KF | W6: TAS | X6: OFF切 | Y6: 横展開方針 | Z6: YF | AA6: CF | AB6: EF | AC6: JF | AD6: KF | AE6: TAS | AF6: OFF切 | AG6: 方針 CLOSE | AH6: 對策 CLOSE | AI6: 完成度 | AJ6: 備考
A7: 1401 | B7: 41798 | C7: ADT | D7: JF | E7: 三路 | F7: 檢查系 | G7: TOM3 | H7: 他拠点報告 | I7: ー | K7: ・歪CAMERA#4 故障 | L7: ・第4TAP發生鬍鬚状的雜訊。 ※推測是歪CAMERA内部的接点不良。 | M7: ・CAMERA更換 ・在歪CAMERA的異常発現用處作成#970GATE ・作成和教育光量異常警報発生時，異常画像発現時的作業流程。 | N7: 初回 | O7: 10 | P7: 259 | R7: 要 | S7: 要 | T7: 要 | U7: - | V7: 要 | W7: - | X7: - | Y7: ・追加#970GATE ・教育光量異常警報発生時，異常画像発現時的作業流程。 | Z7: 完了 | AA7: 完了 | AB7: 完了 | AC7: - | AD7: 完了 | AE7: - | AF7: - | AG7: =IF(Y7="","","CLOSE") -> CLOSE | AH7: =IF(E7="","",IF(COUNTIF(Z7:AE7,"未")=0,"CLOSE","")) -> CLOSE | AI7: =COUNTIF(Z7:AF7,"完了")/COUNTIF(R7:X7,"要") -> 1
A8: =A7+1 -> 1402 | B8: 41812 | C8: ADT | D8: JF | E8: 蔡明建 三路 | F8: 檢查系 | G8: WI | H8: 他拠点報告 | I8: O:\00 製造一部共通\横展開確認\設備異常報告\異常報告書(日文) | J8: O:\00 製造一部共通\横展開確認\設備異常報告\異常報告書(日文)\201406\WI台車抜き出しマニュアル | K8: ・WI CAMERA#11波形異常 | L8: ・推測有落下物掉在CAMERA或光原條紋片上。 ※造成波形異常,影響了平坦度值。 | M8: ・拖出WI光源CAMERA基座,用AIR清除灰塵異物 ・制定連續平坦度惡化時確認流程並教育訓練 ・制定WI光源CAMERA基座拖出的手順並教育訓練. | N8: 初回 | O8: 0 | P8: 0 | R8: 要 | S8: 要 | T8: 要 | U8: - | V8: 要 | W8: - | X8: - | Y8: ・制定連續平坦度惡化時確認流程並教育訓練。 ・制定WI光源CAMERA基座拖出的手順並教育訓練. | Z8: 完了 | AA8: 完了 | AB8: 完了 | AC8: - | AD8: 完了 | AE8: - | AF8: - | AG8: =IF(Y8="","","CLOSE") -> CLOSE | AH8: =IF(E8="","",IF(COUNTIF(Z8:AE8,"未")=0,"CLOSE","")) -> CLOSE | AI8: =COUNTIF(Z8:AF8,"完了")/COUNTIF(R8:X8,"要") -> 1
A9: =A8+1 -> 1403 | B9: 41798 | C9: AFK | D9: LF | E9: 鄭吉勝 | F9: 電氣系 | G9: 帯電Bar | H9: ADT以外 | I9: ..\..\異常報告書(中文)\201406\●LF帯電装置過電流Trip異常-(C_E_J_K_Y_Z)帶電Bar確認.xls | K9: ・LF 帯電装置過電流Trip異常 | L9: ・現場濕度高（65%）的状態下、電荷從帶電Bar樹脂部之裂縫、或是樹脂部的髒污處流竄到支架上，導致過電流並跳脫。 ・由於使用高電壓、絶縁部多少都會因為電氣流動的因素產生裂縫。 | M9: ・工事日時都針對帶電Bar樹脂部實施掃除。 ・裂縫實施Silicon Caulking。 ・帶電Bar的下方設置傳導體（SUS pipe） | N9: 初回 | O9: 95 | P9: 2820 | R9: 要 | S9: 要 | T9: 要 | U9: 要 | V9: 要 | W9: 要 | X9: - | Y9: ・帶電Bar數量確認 ・帶電Bar本體點檢 ・掃除/點檢頻度確認 | Z9: 完了 | AA9: 完了 | AB9: 完了 | AC9: 完了 | AD9: 完了 | AE9: 完了 | AF9: - | AG9: =IF(Y9="","","CLOSE") -> CLOSE | AH9: =IF(E9="","",IF(COUNTIF(Z9:AE9,"未")=0,"CLOSE","")) -> CLOSE | AI9: =COUNTIF(Z9:AF9,"完了")/COUNTIF(R9:X9,"要") -> 1
A10: =A9+1 -> 1404 | B10: 41820 | C10: 全拠点 | D10: 全ライン | E10: 三路 | F10: 系統系 | G10: PAM | H10: ADT以外 | I10: O:\00 製造一部共通\横展開確認\設備異常報告\異常報告書(日文)\201406\20140630 PAM改修.xls | K10: ・PL№無法連結 | L10: ・相同的生産指示書號碼進行2次以上J/C時，發生與PAM内部所持有的號碼不一致，造成PLNo無法連結的現象。 | M10: ・修正版的發行 | N10: 初回 | O10: 0 | P10: 0 | R10: 要 | S10: 要 | T10: 要 | U10: 要 | V10: 要 | W10: - | X10: - | Y10: ・修正版的發行 | Z10: 完了 | AA10: 完了 | AB10: 完了 | AC10: 完了 | AD10: 完了 | AE10: - | AF10: - | AG10: =IF(Y10="","","CLOSE") -> CLOSE | AH10: =IF(E10="","",IF(COUNTIF(Z10:AE10,"未")=0,"CLOSE","")) -> CLOSE | AI10: =COUNTIF(Z10:AF10,"完了")/COUNTIF(R10:X10,"要") -> 1
A11: =A10+1 -> 1405 | B11: 41823 | C11: ADT | D11: CF | E11: 蔵光 | F11: 機械系 | G11: C/V | H11: 他拠点報告 | I11: \\172.18.154.188\adt_public\08_部門情報\8552_素板製造-設備技術\【設備技術修繕紀錄】\03機械\各窯情報資料\20140522 CF本線段ROLL停止--各窯橫展開2014.0606.xls | K11: ・CHAIN断裂異常 (2014/05/22) | L11: ・漏掉冷修後、初期伸長等的点検・確認 | M11: ・CHAIN鬆弛部位的可視化 | N11: 初回 | O11: 259 | P11: 5531 | R11: 要 | S11: 要 | T11: 要 | U11: 要 | V11: 要 | W11: - | X11: - | Y11: ・CHAIN鬆弛部位的可視化 ・LINE SHAFT駆動部的可視化 ※（2014/7/24追記） | Z11: 完了 | AA11: 完了 | AB11: 完了 | AC11: 完了 | AD11: 完了 | AE11: - | AF11: - | AG11: =IF(Y11="","","CLOSE") -> CLOSE | AH11: =IF(E11="","",IF(COUNTIF(Z11:AE11,"未")=0,"CLOSE","")) -> CLOSE | AI11: =COUNTIF(Z11:AF11,"完了")/COUNTIF(R11:X11,"要") -> 1
A12: =A11+1 -> 1406 | B12: 41823 | C12: ADT | D12: CF | E12: 蔵光 | F12: 機械系 | G12: C/V | H12: 他拠点報告 | I12: \\172.18.154.188\adt_public\08_部門情報\8552_素板製造-設備技術\【設備技術修繕紀錄】\03機械\各窯情報資料\20140522 CF本線段ROLL停止--各窯橫展開2014.0606.xls | K12: ・CHAIN断裂異常 (2014/05/22) | L12: ・漏掉冷修後、初期伸長等的点検・確認 | M12: ・CHAIN GUIDE的改造 | N12: 初回 | R12: 要 | S12: 要 | T12: 要 | U12: 要 | V12: 要 | W12: - | X12: - | Y12: ・CHAIN GUIDE的改造 | Z12: 完了 | AA12: 完了 | AB12: 完了 | AC12: 完了 | AD12: 完了 | AE12: - | AF12: - | AG12: =IF(Y12="","","CLOSE") -> CLOSE | AH12: =IF(E12="","",IF(COUNTIF(Z12:AE12,"未")=0,"CLOSE","")) -> CLOSE | AI12: =COUNTIF(Z12:AF12,"完了")/COUNTIF(R12:X12,"要") -> 1
A13: =A12+1 -> 1407 | B13: 41823 | C13: ADT | D13: EF | E13: 万代 | F13: 機械系 | G13: C/V | H13: 他拠点報告 | I13: ー | K13: ・増速SHAFT折損 | L13: ・強度不足 | M13: ・本線増速立起部的CV-Roll SHAFT材質由SS400 25φ變更為SCM435 40φ | N13: 再発 | O13: 120 | P13: 0 | R13: 要 | S13: 要 | T13: 要 | U13: 要 | V13: 要 | W13: - | X13: - | Y13: ・更換SHAFT材質変更的roll | Z13: 完了 | AA13: 完了 | AB13: 完了 | AC13: 完了 | AD13: 完了 | AE13: - | AG13: =IF(Y13="","","CLOSE") -> CLOSE | AH13: =IF(E13="","",IF(COUNTIF(Z13:AE13,"未")=0,"CLOSE","")) -> CLOSE | AI13: =COUNTIF(Z13:AF13,"完了")/COUNTIF(R13:X13,"要") -> 1 | AJ13: 方針CLOSE（冷修対応、来年費用など）
A14: =A13+1 -> 1408 | B14: 41827 | C14: ADT | D14: EF | E14: 鄭吉勝 | F14: 機械系 | G14: C/V | H14: 他拠点報告 | I14: ー | K14: 2Br増速C/V SHAFT破損異常 | L14: ・強度不足 | M14: ・由於現在R5加工的東西變為主流所以實施横展開。(入荷状況要確認） | N14: 再発 | P14: 2.8 | R14: 要 | S14: 要 | T14: 要 | U14: 要 | V14: 要 | W14: - | X14: - | Y14: ・更換為SHAFT材質変更的roll (個別駆動後連結駆動的第一支（増速No.5）→SCM435（shaft径維持現狀） 利用全窯工事日時進行更新) | Z14: 完了 | AA14: 完了 | AB14: 完了 | AC14: 完了 | AD14: 完了 | AE14: - | AF14: - | AG14: =IF(Y14="","","CLOSE") -> CLOSE | AH14: =IF(E14="","",IF(COUNTIF(Z14:AE14,"未")=0,"CLOSE","")) -> CLOSE | AI14: =COUNTIF(Z14:AF14,"完了")/COUNTIF(R14:X14,"要") -> 1 | AJ14: 方針CLOSE（冷修対応、来年費用など）
A15: =A14+1 -> 1409 | B15: 41809 | C15: ADT | D15: OFF切 | E15: 鄭吉勝 | F15: 電氣系 | G15: モーター | H15: 他拠点報告 | I15: 異常報告書（日文）共有フォルダ\其他\●AFK-OFF切#2LineX軸(電纜線焼毀)伺服機構異常-(C_E_J_K_Y_Z)CABLE Bear確認.xlsx | K15: X軸（電纜線燒毀）伺服機構異常 | L15: ・原因調查確認中！ | M15: ・電纜線的更換。 ・次回定修點檢確認 | N15: 初回 | O15: 165 | P15: 615 | R15: 要 | S15: 要 | T15: 要 | U15: 要 | V15: 要 | W15: 要 | X15: 要 | Y15: ・確認橫切機CABLEVEYOR 1.電纜線於CABLEVEYOR中排列是否整齊。 2.CABLEVEYOR中電纜線有無破損狀態。 3.CABLEVEYOR中電纜線有無皺摺或彎曲變形。 4.綑綁電纜線的線材（束帶）是否有斷掉。 | Z15: 完了 | AA15: 完了 | AB15: 完了 | AC15: 完了 | AD15: 完了 | AE15: 完了 | AF15: 完了 | AG15: =IF(Y15="","","CLOSE") -> CLOSE | AH15: =IF(E15="","",IF(COUNTIF(Z15:AE15,"未")=0,"CLOSE","")) -> CLOSE | AI15: =COUNTIF(Z15:AF15,"完了")/COUNTIF(R15:X15,"要") -> 1
A16: =A15+1 -> 1410 | B16: 41837 | C16: ADT | D16: YF | E16: 佐倉 曾志宏 | F16: 其它 | G16: C/V | H16: ADT内対応 | I16: ー | K16: PAD捲起造成板厚計波形異常 | L16: PAD的末端剥落 | M16: ・在PAD貼付作業標準書追加記載貼付方式的使用須知 ・在設備点検作業標準書的PAD点検部位追加關於剥落的內容 | N16: 再発 | O16: 0 | P16: 0 | R16: 要 | S16: 要 | T16: 要 | U16: 要 | V16: 要 | W16: - | X16: - | Y16: 讓整備班、三交代看一遍発生状況的資料，也在巡檢時讓他們看Br板厚計下PAD末端部是否有剥落狀況。 | Z16: 完了 | AA16: 完了 | AB16: 完了 | AC16: 完了 | AD16: 完了 | AE16: - | AF16: - | AG16: =IF(Y16="","","CLOSE") -> CLOSE | AH16: =IF(E16="","",IF(COUNTIF(Z16:AE16,"未")=0,"CLOSE","")) -> CLOSE | AI16: =COUNTIF(Z16:AF16,"完了")/COUNTIF(R16:X16,"要") -> 1
A17: =A16+1 -> 1411 | B17: 41838 | C17: ADT | D17: KF | E17: 鄭吉勝 | F17: 機械系 | G17: 循環 | H17: ADT内対応 | I17: 異常報告書（日文）共有フォルダ\其他\20140718 KF循環系CVキャリアROLL磨損橫展開連絡.xlsx | K17: KF循環系CV CARRIER ROLL磨損 | L17: ・碎玻璃或粉塵堆積 | M17: ・定期巡檢時發現CARRIER ROLL有碎玻璃堆積 立即依賴機械G協助掃除 ・制定聯絡的程序 | N17: 初回 | O17: 0 | P17: 0 | R17: 要 | S17: 要 | T17: 要 | U17: 要 | V17: 要 | W17: - | X17: - | Y17: ・CARRIER ROLL點檢對應流程說明。 ・ 對應作業步驟說明。 | Z17: 完了 | AA17: 完了 | AB17: 完了 | AC17: 完了 | AD17: 完了 | AE17: - | AF17: - | AG17: =IF(Y17="","","CLOSE") -> CLOSE | AH17: =IF(E17="","",IF(COUNTIF(Z17:AE17,"未")=0,"CLOSE","")) -> CLOSE | AI17: =COUNTIF(Z17:AF17,"完了")/COUNTIF(R17:X17,"要") -> 1
A18: =A17+1 -> 1412 | B18: 41824 | C18: AFK | D18: HF | E18: 浅原 | F18: 系統系 | G18: ACE | H18: ADT以外 | I18: 異常報告書（日文）共有フォルダ\其他\20140704HF ACE通信異常.xlsx | K18: ACE通信異常 | L18: LAN驅動程序問題 | M18: LAN驅動程序更新 | N18: 初回 | O18: 18 | P18: 0 | R18: 要 | S18: - | T18: - | U18: - | V18: - | W18: - | X18: - | Y18: LAN驅動程序更新。 8/11再発。対策未定。 | Z18: 完了 | AA18: - | AB18: - | AC18: - | AD18: - | AE18: - | AF18: - | AG18: =IF(Y18="","","CLOSE") -> CLOSE | AH18: =IF(E18="","",IF(COUNTIF(Z18:AE18,"未")=0,"CLOSE","")) -> CLOSE | AI18: =COUNTIF(Z18:AF18,"完了")/COUNTIF(R18:X18,"要") -> 1
A19: =A18+1 -> 1413 | B19: 41836 | C19: ADT | D19: CF | E19: 俊良 | F19: 機械系 | G19: C/V | H19: 他拠点報告 | I19: 異常報告書（日文）共有フォルダ\其他\20140716CF RB採板CV7 ベアリング異常.xlsx | K19: BEARING破損異常 | L19: ・RB LINE的CV点検作業有在定期項目中，雖然有進行点検但是從 安全柵欄外以目視点検，所以沒能発現 | M19: ・点検頻度変更（点検無し→ＪＣ時/工事日点検） ・該部位的可視化 | N19: 初回 | O19: 90 | P19: 50 | R19: - | S19: 要 | T19: 要 | U19: - | V19: - | W19: - | X19: - | Y19: 等待設技見解（CF預定進行BEARING2層化的測試 ～8/末） | Z19: - | AA19: 完了 | AB19: 完了 | AC19: - | AD19: - | AE19: - | AF19: - | AG19: =IF(Y19="","","CLOSE") -> CLOSE | AH19: =IF(E19="","",IF(COUNTIF(Z19:AE19,"未")=0,"CLOSE","")) -> CLOSE | AI19: =COUNTIF(Z19:AF19,"完了")/COUNTIF(R19:X19,"要") -> 1
A20: =A19+1 -> 1414 | B20: 41856 | C20: ADT | D20: ZF | E20: 炳興 | F20: 電氣系 | G20: 循環 | H20: ADT内対応 | I20: 異常報告書（日文）共有フォルダ\其他\20140805 ZF包裝循環4 CULLET BC SLIP異常報告.xlsx | K20: 上游軸承部Slip Sensor感度不良 | L20: 1.Sensor處玻璃粉塵堆積 2.Sensor感應位置不佳 | M20: 1.工事日定期清掃(清掃頻度討論待) 2.工事日全數Sensor感應距離確認(8/14) | N20: 初回 | O20: 0 | P20: 0 | R20: 要 | S20: 要 | T20: 要 | U20: 要 | V20: 要 | W20: - | X20: - | Y20: 1.工事日定期清掃(清掃頻度討論待) 2.工事日全數Sensor感應距離確認(8/14) | Z20: 完了 | AA20: 完了 | AB20: 完了 | AC20: 完了 | AD20: 完了 | AE20: - | AF20: - | AG20: =IF(Y20="","","CLOSE") -> CLOSE | AH20: =IF(E20="","",IF(COUNTIF(Z20:AE20,"未")=0,"CLOSE","")) -> CLOSE | AI20: =COUNTIF(Z20:AF20,"完了")/COUNTIF(R20:X20,"要") -> 1
A21: =A20+1 -> 1415 | B21: 41822 | C21: 高砂 | D21: GF | E21: 浅原 | F21: 機械系 | G21: C/V | H21: ADT以外 | I21: 異常報告書（中文）共有フォルダ\201408以降\20140702GF B-LINE FT部引込CV驅動鏈條斷裂.xls | K21: 駆動CHAIN接頭部破損 | L21: 接頭的定期更換延遅 | M21: 徹底實施定期更換，使用CHAIN更換清冊。 | N21: 初回 | O21: 0 | P21: 161 | R21: 要 | S21: 要 | T21: 要 | U21: 要 | V21: 要 | W21: 要 | X21: - | Y21: 日常点検、週末点検、工事日点検、異常時交換。檢討導入自動給油器(SIMALUBE)。實施1回/半年的定修。CHAIN更換記録以管理清冊作管理。 | Z21: 完了 | AA21: 完了 | AB21: 完了 | AC21: 完了 | AD21: 完了 | AE21: 完了 | AF21: - | AG21: =IF(Y21="","","CLOSE") -> CLOSE | AH21: =IF(E21="","",IF(COUNTIF(Z21:AE21,"未")=0,"CLOSE","")) -> CLOSE | AI21: =COUNTIF(Z21:AF21,"完了")/COUNTIF(R21:X21,"要") -> 1
A22: =A21+1 -> 1416 | B22: 41841 | C22: ADT | D22: JF | E22: 峯謀 | F22: 電氣系 | G22: 採板設備 | H22: ADT内対応 | I22: 異常報告書（中文）共有フォルダ\201407\20140721JF 採板ROBOT制御盤電源異常.xls | K22: 因對應瞬停用UPS的故障造成電源装置的保險絲破損，使得電源無法開啟。 | L22: UPS基板內部的電容器因為長時間過電壓。溫度過高的關係.電容器絕緣失效爆裂.導致UPS故障。 | M22: ・UPS内、電容器耐電圧規格的変更請依賴業者進行更換。以更換後的部分來進行測試，如果沒有問題的話，就依序更換電容器。 ・如果電容器更換前再次發生異常的話，以不會影響UPS電源的配線變更做対応。 | N22: 初回 | O22: 5 | P22: 106 | R22: - | S22: 要 | T22: 要 | U22: 要 | V22: 要 | W22: 要 | X22: - | Y22: 1.電氣測試中.待判定OK後將陸續展開交換作業。 | Z22: - | AA22: 完了 | AB22: 完了 | AC22: 完了 | AD22: 完了 | AE22: 完了 | AF22: - | AG22: =IF(Y22="","","CLOSE") -> CLOSE | AH22: =IF(E22="","",IF(COUNTIF(Z22:AE22,"未")=0,"CLOSE","")) -> CLOSE | AI22: =COUNTIF(Z22:AF22,"完了")/COUNTIF(R22:X22,"要") -> 1 | AJ22: →最終評価はいつまでに出すの？それを決めないと進まない！！ →最終評価は電気G周さんよりOKとの連絡有り。 →J/K冷修導入横展開スケジュール計画有り。(指摘修繕計畫列入)一時CLOSE
A23: =A22+1 -> 1417 | B23: 41863 | C23: AFK | D23: FF | E23: 三路 | F23: 機械系 | G23: P詰め機 | H23: ADT以外 | I23: 異常報告書（中文）共有フォルダ\201408以降\20140805_AFK_FF_PL ChangerPL空PL衝突異常.xls | K23: 実際PL搬送用伺服的馬達連軸器的KEY脱落，造成実際PL搬送的停止位置偏移。 | L23: 連軸器的KEY脱落 | M23: ・KEY加工変更（AFK詢問中？） ・在実際PL搬送（払出側）追加停止位置確認PR | N23: 初回 | O23: 13 | P23: 350 | R23: - | S23: 要 | T23: 要 | U23: 要 | V23: - | W23: - | X23: - | Y23: ・機械G点検後檢討対策 ・在実際PL搬送（払出側）追加停止位置確認PR | Z23: - | AA23: 完了 | AB23: 完了 | AC23: 完了 | AD23: - | AE23: - | AF23: - | AG23: =IF(Y23="","","CLOSE") -> CLOSE | AH23: =IF(E23="","",IF(COUNTIF(Z23:AE23,"未")=0,"CLOSE","")) -> CLOSE | AI23: =COUNTIF(Z23:AF23,"完了")/COUNTIF(R23:X23,"要") -> 1
A24: =A23+1 -> 1418 | B24: 41854 | C24: AFK | D24: TAS | E24: 浅原 | F24: 電氣系 | G24: C/V | H24: ADT以外 | I24: 異常報告書（中文）共有フォルダ\201408以降\20140803 Glass檢知Senser異常.xls | J24: 異常報告書（中文）共有フォルダ\201408以降\20140803 Glass檢知Senser異常.xls | K24: 基板檢查結束後, 未正常移載至採板側, Though (直接通過)造成廢棄Loss（1枚）。之後還是間斷出現Though廢棄, 於是Line停機並呼出設技。 | L24: 就解決了, 所以原因推測為反射板或Senser起霧的關係。 | M24: 持續工事日定期點檢掃除。 | N24: 初回 | O24: 38 | P24: 218 | R24: 要 | S24: 要 | T24: 要 | U24: 要 | V24: 要 | W24: 要 | X24: 要 | Y24: 定期地清掃傳感器。 定期地調整傳感器的靈敏度。 | Z24: 完了 | AA24: 完了 | AB24: 完了 | AC24: 完了 | AD24: 完了 | AE24: 完了 | AF24: 完了 | AG24: =IF(Y24="","","CLOSE") -> CLOSE | AH24: =IF(E24="","",IF(COUNTIF(Z24:AE24,"未")=0,"CLOSE","")) -> CLOSE | AI24: =COUNTIF(Z24:AF24,"完了")/COUNTIF(R24:X24,"要") -> 1
A25: =A24+1 -> 1419 | B25: 41837 | C25: AFK | D25: TAS | E25: 浅原 | F25: 機械系 | G25: 真空Pump | H25: ADT以外 | I25: 異常報告書（中文）共有フォルダ\201407\20140717GUT OFF切NO1真空P力異常.xls | J25: ..\..\異常報告書(中文)\201407\●AFK-GUT OFF切#1真空Pump壓力異常-(C_E_J_K_Y_Z)真空Pump確認.xls | K25: 發生Glass吸著異常発生。真空Pump 由原本使用的#1切替到 #1#2同時使用，也無良化。切替至真空Pump#2單獨使用後 異常才解除。 | L25: 碳片出現部分破損導致壓力低下。推測碳片的磨耗致使失衡, 並發生碳片破損。 | M25: 更換真空Pump #1（7/18實施）。將真空Pump 安全柵内⇒安全柵外 以利保養。改善更換作業性（7/21完成）。檢討定期更換等預防措施可行性 | N25: 初回 | O25: 143 | P25: 554 | R25: 要 | S25: 要 | T25: 要 | U25: 要 | V25: 要 | W25: 要 | X25: 要 | Y25: 確認真空泵的檢查記錄。 確認真空泵的交換記錄。 確認真空泵的設置位置。 | Z25: 完了 | AA25: 完了 | AB25: 完了 | AC25: 完了 | AD25: 完了 | AE25: 完了 | AF25: 完了 | AG25: =IF(Y25="","","CLOSE") -> CLOSE | AH25: =IF(E25="","",IF(COUNTIF(Z25:AE25,"未")=0,"CLOSE","")) -> CLOSE | AI25: =COUNTIF(Z25:AF25,"完了")/COUNTIF(R25:X25,"要") -> 1
A26: =A25+1 -> 1420 | B26: 41843 | C26: ADT | D26: ZF | E26: 浅原 | F26: 檢查系 | G26: 精査 | H26: ADT内対応 | I26: 異常報告書（中文）共有フォルダ\201408以降\複本 20140723ZF 精査ｼﾝｸﾗｲｱﾝﾄ用HUB異常報告.xls | K26: 精査thin client異常。T/P畫面上顯示『remote esktop 沒有接上 remote computer』重新啟動精査判定SERVER,但無法登入。因為精査thin client用的HUB LED 燈號熄滅所以拔掉HUB的電源線後重新插上就回復正常了。之後異常就沒再發生過了。 | L26: ①推測是HUB的電源線鬆脫。 ②重要的檢查機附帶設備的維持管理不足。 | M26: 原因①的對策 固定好HUB電源線,使其不鬆脫。 變更HUB的電源設置位置。 原因②的對策 實施詳查室的處理整頓。 為整備班的檢查表追加HUB確認項目。 | N26: 初回 | O26: 6 | P26: 112 | R26: 要 | S26: 要 | T26: 要 | U26: 要 | V26: 要 | W26: 情報 | X26: 情報 | Y26: 固定好HUB電源線,使其不鬆脫。 變更HUB的電源設置位置。 實施詳查室的處理整頓。 為整備班的檢查表追加HUB確認項目。 | Z26: 完了 | AA26: 完了 | AB26: 完了 | AC26: 完了 | AD26: 完了 | AE26: - | AF26: - | AG26: =IF(Y26="","","CLOSE") -> CLOSE | AH26: =IF(E26="","",IF(COUNTIF(Z26:AE26,"未")=0,"CLOSE","")) -> CLOSE | AI26: =COUNTIF(Z26:AF26,"完了")/COUNTIF(R26:X26,"要") -> 1
A27: =A26+1 -> 1421 | B27: 41857 | C27: AFK | D27: IF | E27: 浅原 | F27: 機械系 | G27: C/V | H27: ADT以外 | I27: 異常報告書（中文）共有フォルダ\201408以降\20140806IF 本線CVロールシャフトエンドプレート脱落異常(中文).xls | K27: 巡檢發現到，本線CV Roll#238的驅動側，防止sprocket key鬆脫的end plate脫落，sprocket外移了10mm左右。呼出設備技術，Guillotine處理開始。修復完成。Guillotine解除。F1採版開始 | L27: 冷修時的旋緊不足。因roll的連續回轉的震動，螺絲鬆脫、掉落。現在使用Nord-Lock墊圈的緣故，如果正確地鎖好的話，不太可能輕易地就鬆脫。 | M27: 下次工事日時增強旋緊度 （在工事日之前，從點檢窗做目視點檢） | N27: 再発 | O27: 35 | P27: 952 | R27: 情報 | S27: 情報 | T27: 情報 | U27: 情報 | V27: 情報 | W27: 情報 | X27: 情報 | Y27: 工事日時、檢查實施。增強旋緊度。 能看見的化。 使用Nord-Lock墊圈。 8/6再発、対策未定。 | Z27: - | AA27: - | AB27: - | AC27: - | AD27: - | AE27: - | AF27: - | AG27: =IF(Y27="","","CLOSE") -> CLOSE | AH27: =IF(E27="","",IF(COUNTIF(Z27:AE27,"未")=0,"CLOSE","")) -> CLOSE | AI27: =COUNTIF(Z27:AF27,"完了")/COUNTIF(R27:X27,"要") -> #DIV/0!
A28: =A27+1 -> 1422 | B28: 41859 | C28: AFK | D28: LF | E28: 浅原 | F28: 機械系 | G28: C/V | H28: ADT以外 | I28: 異常報告書（中文）共有フォルダ\201408以降\20140808LF 本線増速No 4No 5共用惰輪(Idler)固定Plate折損.xls | K28: 製造三交代發現惰輪Idler出現晃動情形。呼出設技機械Team, 確認時發現惰輪Ider的固定Plate折損。（雖然整個斷掉了, 但是沒有脫落還是一直回轉。）開啟Guillotine該處實施焊接補強生産再開 | L28: 増速C/V＃4減速及＃5加速時、推測負荷集中在該處的惰輪Idler而斷裂。同樣規格的惰輪Idler目前使用在増速C/V＃5＃6間、増速C/V＃6＃7間、仍追加一片Plate並進行了焊接補強（LF建設時） | M28: 緊急對應內側追加一片Plate並進行焊接補強對策製作一整片的新的Plate、於下回工事日進行設置 | N28: 初回 | O28: 60 | P28: 1234 | R28: - | S28: - | T28: - | U28: - | V28: 要 | W28: - | X28: - | Y28: KF 本線№4 C/V。 Idler軸的材質變更為SCM435。 （利用冷修工事進行） | Z28: - | AA28: - | AB28: - | AC28: - | AD28: 完了 | AE28: - | AF28: - | AG28: =IF(Y28="","","CLOSE") -> CLOSE | AH28: =IF(E28="","",IF(COUNTIF(Z28:AE28,"未")=0,"CLOSE","")) -> CLOSE | AI28: =COUNTIF(Z28:AF28,"完了")/COUNTIF(R28:X28,"要") -> 1
A29: =A28+1 -> 1423 | B29: 41855 | C29: 高砂 | D29: GF | E29: 浅原 | F29: 電氣系 | G29: A/K | H29: ADT以外 | I29: 異常報告書（中文）共有フォルダ\201408以降\20140804 GF B-LINE洗浄機Air_Knife_INV異常.xls | K29: B-LINE洗浄機Air_Knife_INV異常発生(2Br全採中, 因此無Loss)Thermal(積熱繼電器)跳脫無法復歸, 因此呼出設技實施Blower更換B-LINE刮傷檢查後開始採板 | L29: Blower_Motor過熱融解導致Bearing卡住、再加上Motor的熱度影響到 Motor冷却用Fan的樹脂Blade(葉片)融解※GF1 ON-TAS Start時(2008年～)起持續使用。 無更換& Overhaul(大檢修)。 | M29: ・毎月工事日更換2台備品, 並依序實施 Overhaul(大檢修)。(※9台+預備2台 約需4個月可全數更換) | N29: 初回 | O29: 0 | P29: 0 | R29: - | S29: - | T29: - | U29: 要 | V29: 要 | W29: 要 | X29: 要 | Y29: 並依序實施 Overhaul。 （設備技術相談待） ADT OFF-TAS・・・1回/3年 ON-TAS・・・1回/冷修 | Z29: - | AA29: - | AB29: - | AC29: 完了 | AD29: 完了 | AE29: 完了 | AF29: 完了 | AG29: =IF(Y29="","","CLOSE") -> CLOSE | AH29: =IF(E29="","",IF(COUNTIF(Z29:AE29,"未")=0,"CLOSE","")) -> CLOSE | AI29: =COUNTIF(Z29:AF29,"完了")/COUNTIF(R29:X29,"要") -> 1
A30: =A29+1 -> 1424 | B30: 41851 | C30: AFK | D30: TAS | E30: 浅原 | F30: 電氣系 | G30: 水處理場電源供應器 | H30: ADT以外 | I30: 異常報告書（中文）共有フォルダ\201408以降\20140731GUT GUT水處理場電源供應器停止異常.xls | K30: 於GUT全產線純水發生桶槽缺水預報及缺水警報、產線依序停止。由於水處理場制御盤警報畫面之2B3T №2 PUMP有出現停止警報（№1PUMP稼働）、因此呼出設技。由於洗滌器的電源是由FF窯供給的，因此沒有停止。以臨時電源來讓純水桶槽得以往產線供給（生産再開）。制御盤内之電源供應器（1台）確認故障、更換為予備品。設備復舊。 | L30: 由於主電源的制御盤電源發生停止因此警報沒能響起。由於使用壽命可達10年因此未進行更換。（DF：GUT 2005年8月量産開始）由於緊急用的純水Back Up供給手順未能準備妥當因此耽擱到生産之再開。 | M30: 8/24 伴隨著DF3的冷修工事計劃於停電時將水處理場的電源供應器進行全數更換。其他、關於各產線之制御電源計畫藉由明年度的起業申請、依序進行更換。關於水處理場的警報因為對於人體、環境都有很顯著的影響、有依賴希望能從上位階層來發報，但得到的回覆是說很困難。（於設技再進行檢討） | N30: 初回 | O30: 0 | P30: 344 | R30: 要 | S30: 要 | T30: 要 | U30: 要 | V30: 要 | W30: 要 | X30: - | Y30: 重要的設備的電源供應器。 計劃地更新。 協議設技決定。 ※橫(側)展開連決定在擔當者會議上協議電G更新哪個設備。 2014/10/8 各設備のDC電源装置について、「優先順位」・「交換頻度」のリストを各ライン毎に電気Gが作成中。 | Z30: 完了 | AA30: 完了 | AB30: 完了 | AC30: 完了 | AD30: 完了 | AE30: 完了 | AF30: - | AG30: =IF(Y30="","","CLOSE") -> CLOSE | AH30: =IF(E30="","",IF(COUNTIF(Z30:AE30,"未")=0,"CLOSE","")) -> CLOSE | AI30: =COUNTIF(Z30:AF30,"完了")/COUNTIF(R30:X30,"要") -> 1
A31: =A30+1 -> 1425 | B31: 41857 | C31: AFK | D31: IF | E31: 浅原 | F31: 機械系 | G31: C/V | H31: ADT以外 | I31: 異常報告書（中文）共有フォルダ\201408以降\20140806IF 本線CVロールシャフトエンドプレート脱落異常(中文).xls | K31: 巡檢時發現本線増速CV_Roll驅動側防止Sprocket_Key脫落的End_Plate上面的兩支固定螺栓有一支已經脱落了、剩下一支也快要脱落了、Plate呈現不夠穩固的狀態。和上次的Roll同一支。※上午巡檢的部分確認沒有問題。呼出設技、開啟Guillotine H/O捨板處理。這次使用樂泰( LOCTITE) 來固定螺栓。復歸結束後。F1採板開始。 | L31: 上回在8/6發生時、以確實進行螺栓増締鎖緊的對策、 再加上使用的已經是Nord-Lock的華司、但是螺栓還是鬆掉了。 原因調査中。 | M31: 【緊急對策】 使用樂泰( LOCTITE) 來固定螺栓。 （包含同様的發生位置、持續由點檢口進行目視點檢） 【恒久對策】 現段階未決定。原因調査中。 | R31: 情報 | S31: 情報 | T31: 情報 | U31: 情報 | V31: 情報 | W31: 情報 | X31: 情報 | Y31: 再発。原因不明。対策未定。 | Z31: - | AA31: - | AB31: - | AC31: - | AD31: - | AE31: - | AF31: - | AG31: =IF(Y31="","","CLOSE") -> CLOSE | AH31: =IF(E31="","",IF(COUNTIF(Z31:AE31,"未")=0,"CLOSE","")) -> CLOSE | AI31: =COUNTIF(Z31:AF31,"完了")/COUNTIF(R31:X31,"要") -> #DIV/0!
A32: =A31+1 -> 1426 | B32: 41862 | C32: AFK | D32: HF | E32: 浅原 | F32: 系統系 | G32: ACE | H32: ADT以外 | I32: 異常報告書（中文）共有フォルダ\201408以降\20140811HF ACE通信異常（再）.xls | K32: ACE通信異常 | L32: 懷疑PC內藏LAN CARD的能力不足。 | M32: 擴張型NIC(LAN CARD)變更預定。 | N32: 再発 | O32: 0 | P32: 0 | R32: 情報 | S32: - | T32: - | U32: - | V32: - | W32: - | X32: - | Y32: 再発。 AFKの対策としては、擴張型NIC(LAN CARD)變更。 ★ADT内のSiemens製PCでは発生していない事と（個体不良の疑い）、発生原因が特定出来ていない事から、ADTでは「情報」のみとする。（ADT電気） | Z32: - | AA32: - | AB32: - | AC32: - | AD32: - | AE32: - | AF32: - | AG32: =IF(Y32="","","CLOSE") -> CLOSE | AH32: =IF(E32="","",IF(COUNTIF(Z32:AE32,"未")=0,"CLOSE","")) -> CLOSE | AI32: =COUNTIF(Z32:AF32,"完了")/COUNTIF(R32:X32,"要") -> #DIV/0!
A33: =A32+1 -> 1427 | B33: 41849 | C33: AFK | D33: HF | E33: 三路 | F33: 電氣系 | G33: C/V | H33: ADT以外 | I33: 異常報告書（中文）共有フォルダ\201407\20140719HF 2Br紙巻CV驅動伺服馬達過負荷停止異常-中文.xls | K33: 紙巻C/V因伺服異常（過負荷）而停止。即使更換Motor・Amp・Relay・DC電源装置也沒有良化。※在Motor単体下負荷率低沒有發生異常。將伺服的Tuning模式由AUTO變更為MANUAL後良化。 | L33: 由於Motor単独運転下負荷率低，所以假定是滾輪、惰輪的軸承劣化等機械性的要因。再加上Motor的Tuning模式為AUTO Tuning，所以累積負荷率造成異常。 | M33: Tuning模式由AUTO變更為MANUAL。 | N33: 初回 | O33: 0 | P33: 0 | R33: - | S33: - | T33: - | U33: - | V33: - | W33: - | X33: - | Y33: 因為AFK沒有找出根本的原因（為何負荷會變高?），所以ADT的方針就是什麼都不要做。 先看看伺服的AUTO Tuning的負荷状態再來應對。 雖然認為伺服馬達的負荷上好像有什麼大的負荷変動，但最終卻什麼都沒有發現。 擔心同様的事件時做MANUAL的設定是比較有利，但是負荷漸漸加重時AUTO則比較有利。 | Z33: - | AA33: - | AB33: - | AC33: - | AD33: - | AE33: - | AF33: - | AG33: =IF(Y33="","","CLOSE") -> CLOSE | AH33: =IF(E33="","",IF(COUNTIF(Z33:AE33,"未")=0,"CLOSE","")) -> CLOSE | AI33: =COUNTIF(Z33:AF33,"完了")/COUNTIF(R33:X33,"要") -> #DIV/0!
A34: =A33+1 -> 1428 | B34: 41878 | C34: ADT | D34: JF | E34: 三路 | F34: 電氣系 | G34: 縦切機 | H34: ADT内対応 | I34: 異常報告書（中文）共有フォルダ\201408以降\20140827JF №1縦切機停止異常.xls | K34: 採板中由於Frame上昇，造成沒有縦切線。另外也無法做TP的操作。 ※沒有發出異常警報 | L34: Frame上昇・無法操作TP的原因 ・由於PLC不知是什麼原因造成停止。 沒有異常警報的原因 ・由於PLC停止造成警報無法出力。 | M34: ・雜訊対策検討中（ADT電気） ・改造成以本線Master PLC來監視縦切機PLC，當PLC異常時由本線Master PLC來發出警報的soft。 | N34: 初回 | O34: 9 | P34: 172 | R34: 要 | S34: 要 | T34: 要 | U34: 要 | V34: 要 | W34: - | X34: - | Y34: 改造成即使在縦切機PLC發生異常時也能夠發出警報的soft。 | Z34: 完了 | AA34: 完了 | AB34: 完了 | AC34: 完了 | AD34: 完了 | AE34: - | AF34: - | AG34: =IF(Y34="","","CLOSE") -> CLOSE | AH34: =IF(E34="","",IF(COUNTIF(Z34:AE34,"未")=0,"CLOSE","")) -> CLOSE | AI34: =COUNTIF(Z34:AF34,"完了")/COUNTIF(R34:X34,"要") -> 1 | AJ34: 方針CLOSE（KF/冷修中対応）←12/30完了
A35: =A34+1 -> 1429 | B35: 41881 | C35: ADT | D35: CF | E35: 蔵光 | F35: 機械系 | G35: SMAP | H35: ADT内対応 | I35: 異常報告書（中文）共有フォルダ\201408以降\20140830CF L側SMAP動作異常.xls | K35: 三交代聯絡L側SMAP動作異常。整備進行確認懷疑電磁閥損壞，聯絡電氣機械進行對應。三交代協助耳部拿取，進行電磁閥更換。更換完畢經過動作測試與採板測試異常再發。將氣壓缸32號潤滑油開啟後，進行動作測試。測試OK，恢復SMAP採板。觀察無再發。 | L35: 更換電磁閥後異常再發。進行32號潤滑油的給油調整後，動作異常良化。此處氣壓缸潤滑油平時是關閉沒有使用的狀態。因此造成此次氣壓缸潤滑不足進而造成SMAP動作異常。不使用的理由是在消音器的出風口會有油汙噴濺的可能。會有品質上的疑慮。 | M35: 更換電磁閥與開啟32號潤滑油 (暫時對應-機械、電氣)。改善32號潤滑油使用方式。平時不使用=>1次/2週 (每次開啟8小時) (頻度可再檢討)電磁閥消音器使用吸油棉包覆防止潤滑油噴濺。 | N35: 初回 | O35: 0 | P35: 113 | R35: - | S35: 要 | T35: 要 | U35: 要 | V35: 要 | W35: - | X35: - | Y35: ①於整備日常點檢表追記 Lubricator給油器相關管理項目（Oil殘量、開度Dial數値、給油）。 ②教育整備人員Lubricator給油器的作用。 ③設置Lubricator給油器的設備需全數設置Exhaust Cleaner （油霧回収機器）。（ADT全窯）（對象設備）本線SMAP、本線GATE_Shutter、FT/引入/BB PAD部。 | Z35: - | AA35: 完了 | AB35: 完了 | AC35: 完了 | AD35: 完了 | AE35: - | AF35: - | AG35: =IF(Y35="","","CLOSE") -> CLOSE | AH35: =IF(E35="","",IF(COUNTIF(Z35:AE35,"未")=0,"CLOSE","")) -> CLOSE | AI35: =COUNTIF(Z35:AF35,"完了")/COUNTIF(R35:X35,"要") -> 1 | AJ35: Y/Eはどうするの？ →YF確認中。 →EFは2Brのみ残っている。（12月中に完了させます。）
A36: =A35+1 -> 1430 | B36: 41880 | C36: AFK | D36: HF | E36: 三路 | F36: 機械系 | G36: 紙巻機 | H36: ADT以外 | I36: 異常報告書（中文）共有フォルダ\201408以降\20140821HF IZUMI産業製 紙巻機切刀上刃LM_Guide固定螺栓折損異常.xls | K36: 由於Cutter的紙切不良進行點檢時，發現將Cutter的上刀刃固定在LM Guide處的螺栓折損。由於螺栓更換2天後還是發生同様的異常，因此做Cutter Unit的更換。 | L36: 一直以來，上刀刃和下刀刃的上下是以下刀刃側的Liner調整，由於下刀刃的調整量已經用盡，因此在上刀刃側LM Guide處加入Liner做調整，造成Cylinder Piston(汽缸活塞)的負荷。 | M36: ・發現左右Cylinder的昇降時間點有明顯錯開時，就進行Cylinder点検而不要勉強去調整。 ・關於Cutter的紙切，下刀刃的調整量用盡時，就做Cutter Unit本体的更換。 | N36: 初回 | O36: 0 | P36: 0 | R36: - | S36: - | T36: - | U36: 要 | V36: 要 | W36: 要 | X36: - | Y36: ・下次工事日進行CYL及LM Guide的点検。 ・点検後Cutter昇降動作如果有異常的話，請依賴機械做CYL的確認，製造方面不要勉強去做調整。 | Z36: - | AA36: - | AB36: - | AC36: 完了 | AD36: 完了 | AE36: 完了 | AF36: - | AG36: =IF(Y36="","","CLOSE") -> CLOSE | AH36: =IF(E36="","",IF(COUNTIF(Z36:AE36,"未")=0,"CLOSE","")) -> CLOSE | AI36: =COUNTIF(Z36:AF36,"完了")/COUNTIF(R36:X36,"要") -> 1
A37: =A36+1 -> 1431 | B37: 41884 | C37: ADT | D37: EF | E37: 万代 | F37: 機械系 | G37: 採板設備 | H37: ADT内対応 | I37: 異常報告書（中文）共有フォルダ\201408以降\20140902EF 6P採板RB紙掴みシリンダー異常rev.1.xls | K37: 6:24 6POS 採板ROBOT發生紙抓動作異常。6:30 切替2Bｒ全採。6:40 確認到6POS左上紙抓CYL脫落。呼出整備。7:10 6POS左上部 紙抓CYL交換作業開始。7:40 CYL更換後、進行試板流及CYL動作速度調整。8:15 1Bｒ恢復全採 | M37: 壓力設定在0.13Mpa。預定變更CYL型式 MGPL12→MGPM12(額定扭矩up） | N37: 再発 | O37: 6 | P37: 29 | R37: - | S37: 要 | T37: 要 | U37: - | V37: 要 | W37: - | X37: - | Y37: 壓力設定在0.13Mpa。預定變更CYL型式 MGPL12→MGPM12(額定扭矩up）(結論）0.20Mpaで使用することでCLOSE | Z37: - | AA37: 完了 | AB37: 完了 | AC37: - | AD37: 完了 | AE37: - | AF37: - | AG37: =IF(Y37="","","CLOSE") -> CLOSE | AH37: =IF(E37="","",IF(COUNTIF(Z37:AE37,"未")=0,"CLOSE","")) -> CLOSE | AI37: =COUNTIF(Z37:AF37,"完了")/COUNTIF(R37:X37,"要") -> 1
A38: =A37+1 -> 1432 | B38: 41892 | C38: ADT | D38: YF | E38: 仕明 | F38: 機械系 | G38: SMAP | H38: ADT内対応 | I38: 異常報告書（中文）共有フォルダ\201408以降\20140910 YF 包裝 R側 SMAP異常報告書.xls | K38: 時規皮帶劣化，導致作動不良 | M38: 1.進行L側SMAP時規皮帶及調速閥點檢(橫展開)。2.平時SMAP作動速度發生變化時立即進行調整，若無法調整連絡機械人員進行確認 3.CYLINDER交換時連同調速閥也一倂更換 | N38: 初回 | O38: 3 | P38: 92 | R38: 要 | S38: 要 | T38: 要 | U38: 要 | V38: 要 | W38: - | X38: - | Y38: 1.進行L側SMAP時規皮帶及調速閥點檢(橫展開)。2.平時SMAP作動速度發生變化時立即進行調整，若無法調整連絡機械人員進行確認 3.CYLINDER更換時連同調速閥也一倂更換 | Z38: 完了 | AA38: 完了 | AB38: 完了 | AC38: 完了 | AD38: 完了 | AE38: - | AF38: - | AG38: =IF(Y38="","","CLOSE") -> CLOSE | AH38: =IF(E38="","",IF(COUNTIF(Z38:AE38,"未")=0,"CLOSE","")) -> CLOSE | AI38: =COUNTIF(Z38:AF38,"完了")/COUNTIF(R38:X38,"要") -> 1
A39: =A38+1 -> 1433 | B39: 41889 | C39: 高砂 | D39: OFF切 | E39: 三路 | F39: 機械系 | G39: C/V | H39: ADT以外 | I39: 異常報告書（中文）共有フォルダ\201408以降\20140907TDS2 搬送異常Trouble報告.xls | J39: O:\00 製造一部共通\横展開確認\設備異常報告\異常報告書(日文)\201408以降\ADT OFF切機擴出CV驅動惰輪.xls | K39: 由於皮帶摩耗 導致鐵絲呈現外露状態 因此進行皮帶更換。由於搬送皮帶偏移到Pulley突出部位的上方、因接觸而摩耗 | M39: 做為預防措置、確認皮帶摩耗状態時若發現偏移狀況、需隨時進行Pulley的對芯調整 | N39: 初回 | O39: 180 | P39: 0 | R39: - | S39: - | T39: - | U39: - | V39: - | W39: - | X39: 要 | Y39: 做為預防措置、確認皮帶摩耗状態時若發現偏移狀況、需隨時進行Pulley的對芯調整 | Z39: - | AA39: - | AB39: - | AC39: - | AD39: - | AE39: - | AF39: 完了 | AG39: =IF(Y39="","","CLOSE") -> CLOSE | AH39: =IF(E39="","",IF(COUNTIF(Z39:AE39,"未")=0,"CLOSE","")) -> CLOSE | AI39: =COUNTIF(Z39:AF39,"完了")/COUNTIF(R39:X39,"要") -> 1
A40: =A39+1 -> 1434 | B40: 41875 | C40: 高砂 | D40: TAS | E40: 三路 | F40: 機械系 | G40: 紙巻機 | H40: ADT以外 | I40: 異常報告書（中文）共有フォルダ\201408以降\20140824GUT GUT3紙機送紙偏移異常.xls | K40: 因出紙皮帶Servo Amp（過負荷）而發生異常停止。確認驅動部時發現馬達温度異常升高。 | L40: 確認到№1、№7 皮帶（兩端）偏移並接觸到側邊的護蓋、引起馬達過負載。 | M40: 與設技檢討中 | N40: 初回 | O40: 160 | P40: 2697 | R40: - | S40: - | T40: - | U40: 要 | V40: 要 | W40: 要 | X40: - | Y40: 進行異常報告書的互閱，並針對紙排出Belt的伺服有過負荷異常時及紙有傾斜被捲的状況時，教育現場人員可能是送紙Belt發生偏移。 | Z40: - | AA40: - | AB40: - | AC40: 完了 | AD40: 完了 | AE40: 完了 | AF40: - | AG40: =IF(Y40="","","CLOSE") -> CLOSE | AH40: =IF(E40="","",IF(COUNTIF(Z40:AE40,"未")=0,"CLOSE","")) -> CLOSE | AI40: =COUNTIF(Z40:AF40,"完了")/COUNTIF(R40:X40,"要") -> 1
A41: =A40+1 -> 1435 | B41: 41877 | C41: AFK | D41: TAS | E41: 三路 | F41: 電氣系 | G41: 移載設備 | H41: ADT以外 | I41: 異常報告書（中文）共有フォルダ\201408以降\20140826GUT OFF切3上流移載機異常.xls | K41: 中班在進行事前準備時, 進行設備運轉, 並投入刮傷檢查用的樣品, 此時, 上流側№1移載機（Master、Slave兩者）Servo發生異常無法復歸, 因此呼出設技（電氣T）。 | L41: 計畫於OFF切№1～№3『搬送C/V相關參數變更』並進行作業。由於OFF切№1及2是在生産中實施的, 變更後也無設備上的異常。原本打算№3也同様要重寫『搬送C/V參數』,但是誤操作變更了上流№1移載機（Splave側）的參數。此重寫作業並未事先聯絡製造, 另外因為產線計畫停止中,所以沒有確認動作就結束此作業。 | M41: 因為PLC Soft裡面有同様的回路, 導致誤操作, 變更了移載機的參數, 為了防止弄錯 軸No.的位置, 會直接在PLC Soft内進行軸№表示以防止失誤。 | N41: 初回 | O41: 0 | P41: 0 | R41: 情報 | S41: 情報 | T41: 情報 | U41: 情報 | V41: 情報 | W41: 情報 | X41: 要 | Y41: Soft變更時製造的立會及不要忘記聯絡的事項，已向ADT設技再次依賴完畢。 | Z41: - | AA41: - | AB41: - | AC41: - | AD41: - | AE41: - | AF41: 完了 | AG41: =IF(Y41="","","CLOSE") -> CLOSE | AH41: =IF(E41="","",IF(COUNTIF(Z41:AE41,"未")=0,"CLOSE","")) -> CLOSE | AI41: =COUNTIF(Z41:AF41,"完了")/COUNTIF(R41:X41,"要") -> 1
A42: =A41+1 -> 1436 | B42: 41894 | C42: 高砂 | D42: TAS | E42: 三路 | F42: 機械系 | G42: 移載設備 | H42: ADT以外 | I42: 異常報告書（中文）共有フォルダ\201408以降\20140912 WIT1 上流移載機旋回異常.xls | J42: 異常報告書（中文）共有フォルダ\201408以降\TAS 自動線移載機固定螺絲寫真及OFF原點標示寫真.xlsx | K42: G8→G7.5JC之後, 上流移載機發生吸著異常。在無板裂、基板亦無異常的狀態下, 移載機旋回之後, 未停在原本應該停止的位置上確認過旋回位置的指令之後, 「90度」的設定沒有問題, 但是旋回不足, 只有回轉了約87度左右 | L42: 原因不明 | M42: 強調mark標示方式, 即使從旋回部的安全柵外面也可看到旋回位置並定時確認 （每小時） | N42: 初回 | O42: 60 | P42: 1086 | R42: - | S42: - | T42: - | U42: - | V42: - | W42: 要 | X42: - | Y42: 雖然原因不明，但要確認Robot Hand裝設處是否有Mark標示。 | Z42: - | AA42: - | AB42: - | AC42: - | AD42: - | AE42: 完了 | AF42: - | AG42: =IF(Y42="","","CLOSE") -> CLOSE | AH42: =IF(E42="","",IF(COUNTIF(Z42:AE42,"未")=0,"CLOSE","")) -> CLOSE | AI42: =COUNTIF(Z42:AF42,"完了")/COUNTIF(R42:X42,"要") -> 1
A43: =A42+1 -> 1437 | B43: 41890 | C43: 高砂 | D43: GF | E43: 三路 | F43: 機械系 | G43: 循環 | H43: ADT以外 | I43: O:\00 製造一部共通\横展開確認\設備異常報告\異常報告書(中文)\201408以降\20140908GF No.2循環CV(Crusher前)Pully Shaft斷裂.xls | K43: 循環巡檢時，發現#2CV Tail pully的Shaft斷裂狀況下在進行C/V回転。利用設技(工作)呼出対応進行予備Pully的更換 | L43: 推測是Belt張力過緊造成疲乏破壊。 | M43: Belt張力調整一斉做修正及實施Shaft和Drum接合部分的目視点検。 但是此次断裂的部分是Drum内部，所以無法做同一處的点検，因此變成只點檢外側。 | N43: 初回 | O43: 0 | P43: 0 | R43: 要 | S43: 要 | T43: 要 | U43: 要 | V43: 要 | W43: - | X43: - | Y43: ・在工事日等點檢各Belt的張力是否過緊。 | Z43: 完了 | AA43: 完了 | AB43: 完了 | AC43: 完了 | AD43: 完了 | AE43: - | AF43: - | AG43: =IF(Y43="","","CLOSE") -> CLOSE | AH43: =IF(E43="","",IF(COUNTIF(Z43:AE43,"未")=0,"CLOSE","")) -> CLOSE | AI43: =COUNTIF(Z43:AF43,"完了")/COUNTIF(R43:X43,"要") -> 1
A44: =A43+1 -> 1438 | B44: 41906 | C44: ADT | D44: ZF | E44: 佐倉 | F44: 機械系 | G44: 横切り機 | H44: ADT内対応 | I44: ー | K44: BUR Base上裝設的螺母鬆脫掉下。 | L44: 有裝上Nord-Lock washers但鬆脫。原因不明 | M44: 実施鎖緊。 | N44: 初回 | O44: 0 | P44: 0 | R44: - | S44: 要 | T44: 要 | U44: - | V44: 要 | W44: - | X44: - | Y44: 確認是否鬆脫及鎖緊 | Z44: - | AA44: 完了 | AB44: 完了 | AC44: - | AD44: 完了 | AE44: - | AF44: - | AG44: =IF(Y44="","","CLOSE") -> CLOSE | AH44: =IF(E44="","",IF(COUNTIF(Z44:AE44,"未")=0,"CLOSE","")) -> CLOSE | AI44: =COUNTIF(Z44:AF44,"完了")/COUNTIF(R44:X44,"要") -> 1
A45: =A44+1 -> 1439 | B45: 41895 | C45: 高砂 | D45: GF | E45: 鄭吉勝 | F45: 機械系 | G45: A/K | H45: ADT以外 | I45: 異常報告書（中文）共有フォルダ\201408以降\20140913GF B-LINE洗淨機風刀INV異常-1.xls | K45: 9/2工事日針對上一回發生的INV異常對策, 由設技進行O/H (Overhaul)的Blower馬達更換，9/13 00:00巡檢時確認到Blower馬達的異音變大，04:55INV異常警報發出, Line停止。 | L45: INV馬達的Impeller (葉片)和Casing的間距調整不足實施O/H (Overhaul)作業時, 用來調整間距的Liner墊片不見了, 所以未經過適當的間距調整（一般設定在1mm左右的間距）。再加上只有O/H作業經歷比較淺的作業者所實施。 | M45: 1.針對本Blower的Overhaul翻修對象零件及其整備要件加以明確化製作整備手順書。 2.向設技(工作)人員針對此異常內容宣導並教育。 3.如果作業人員對於這項整備作業的經驗較淺, 需由主任指示, 與更有經驗的人員一同作業。 | N45: 再発 | O45: 235 | P45: 147 | R45: 情報 | S45: 情報 | T45: 情報 | U45: 情報 | V45: 情報 | W45: 情報 | X45: 情報 | Y45: 設備技術O/H (Overhaul)翻修過必須再一次確認安裝後有無異常聲音及奇怪的地方 | Z45: - | AA45: - | AB45: - | AC45: - | AD45: - | AE45: - | AF45: - | AG45: =IF(Y45="","","CLOSE") -> CLOSE | AH45: =IF(E45="","",IF(COUNTIF(Z45:AE45,"未")=0,"CLOSE","")) -> CLOSE | AI45: =COUNTIF(Z45:AF45,"完了")/COUNTIF(R45:X45,"要") -> #DIV/0!
A46: =A45+1 -> 1440 | B46: 41900 | C46: 高砂 | D46: GF | E46: 鄭吉勝 | F46: 電氣系 | G46: PAM | H46: ADT以外 | I46: 異常報告書（中文）共有フォルダ\201408以降\20140918GF TOM3-PAM通信異常.xls | K46: TOM3檢查機PAM通信異常 | L46: ・PAM精査ServerCPU故障 最近GF出現TOM3 WI PAM TOM3 PAM通信異常散發，但是每次會自動復歸 or 重新啟動 HOSTPC、識別PC、畫處PC就能復歸。 ・設技調查後原因不明。 2014/9/2工事日重新啟動PAM精査Server之後, 就沒有再發生過了, 很可能是PAM精査Server故障的前兆。 | M46: ・PAM精査Server故障時的預防對策, 進行了預備PAM精査Server的精査T/P 面板的設定。(因為只要變更Server, 設定就會出現Default。) | N46: 初回 | O46: 170 | P46: 311 | R46: 情報 | S46: 情報 | T46: 情報 | U46: 情報 | V46: 情報 | W46: 情報 | X46: 情報 | Y46: ・為硬體上的故障, Server必須要有預備機 ・TOM3精査設定畫面資料保存（生產推進課） | Z46: - | AA46: - | AB46: - | AC46: - | AD46: - | AE46: - | AF46: - | AG46: =IF(Y46="","","CLOSE") -> CLOSE | AH46: =IF(E46="","",IF(COUNTIF(Z46:AE46,"未")=0,"CLOSE","")) -> CLOSE | AI46: =COUNTIF(Z46:AF46,"完了")/COUNTIF(R46:X46,"要") -> #DIV/0!
A47: =A46+1 -> 1441 | B47: 41919 | C47: ADT | D47: EF | E47: 万代 | F47: 機械系 | G47: C/V | H47: 他拠点報告 | I47: 異常報告書（中文）共有フォルダ\201408以降\20141007EF 2Br引込CVﾁｪｰﾝ（ｾﾝｻｰ検出ﾌﾟﾚｰﾄ部ｼﾞｮｲﾝﾄﾋﾟﾝ）折損.xls | K47: 2Br引入C/V3?條（Senser檢出Plate部Joint Pin）折損 | L47: 但此折損處的鍊條、Joint Pin, 自從EF建設（2007年）以後為期7年內完全沒有更換過。 | M47: 定期於每次冷修進行更換。針對鍊條生鏽、潤滑油乾掉、震動等狀況 可能會導致 鍊條斷裂的危險性進行教育訓練。 | N47: 初回 | O47: 10 | P47: 257 | R47: 情報 | S47: 要 | T47: 要 | U47: 情報 | V47: 情報 | W47: - | X47: - | Y47: 確認於每次冷修進行更換。確保予備品。 | Z47: - | AA47: 完了 | AB47: 完了 | AC47: - | AD47: - | AE47: - | AF47: - | AG47: =IF(Y47="","","CLOSE") -> CLOSE | AH47: =IF(E47="","",IF(COUNTIF(Z47:AE47,"未")=0,"CLOSE","")) -> CLOSE | AI47: =COUNTIF(Z47:AF47,"完了")/COUNTIF(R47:X47,"要") -> 1
A48: =A47+1 -> 1442 | B48: 41914 | C48: AFK | D48: IF | E48: 鄭吉勝 | F48: 檢查系 | G48: TOM3 | H48: ADT以外 | I48: 異常報告書（中文）共有フォルダ\201408以降\20141002IF TOM3畫像處理PC當機散發異常.xls | K48: TOM3画像処理PC Freeze散発異常 | L48: 6chBOX異常的可能性很高 | M48: 因為還未掌握到確切的原因, 預定下回工事日將拆下來的6chBOX連接到目前未使用的NET外的畫像處理PC, 以確認並重現當時的現象 | N48: 初回 | O48: 0 | P48: 136 | R48: 情報 | S48: 情報 | T48: 情報 | U48: 情報 | V48: 情報 | W48: - | X48: - | Y48: 待ENG原因調查及再現性確認 | Z48: - | AA48: - | AB48: - | AC48: - | AD48: - | AE48: - | AF48: - | AG48: =IF(Y48="","","CLOSE") -> CLOSE | AH48: =IF(E48="","",IF(COUNTIF(Z48:AE48,"未")=0,"CLOSE","")) -> CLOSE | AI48: =COUNTIF(Z48:AF48,"完了")/COUNTIF(R48:X48,"要") -> #DIV/0!
A49: =A48+1 -> 1443 | B49: 41916 | C49: AFK | D49: FF | E49: 三路 | F49: 檢查系 | G49: WI | H49: ADT以外 | I49: 異常報告書（中文）共有フォルダ\201408以降\20141008_AFK_FF_WI検査機#15Camera異常.xls | K49: ・発生SP-RANK「T」。#15 CAMERA光量波形變異常高的状態。 | L49: ・原因不明 | M49: ・由於原因不明所以沒有対策。 | N49: 初回 | O49: 0 | P49: 0 | R49: 情報 | S49: 情報 | T49: 情報 | U49: 情報 | V49: 情報 | W49: - | X49: - | Y49: ・情報共有 ※發生同様事例時，希望能夠利用纜線更換等來找出原因處。 | Z49: - | AA49: - | AB49: - | AC49: - | AD49: - | AE49: - | AF49: - | AG49: =IF(Y49="","","CLOSE") -> CLOSE | AH49: =IF(E49="","",IF(COUNTIF(Z49:AE49,"未")=0,"CLOSE","")) -> CLOSE | AI49: =COUNTIF(Z49:AF49,"完了")/COUNTIF(R49:X49,"要") -> #DIV/0!
A50: =A49+1 -> 1444 | B50: 41925 | C50: AFK | D50: HF | E50: 三路 | F50: 電氣系 | G50: 反転設備 | H50: ADT以外 | I50: 異常報告書（中文）共有フォルダ\201408以降\20141012 HF 2Br反轉移載Robot停止 疑似Servo Encorder異常.xls | K50: ・Robot Pendant Controller零星發生「1326:R軸編碼器絕對異常」。更換R軸的伺服馬達後就無異常。 | L50: ・推測因經年劣化造成伺服馬達的編碼器異常。 | M50: ・更換伺服馬達 ※再発時予定更換機内的Harness。 | N50: 初回 | O50: 0 | P50: 0 | R50: 情報 | S50: 情報 | T50: 情報 | U50: 情報 | V50: 情報 | W50: 情報 | X50: - | Y50: ・情報共有。 ※在Robot異常発生時能夠先行實施異常内容的確認。 | Z50: - | AA50: - | AB50: - | AC50: - | AD50: - | AE50: - | AF50: - | AG50: =IF(Y50="","","CLOSE") -> CLOSE | AH50: =IF(E50="","",IF(COUNTIF(Z50:AE50,"未")=0,"CLOSE","")) -> CLOSE | AI50: =COUNTIF(Z50:AF50,"完了")/COUNTIF(R50:X50,"要") -> #DIV/0!
A51: =A50+1 -> 1445 | B51: 41920 | C51: 高砂 | D51: TAS | E51: 三路 | F51: 電氣系 | G51: 採板設備 | H51: ADT以外 | I51: 異常報告書（中文）共有フォルダ\201408以降\20141008 WIT NO1 Robot採板機衝突破損.xlsx | K51: ・定修後第1枚基板積載至PL時，Robot-Hand和PL碰撞造成Hand破損。 | L51: ・使用Pendant Controller來操作Robot時，錯將T軸的補正値寫入。 | M51: ・實施T軸補正値不會被代入的程式変更。 | N51: 初回 | O51: 0 | P51: 0 | R51: 情報 | S51: 情報 | T51: 情報 | U51: 情報 | V51: 情報 | W51: 要 | X51: - | Y51: ・情報共有。 ※製造不使用Pendant Controller來進行操作，但在電気G等操作後有必要以低速模式等來確認是否正常的作動。 | Z51: - | AA51: - | AB51: - | AC51: - | AD51: - | AE51: 完了 | AF51: - | AG51: =IF(Y51="","","CLOSE") -> CLOSE | AH51: =IF(E51="","",IF(COUNTIF(Z51:AE51,"未")=0,"CLOSE","")) -> CLOSE | AI51: =COUNTIF(Z51:AF51,"完了")/COUNTIF(R51:X51,"要") -> 1
A52: =A51+1 -> 1446 | B52: 41924 | C52: 高砂 | D52: GF | E52: 三路 | F52: 機械系 | G52: H/O | H52: ADT以外 | I52: 異常報告書（中文）共有フォルダ\201408以降\20141012GF 本線GateCV開閉動作異常.xlsx | J52: O:\00 製造一部共通\横展開確認\設備異常報告\異常報告書(日文)\201408以降\本線HO油圧関係資料 | K52: ・H/O GATE的動作異常。在「開」的状態下停止。 | L52: ・因作動油内的汚染物質，引起Pilot Check閥的作動不良。 | M52: ・更換作動油。 ・電磁閥unit的定期更換。 （電磁閥、切替閥、Check閥、流動控制閥） ・在電磁閥unit裝設圧力計。 | N52: 初回 | O52: 195 | P52: 4012 | R52: 要 | S52: 要 | T52: 要 | U52: 要 | V52: 要 | W52: - | X52: - | Y52: ・在電磁閥unit裝設圧力計，較易特定出異常発生源。 ※ADT電磁閥定期更換規定 ★電磁閥unit的定期更換，基本上在每次冷修時實施。 發生不具合時就更換。即使更換也無法改善時就更換作動油。 | Z52: 完了 | AA52: 完了 | AB52: 完了 | AC52: 完了 | AD52: 完了 | AE52: - | AF52: - | AG52: =IF(Y52="","","CLOSE") -> CLOSE | AH52: =IF(E52="","",IF(COUNTIF(Z52:AE52,"未")=0,"CLOSE","")) -> CLOSE | AI52: =COUNTIF(Z52:AF52,"完了")/COUNTIF(R52:X52,"要") -> 1 | AJ52: →4月/Eまでクローズできないのか？いつやる？忘れないのか？誰が責任もって進捗管理するのか？ →YZはタイプが異なるため、高谷さんと相談します。 →JFは冷修対応(指摘修繕計畫列入)一時CLOSE
A53: =A52+1 -> 1447 | B53: 41929 | C53: 高砂 | D53: TAS | E53: 三路 | F53: 機械系 | G53: 投入ラクラクハンド | H53: ADT以外 | I53: O:\00 製造一部共通\横展開確認\設備異常報告\異常報告書(中文)\201408以降\20141017 WIT1樂樂手Trouble.xls | K53: ・真空Pump吐出口的消音器發生堵塞，造成Thermal trip。 | L53: ・Carbon plate的磨耗粉造成消音器的堵塞。 | M53: ・以拆下消音器做為応急処置。 | N53: 初回 | O53: 120 | P53: 2768 | R53: 情報 | S53: - | T53: - | U53: 要 | V53: 要 | W53: 要 | X53: 要 | Y53: ・在實施樂樂手真空Pump維修保養時，也一併更換消音器。 ※R/B的真空Pump是被設置在安全柵欄外側，經判斷無品質的疑慮所以不做横展開。 | Z53: - | AA53: - | AB53: - | AC53: 完了 | AD53: 完了 | AE53: 完了 | AF53: 完了 | AG53: =IF(Y53="","","CLOSE") -> CLOSE | AH53: =IF(E53="","",IF(COUNTIF(Z53:AE53,"未")=0,"CLOSE","")) -> CLOSE | AI53: =COUNTIF(Z53:AF53,"完了")/COUNTIF(R53:X53,"要") -> 1
A54: =A53+1 -> 1448 | B54: 41930 | C54: 高砂 | D54: GF | E54: 三路 | F54: 檢查系 | G54: TOM3 | H54: ADT以外 | I54: 異常報告書（中文）共有フォルダ\201408以降\20141018GF TOM3画処PC故障.xls | K54: #19画素PC的電源低下，検査該部位做捨板。 | L54: ・推定是PC電源unit的故障。 | M54: ・接收電源unit故障原因的結果並検討。發生同樣事例時馬上進行PC的更換。 | N54: 初回 | O54: 80 | P54: 66 | R54: 情報 | S54: 情報 | T54: 情報 | U54: 情報 | V54: 情報 | W54: - | X54: - | Y54: 情報共有 | Z54: - | AA54: - | AB54: - | AC54: - | AD54: - | AE54: - | AF54: - | AG54: =IF(Y54="","","CLOSE") -> CLOSE | AH54: =IF(E54="","",IF(COUNTIF(Z54:AE54,"未")=0,"CLOSE","")) -> CLOSE | AI54: =COUNTIF(Z54:AF54,"完了")/COUNTIF(R54:X54,"要") -> #DIV/0!
A55: =A54+1 -> 1449 | B55: 41932 | C55: 高砂 | D55: GF | E55: 三路 | F55: 電氣系 | G55: 検査機光源的電源Plug | H55: ADT以外 | I55: 異常報告書（中文）共有フォルダ\201408以降\20141021GF B-LINE泡検査機光源の電源プラグ焼損.xlsx | K55: ・泡検査機光源的電源plug和OA tap焼毀。 | L55: ・推定是被設置在装置裏面的排気口附近，而妨礙到plug的散熱。 ・針對Plug的額定13A，被確認了瞬間通過20A左右的電流。由此推定Plug被加熱而損壞。 | M55: ・將ＯＡ tap移設至不會接收到排気口熱風的位置。 ・更換為額定電流較大的電源Plug。 ・不使用ＯＡ tap而直接連接至電源。 | N55: 初回 | O55: 0 | P55: 0 | R55: 要 | S55: 要 | T55: 要 | U55: 要 | V55: 要 | W55: 要 | X55: - | Y55: ・確認ＯＡ tap和電源Plug是否有熱損傷。 | Z55: 完了 | AA55: 完了 | AB55: 完了 | AC55: 完了 | AD55: 完了 | AE55: 完了 | AF55: - | AG55: =IF(Y55="","","CLOSE") -> CLOSE | AH55: =IF(E55="","",IF(COUNTIF(Z55:AE55,"未")=0,"CLOSE","")) -> CLOSE | AI55: =COUNTIF(Z55:AF55,"完了")/COUNTIF(R55:X55,"要") -> 1
A56: =A55+1 -> 1450 | B56: 41935 | C56: AFK | D56: IF | E56: 鄭吉勝 | F56: 機械系 | G56: SMAP | H56: ADT以外 | I56: 異常報告書（中文）共有フォルダ\201408以降\20141023IF 本線SMAP R側アーム開閉異常.xlsx | K56: 本線SMAP R側ARM開閉動作異常 | L56: ・由於Jacky Bolt鬆脫 （冷修時應該沒有進行増締確認）、導致Bracket的設定位置並未被完全固定。因此，推測在每次ARM動作時（Pully被皮帶拉扯），Bracket的固定螺絲負荷增大，導致螺絲出現疲勞破壞的狀況。 | M56: 針對Jacky Bolt、Bracket固定螺絲旋緊狀況進行點檢。 | N56: 初回 | O56: 92 | P56: 335 | R56: 要 | S56: 要 | T56: 要 | U56: 要 | V56: 要 | W56: - | X56: - | Y56: 針對Jacky Bolt、Bracket固定螺絲旋緊狀況進行點檢。 | Z56: 完了 | AA56: 完了 | AB56: 完了 | AC56: 完了 | AD56: 完了 | AE56: - | AF56: - | AG56: =IF(Y56="","","CLOSE") -> CLOSE | AH56: =IF(E56="","",IF(COUNTIF(Z56:AE56,"未")=0,"CLOSE","")) -> CLOSE | AI56: =COUNTIF(Z56:AF56,"完了")/COUNTIF(R56:X56,"要") -> 1 | AJ56: →4月/Eまでクローズできないのか？いつやる？忘れないのか？ →JF/冷修対応
A57: =A56+1 -> 1451 | B57: 41944 | C57: AFK | D57: TAS | E57: 三路 | F57: 機械系 | G57: 投入採板機 | H57: ADT以外 | I57: 異常報告書（中文）共有フォルダ\201408以降\20141101GUT GUT№1投入採板機減速機異常.xls | K57: ・因伺服馬達過負載而停止。 | L57: ・因為減速機的NEEDLE BEARING（滾針軸承）破損。 | M57: ・計画（1回/4年）實施定期更換 | N57: 再発 | O57: 267 | P57: 2622 | R57: 情報 | S57: 情報 | T57: 情報 | U57: 情報 | V57: 情報 | W57: 要 | X57: - | Y57: ・雖然ADT也有相同類型的投入採板機，但由於現在中止使用，所以只做情報共有之用。 | Z57: - | AA57: - | AB57: - | AC57: - | AD57: - | AE57: 完了 | AF57: - | AG57: =IF(Y57="","","CLOSE") -> CLOSE | AH57: =IF(E57="","",IF(COUNTIF(Z57:AE57,"未")=0,"CLOSE","")) -> CLOSE | AI57: =COUNTIF(Z57:AF57,"完了")/COUNTIF(R57:X57,"要") -> 1
A58: =A57+1 -> 1452 | B58: 41968 | C58: 高砂 | D58: BF | E58: 三路 | F58: 機械系 | G58: P詰め機 | H58: ADT以外 | I58: 異常報告書（中文）共有フォルダ\201408以降\20141125BF BDS P詰機サーボ駆動カップリング部締結不良.xlsx | K58: ・P包裝機往PL側走行中撞到PL。 | L58: ・伺服馬達和滾珠螺桿間的連軸器鬆脫，推測是因自体重量往PL側滑動。 ※走行用的滾珠螺桿不是水平而是往PL側傾斜設置。 | M58: ・連軸器、集電環處的鎖緊。 | N58: 初回 | O58: 450 | P58: 444 | R58: 要 | S58: 要 | T58: 要 | U58: - | V58: - | W58: - | X58: - | Y58: ・点検連軸器是否有鬆脫。 | Z58: 完了 | AA58: 完了 | AB58: 完了 | AC58: - | AD58: - | AE58: - | AF58: - | AG58: =IF(Y58="","","CLOSE") -> CLOSE | AH58: =IF(E58="","",IF(COUNTIF(Z58:AE58,"未")=0,"CLOSE","")) -> CLOSE | AI58: =COUNTIF(Z58:AF58,"完了")/COUNTIF(R58:X58,"要") -> 1
A59: =A58+1 -> 1453 | B59: 41968 | C59: AFK | D59: DF | E59: 三路 | F59: 電氣系 | G59: SMAP | H59: ADT以外 | I59: 異常報告書（中文）共有フォルダ\201408以降\20141125_AFK_DF_SMAP・伸縮CV衝突.xls | J59: 異常報告書（日文）共有フォルダ\其他\本線伸縮CV段OP SOFT調整.xlsx | K59: ・由於在Bath窓玻璃採板中（NET120"）是以ACE來測試NET180"的切出，所以伸縮C/V實施毎葉J/C而撞到SMAP，造成滾珠螺桿和離合器破損。 | L59: ・作業人員的教育不足 ・設備上無互鎖機制。 | M59: ・硬體面上互鎖機制的追加目前検討中 ・在軟體内設置互鎖機制來應急。 ※改造成任意値以上的JC動作無法執行。 | N59: 初回 | O59: 0 | P59: 0 | R59: - | S59: 要 | T59: 要 | U59: 要 | V59: 要 | W59: - | X59: - | Y59: ・追加硬體面上的互鎖機制（ADTとしての方針は12/10に決定） 現在AFKのハード的改造部分、返事待ち（12/19現在） | Z59: - | AA59: 完了 | AB59: 完了 | AC59: 完了 | AD59: 完了 | AE59: - | AF59: - | AG59: =IF(Y59="","","CLOSE") -> CLOSE | AH59: =IF(E59="","",IF(COUNTIF(Z59:AE59,"未")=0,"CLOSE","")) -> CLOSE | AI59: =COUNTIF(Z59:AF59,"完了")/COUNTIF(R59:X59,"要") -> 1 | AJ59: →いつまでに電気に方針決めてもらうの？ →ソフト面は方針決定しました。T/Pにｲﾝﾀｰﾛｯｸいれます。（電気とテスト等含めた日程調整必要） ⇒現在、電気/金子氏とスケジューリング中
A60: =A59+1 -> 1454 | B60: 41974 | C60: 高砂 | D60: TAS | E60: 鄭吉勝 | F60: 機械系 | G60: 洗浄機 | H60: ADT以外 | I60: 異常報告書（中文）共有フォルダ\201408以降\20141201WIT1 洗浄機前洗駆動シャフトスプロケットキー抜け.xls | K60: 洗淨機前洗驅動Shaft_Sprocket_Key脫落 | L60: ・驅動Shaft Shaft & Pin 因老化劣化而摩耗、再加上磨耗所引起的固定螺絲鬆脫所致 | M60: 更換該驅動Shaft | N60: 初回 | O60: 192 | P60: 4339 | R60: - | S60: - | T60: - | U60: 要 | V60: 要 | W60: 要 | X60: 要 | Y60: ・針對洗淨機所有部位的驅動Shaft Sprocket進行點檢 | Z60: - | AA60: - | AB60: - | AC60: 完了 | AD60: 完了 | AE60: 完了 | AF60: 完了 | AG60: =IF(Y60="","","CLOSE") -> CLOSE | AH60: =IF(E60="","",IF(COUNTIF(Z60:AE60,"未")=0,"CLOSE","")) -> CLOSE | AI60: =COUNTIF(Z60:AF60,"完了")/COUNTIF(R60:X60,"要") -> 1
A61: =A60+1 -> 1455 | B61: 41991 | C61: 高砂 | D61: OFF切 | E61: 鄭吉勝 | F61: 機械系 | G61: A/K | H61: ADT以外 | I61: 異常報告書（中文）共有フォルダ\201408以降\20141218TDS2 AKブロワーダクトホース破損.xlsx | K61: AK Blower Duct Hose破損 | L61: 推測經過長期受熱硬化，受到使用時的壓力及震動影響，才會從Duct連結部位發生破裂。 該Duct Hose查無更換履歷，稼働年數已超過6年以上。Duct Hose 為東拓工業製的耐熱仕様（～80℃），但素材為EPDM（合成橡膠），有可能是因硬化導致破裂。 | M61: ①點檢項目追加該Duct Hose連結部位的目視點檢 ②其他Line針對同樣設備的Duct Hose進行更新 | N61: 初回 | O61: 159 | P61: 570 | R61: - | S61: - | T61: - | U61: 要 | V61: 要 | W61: 要 | X61: 要 | Y61: ①Blower裝置的Duct Hose目視點檢 ②Blower裝置的Duct Hose預備品準備 | Z61: - | AA61: - | AB61: - | AC61: 完了 | AD61: 完了 | AE61: 完了 | AF61: 完了 | AG61: =IF(Y61="","","CLOSE") -> CLOSE | AH61: =IF(E61="","",IF(COUNTIF(Z61:AE61,"未")=0,"CLOSE","")) -> CLOSE | AI61: =COUNTIF(Z61:AF61,"完了")/COUNTIF(R61:X61,"要") -> 1
A62: =A61+1 -> 1456 | B62: 41995 | C62: AFK | D62: IF | E62: 三路 | F62: 機械系 | G62: 紙巻機 | H62: ADT以外 | I62: 異常報告書（中文）共有フォルダ\201408以降\20141219IF 1Br IZUMI 製紙巻機紙出紙皮帶CV驅動聯軸器板彈簧損壞.xlsx | K62: 紙排出ベルトサーボモーターカップリングのディスクが破損しサーボ異常となった。 | L62: ・経年劣化？ | M62: ・カップリング部の定期点検の実施。定期交換の検討。 | N62: 初回 | O62: 3 | P62: 79 | R62: - | S62: - | T62: - | U62: 要 | V62: 要 | W62: 要 | X62: - | Y62: 現状、ADTでは１回/週のパトロール時にカップリング点検を実施しており、その際にディスクの変形や割れなどが発見された場合、交換を実施する方針である。 ※パトロール＝設技機械による週末点検にて実施。チェック項目も有り。 | Z62: - | AA62: - | AB62: - | AC62: 完了 | AD62: 完了 | AE62: 完了 | AF62: - | AG62: =IF(Y62="","","CLOSE") -> CLOSE | AH62: =IF(E62="","",IF(COUNTIF(Z62:AE62,"未")=0,"CLOSE","")) -> CLOSE | AI62: =COUNTIF(Z62:AF62,"完了")/COUNTIF(R62:X62,"要") -> 1
A63: =A62+1 -> 1457 | B63: 42008 | C63: AFK | D63: LF | E63: 蔵光 | F63: 機械系 | G63: H/O | H63: ADT以外 | I63: 異常報告書（中文）共有フォルダ\201501以降\20150104 LF 本線Gate_Hopper_CYL動作不良.xlsx | K63: ホッパーを開閉するシリンダーのベース部分の溶接が破損 | L63: ・シリンダーロッドとIジョイント連結部分のネジの緩みがあった。 | M63: ・シリンダーロッドとIジョイント部分に緩み止めの施工を実施する。（KF) ⇒ADTとは機構が違うため、情報として扱う | N63: 初回 | O63: 240 | P63: 5025 | R63: 要 | S63: 要 | T63: 要 | U63: 要 | V63: 要 | W63: - | X63: - | Y63: まずは工事日に点検を行ってください。 | Z63: 完了 | AA63: 完了 | AB63: 完了 | AC63: 完了 | AD63: 完了 | AE63: - | AF63: - | AG63: =IF(Y63="","","CLOSE") -> CLOSE | AH63: =IF(E63="","",IF(COUNTIF(Z63:AE63,"未")=0,"CLOSE","")) -> CLOSE | AI63: =COUNTIF(Z63:AF63,"完了")/COUNTIF(R63:X63,"要") -> 1
A64: =A63+1 -> 1458 | B64: 42019 | C64: AFK | D64: TAS | E64: 蔵光 | F64: 機械系 | G64: 洗浄機 | H64: ADT以外 | I64: \\172.18.154.189\mfg_public\00 製造一部共通\横展開確認\設備異常報告\異常報告書(中文)\201501以降\20150115_AFK_GUT_アライメントタイムオーバー.xls | K64: 洗浄3ラインNGマーキング前アライメント タイムオーバー発生 | L64: ・経年劣化？（AFK調査中） | M64: ・定期交換実施予定(2年周期) ・予備品の準備 | N64: 初回 | O64: 110 | P64: 2400 | R64: - | S64: - | T64: - | U64: - | V64: - | W64: 要 | X64: 要 | Y64: 定期交換の頻度は？ 予備品はあるか？ | Z64: - | AA64: - | AB64: - | AC64: - | AD64: - | AE64: 完了 | AF64: 完了 | AG64: =IF(Y64="","","CLOSE") -> CLOSE | AH64: =IF(E64="","",IF(COUNTIF(Z64:AE64,"未")=0,"CLOSE","")) -> CLOSE | AI64: =COUNTIF(Z64:AF64,"完了")/COUNTIF(R64:X64,"要") -> 1
A65: =A64+1 -> 1459 | B65: 42020 | C65: 高砂 | D65: GF | E65: 蔵光 | F65: 系統系 | G65: 泡検査器 | H65: ADT以外 | I65: 異常報告書（中文）共有フォルダ\201501以降\20150116GF A-LINE泡検査機ソフト不具合.xlsx | K65: 泡検査機光源メタルハライドランプ寿命により消灯。 ※該当光源は警報閾値下回るも警報発生せず。 | L65: ・泡検査機ソフト不具合 (2008年建設時からの問題) | M65: ・泡検査機ソフト修正 ※LOSSEVに不具合修正依頼 | N65: 初回 | O65: 120 | P65: 0 | R65: - | S65: - | T65: - | U65: - | V65: - | W65: 要 | X65: - | Y65: ソフトに不具合があるのか確認必要 | Z65: - | AA65: - | AB65: - | AC65: - | AD65: - | AE65: 完了 | AF65: - | AG65: =IF(Y65="","","CLOSE") -> CLOSE | AH65: =IF(E65="","",IF(COUNTIF(Z65:AE65,"未")=0,"CLOSE","")) -> CLOSE | AI65: =COUNTIF(Z65:AF65,"完了")/COUNTIF(R65:X65,"要") -> 1
A66: =A65+1 -> 1460 | B66: 42020 | C66: 高砂 | D66: TAS | E66: 蔵光 | F66: 機械系 | G66: 洗浄機 | H66: ADT以外 | I66: 異常報告書（中文）共有フォルダ\201501以降\20150116WIT1 洗浄機塩酸槽駆動シャフトカップリング破損.xlsx | K66: 塩酸槽駆動シャフトカップリング破損 | L66: ・Zr（ジルコニウム）製のカップリング本体とキーの摩耗 | M66: ・駆動シャフトのカップリング解体&摩耗具合確認実施 ・増し締めの作業標準書作成 | N66: 初回 | O66: 300 | P66: 7561 | R66: - | S66: - | T66: - | U66: 要 | V66: 要 | W66: 要 | X66: 要 | Y66: 増し締めの作業標準書の有無確認（？） | Z66: - | AA66: - | AB66: - | AC66: 完了 | AD66: 完了 | AE66: 完了 | AF66: 完了 | AG66: =IF(Y66="","","CLOSE") -> CLOSE | AH66: =IF(E66="","",IF(COUNTIF(Z66:AE66,"未")=0,"CLOSE","")) -> CLOSE | AI66: =COUNTIF(Z66:AF66,"完了")/COUNTIF(R66:X66,"要") -> 1
A67: =A66+1 -> 1461 | B67: 41983 | C67: 高砂 | D67: TAS | E67: 蔵光 | F67: 機械系 | G67: 投入ラクラクハンド | H67: ADT以外 | I67: 異常報告書（中文）共有フォルダ\201501以降\20141210WIT1 投入ラクラクハンド旋回ベアリング破損.xlsx | K67: 投入ラクラクハンドで旋回部のベアリングに異音/引っかかり有り | L67: ・ベアリング不具合 | M67: ・定期交換実施(1年) | N67: 初回 | O67: 120 | P67: 2712 | R67: - | S67: - | T67: - | U67: 情報 | V67: 情報 | W67: 要 | X67: 要 | Y67: 定期交換の頻度は？ | Z67: - | AA67: - | AB67: - | AC67: - | AD67: - | AE67: 完了 | AF67: 完了 | AG67: =IF(Y67="","","CLOSE") -> CLOSE | AH67: =IF(E67="","",IF(COUNTIF(Z67:AE67,"未")=0,"CLOSE","")) -> CLOSE | AI67: =COUNTIF(Z67:AF67,"完了")/COUNTIF(R67:X67,"要") -> 1
A68: =A67+1 -> 1462 | B68: 42038 | C68: AFK | D68: DF | E68: 蔵光 | F68: 機械系 | G68: P詰め機 | H68: ADT以外 | I68: ー | K68: G8パレットの落下 | L68: ・G8実パレットにG6を横桟側に採板しているため重心が底桟側へ偏った状態となり、PL払い出し中に底桟側から滑り落ちた後、原点移動する空パレット Trailerと衝突したと推定する。 | M68: ・G8パレットの全面を安定して受けられるように、実PL搬送TrailerのFrame長さ延長（100mm延長）及びMCナイロンプレート設置。 | N68: 初回 | O68: 0 | P68: 424 | R68: - | S68: 情報 | T68: 情報 | U68: 情報 | V68: 情報 | W68: 情報 | X68: - | Y68: Ｇ8パレットにＧ6を積む際はセンターに積むこと →ADTとして現状採板予定はないので情報としての扱い | Z68: - | AA68: - | AB68: - | AC68: - | AD68: - | AE68: - | AF68: - | AG68: =IF(Y68="","","CLOSE") -> CLOSE | AH68: =IF(E68="","",IF(COUNTIF(Z68:AE68,"未")=0,"CLOSE","")) -> CLOSE | AI68: =COUNTIF(Z68:AF68,"完了")/COUNTIF(R68:X68,"要") -> #DIV/0!
A69: =A68+1 -> 1463 | B69: 42032 | C69: AFK | D69: TAS | E69: 鄭吉勝 | F69: 機械系 | G69: 位置決め | H69: ADT以外 | I69: 異常報告書（中文）共有フォルダ\201501以降\20150128GUT1 FT位置決めアライメントサーボ異常.xlsx | K69: 自動採板機後の位置決FT Alignment Servo異常 | L69: . 稼動中無法定期確認Ball screw狀態。 . 外有Cover難以進行點檢 . 長時間使用導致Ball screw固定Nut鬆動 於作動中發生異音 | M69: . 定期確認作動狀態及異音 . 定修工事時進行給油並手動確認有無異常 . 確認Ball screw 固定Bolt及 Nut 兩者之間預留的縫隙大小 | N69: 初回 | O69: 62 | P69: 598 | R69: 情報 | S69: 情報 | T69: 情報 | U69: 要 | V69: 要 | W69: 要 | X69: 要 | Y69: 定期點檢 | Z69: - | AA69: - | AB69: - | AC69: 完了 | AD69: 完了 | AE69: 完了 | AF69: 完了 | AG69: =IF(Y69="","","CLOSE") -> CLOSE | AH69: =IF(E69="","",IF(COUNTIF(Z69:AE69,"未")=0,"CLOSE","")) -> CLOSE | AI69: =COUNTIF(Z69:AF69,"完了")/COUNTIF(R69:X69,"要") -> 1
A70: =A69+1 -> 1464 | B70: 42037 | C70: 高砂 | D70: BF | E70: 鄭吉勝 | F70: 機械系 | G70: SMAP | H70: ADT以外 | I70: 異常報告書（中文）共有フォルダ\201501以降\20150202BF 本線L側SMAPシリンダー内部リークによる動作不良.xlsx | K70: SMAP上昇之後高度自然下降，因為距離待機位置過低而與基板衝撞。於伸縮C/V上破板，先讓L側SMAP退避之後使用耳離。（R側則持續使用SMAP。） | L70: 由於SMAP上昇之後，待機位置的排氣側發生微量漏氣，推斷為内部洩漏。 | M70: 更換CYL交換之後，就不再出現動作不良的現象。這次的SMAP動作不良其實在1月後半段開始偶發，內部曾經討論過要在2/24工事日更換CYL對應。 | N70: 初回 | O70: 10 | P70: 588 | R70: 要 | S70: 要 | T70: 要 | U70: 要 | V70: 要 | W70: - | X70: - | Y70: SMAP シリンダーの解体点検 | Z70: 完了 | AA70: 完了 | AB70: 完了 | AC70: 完了 | AD70: 完了 | AE70: - | AF70: - | AG70: =IF(Y70="","","CLOSE") -> CLOSE | AH70: =IF(E70="","",IF(COUNTIF(Z70:AE70,"未")=0,"CLOSE","")) -> CLOSE | AI70: =COUNTIF(Z70:AF70,"完了")/COUNTIF(R70:X70,"要") -> 1
A71: =A70+1 -> 1465 | B71: 42056 | C71: ADT | D71: YF | E71: 鄭吉勝 | F71: 檢查系 | G71: TOM3 | H71: 他拠点報告 | I71: 異常報告書（中文）共有フォルダ\201501以降\20150221YF TOM3畫處PC2_Freeze故障報告.xlsx | K71: YF TOM 畫處PC#2 在02/21(春節期間)生產中，突然發生 PC Freeze 異常二回，第二回發生後便無法自動解除。 | L71: 從回收的 EventLog 來看，D磁碟有寫入延遲的記錄。 YF 11/08 瞬間停電，當時造成畫處PC共有5顆HDD毀損。 | M71: 更換HDD並Recovery資料。 | N71: 初回 | O71: 20 | P71: 0 | R71: 情報 | S71: 情報 | T71: 情報 | U71: 情報 | V71: 情報 | W71: - | X71: - | Y71: TOM3 畫處PC異常情報聯絡 | Z71: - | AA71: - | AB71: - | AC71: - | AD71: - | AE71: - | AF71: - | AG71: =IF(Y71="","","CLOSE") -> CLOSE | AH71: =IF(E71="","",IF(COUNTIF(Z71:AE71,"未")=0,"CLOSE","")) -> CLOSE | AI71: =COUNTIF(Z71:AF71,"完了")/COUNTIF(R71:X71,"要") -> #DIV/0!
... A89: =A88+1 -> 1483 | B89: 42228 | C89: AFK | D89: TAS | E89: 鄭吉勝 | F89: 電氣系 | G89: 採板設備 | H89: ADT以外 | I89: 異常報告書（中文）共有フォルダ\201501以降\20150812GUT2 ROBOT採板機CABLE斷線異常.xlsx | K89: 採板Robot Cable Pan(CD管內)斷線 | L89: ＜管理面＞ 該Robot的採板有2POS，#2 T/T採板頻度較少，因此未確實確認到左右的動作。 ＜設備面＞ 採板POS有２處，雖然左右的可動範圍大，但是Cable Pan 比其他Line還要小145mm，才會導致金屬軟管糾纏在一起。 | M89: ＜管理面＞ 以目視進行外觀點檢，但未設定Hose內部的點檢頻度，有必要時點檢。 ＜設備面＞ Cable Pan的部分變更為其他Line的580mmType（報價中） | N89: 初回 | O89: 130 | P89: 1441 | R89: 情報 | S89: 要 | T89: 要 | U89: 要 | V89: 要 | W89: 要 | X89: - | Y89: 針對採板ROBOT Cable Pan中的CD管配線進行點檢確認。 1. ROBOT Cable Pan的直徑大小 2. CD管內的Cable有無線路折損狀況 | Z89: - | AA89: 完了 | AB89: 完了 | AC89: 完了 | AD89: 完了 | AE89: 完了 | AF89: - | AG89: =IF(Y89="","","CLOSE") -> CLOSE | AH89: =IF(E89="","",IF(COUNTIF(Z89:AE89,"未")=0,"CLOSE","")) -> CLOSE | AI89: =COUNTIF(Z89:AF89,"完了")/COUNTIF(R89:X89,"要") -> 1
A90: =A89+1 -> 1484 | B90: 42285 | C90: 高砂 | D90: BF | E90: 鄭吉勝 | F90: 機械系 | G90: BDS | H90: ADT以外 | I90: 異常報告書（中文）共有フォルダ\201501以降\20151008 BF BDS軸受架台溶接部亀裂.xls | J90: 異常報告書（中文）共有フォルダ\201501以降\★BDS軸受架台溶接部亀裂橫展開確認DATA | K90: BDS 軸受架台焊接部位亀裂 | L90: BF2Br的BDS在搬運玻璃待機時，整個ARM發生搖晃的狀況。 焊接部位的疲勞破壞 | M90: 利用補強PLATE進行重新焊接 | N90: 初回 | O90: 0 | P90: 0 | R90: 要 | S90: 要 | T90: 要 | U90: 要 | V90: 要 | W90: - | X90: - | Y90: BDS 軸受架實施點檢Crack有無 | Z90: 完了 | AA90: 完了 | AB90: 完了 | AC90: 完了 | AD90: 完了 | AE90: - | AF90: - | AG90: =IF(Y90="","","CLOSE") -> CLOSE | AH90: =IF(E90="","",IF(COUNTIF(Z90:AE90,"未")=0,"CLOSE","")) -> CLOSE | AI90: =COUNTIF(Z90:AF90,"完了")/COUNTIF(R90:X90,"要") -> 1
A91: =A90+1 -> 1485 | B91: 42285 | C91: 高砂 | D91: BF | E91: 鄭吉勝 | F91: 電氣系 | G91: 縦切機 | H91: ADT以外 | I91: 異常報告書（中文）共有フォルダ\201501以降\20151008BF 縦切機SEQUENCER異常.xls | K91: 縱切機シーケンサー異常 | L91: 推定原因（設技見解） Sequencer PLC發出警報①受到雜訊影響、②機器（CPU UNIT、MOTION UNIT、SEQUENCER BASE UNIT）異常 | M91: SEQUENCER BASE UNIT更換 | N91: 初回 | O91: 30 | P91: 1600 | R91: 情報 | S91: 情報 | T91: 情報 | U91: 情報 | V91: 情報 | W91: 情報 | X91: 情報 | Y91: 情報共有 | Z91: - | AA91: - | AB91: - | AC91: - | AD91: - | AE91: - | AF91: - | AG91: =IF(Y91="","","CLOSE") -> CLOSE | AH91: =IF(E91="","",IF(COUNTIF(Z91:AE91,"未")=0,"CLOSE","")) -> CLOSE | AI91: =COUNTIF(Z91:AF91,"完了")/COUNTIF(R91:X91,"要") -> #DIV/0!
A92: =A91+1 -> 1486 | B92: 42295 | C92: 高砂 | D92: TAS | E92: 鄭吉勝 | F92: 機械系 | G92: WIT1號線投入機昇降LM GUIDE(ガイド)破損 | H92: ADT以外 | I92: 異常報告書（中文）共有フォルダ\201501以降\20151018TAS WIT NO1投入機(樂樂手)昇降LM GUIDE破損.xls | K92: 樂樂手朝向吸著位置下降的途中 脫離了LM GUIDE的軌道 | L92: 曾經針對LM GUIDE軌道的部分進行給脂，GUIDE的培林部位 未給脂。結果導致 GUIDE的培林生鏽，培林脫落之後，該部位出現的縫隙影響到LM GUIDE軌道 繼而破損。 | M92: 實施備品更換。 於現場張貼這次發生的異常內容，並註記 給脂日期及下回的給脂日期 進行管理。 | N92: 初回 | O92: 440 | P92: 18923 | R92: - | S92: - | T92: - | U92: - | V92: - | W92: 要 | X92: 要 | Y92: 1.LM GUIDE確認 2.定期給指明確化 | Z92: - | AA92: - | AB92: - | AC92: - | AD92: - | AE92: 完了 | AF92: 完了 | AG92: =IF(Y92="","","CLOSE") -> CLOSE | AH92: =IF(E92="","",IF(COUNTIF(Z92:AE92,"未")=0,"CLOSE","")) -> CLOSE | AI92: =COUNTIF(Z92:AF92,"完了")/COUNTIF(R92:X92,"要") -> 1
A93: =A92+1 -> 1487 | B93: 42266 | C93: ADT | D93: YF | E93: 鄭吉勝 | F93: 機械系 | G93: 横切機 | H93: ADT内対応 | I93: 異常報告書（中文）共有フォルダ\201501以降\20150919 YF本線橫切NO1走行皮帶斷裂異常.xls | K93: 本線橫切機＃1走行皮帶斷裂異常 | L93: 長期間使用による経年劣化 | M93: 1.工事日を利用し1回/6ヶ月の点検実施 2.年度修繕計画に項目を追加 | N93: 初回 | O93: 5 | P93: 71 | R93: 情報 | S93: 情報 | T93: 情報 | U93: 情報 | V93: 情報 | W93: 情報 | X93: 情報 | Y93: 情報共有 | Z93: - | AA93: - | AB93: - | AC93: - | AD93: - | AE93: - | AF93: - | AG93: =IF(Y93="","","CLOSE") -> CLOSE | AH93: =IF(E93="","",IF(COUNTIF(Z93:AE93,"未")=0,"CLOSE","")) -> CLOSE | AI93: =COUNTIF(Z93:AF93,"完了")/COUNTIF(R93:X93,"要") -> #DIV/0!
A94: =A93+1 -> 1488 | B94: 42275 | C94: ADT | D94: ZF | E94: 鄭吉勝 | F94: 電氣系 | G94: 位置決め | H94: 他拠点報告 | I94: 異常報告書（中文）共有フォルダ\201501以降\20150928 ZF 1BR引入板揃異常報告.xlsx | K94: 1BR引込み板揃え動作不可 | L94: 1 従来1回/3年の冷修での交換という管理になっていた。 2 サーボアンプバッテリー電圧低下で重故障となり警報リセット及び動作不可となるソフトであった。 | M94: 1 冷修間隔も延長されている事から 今後は1回/2年、冷修の2回/4年の交換サイクルへ管理基準を変更する。年度修繕計画に点検項目を追加する 2 サーボアンプバッテリー電圧が低下してもモーター駆動には影響は出ないため軽故障（警報のみ）へとソフト変更実施 | N94: 初回 | P94: 372.39 | R94: 要 | S94: 要 | T94: 要 | U94: 要 | V94: 要 | W94: 情報 | X94: 情報 | Y94: 1.サーボアンプバッテリ點檢確認 2.サーボアンプバッテリー電圧が低下してもモーター駆動には影響は出ないため軽故障（警報のみ）へとソフト変更実施 | Z94: 完了 | AA94: 完了 | AB94: 完了 | AC94: 完了 | AD94: 完了 | AE94: - | AF94: - | AG94: =IF(Y94="","","CLOSE") -> CLOSE | AH94: =IF(E94="","",IF(COUNTIF(Z94:AE94,"未")=0,"CLOSE","")) -> CLOSE | AI94: =COUNTIF(Z94:AF94,"完了")/COUNTIF(R94:X94,"要") -> 1
A95: =A94+1 -> 1489 | B95: 42318 | C95: AFK | D95: FF | E95: 鄭吉勝 | F95: 機械系 | G95: TOM3ブース内駆動部 | H95: ADT以外 | I95: 異常報告書（中文）共有フォルダ\201501以降\20151110FF TOM3 Booth內驅動部異常.xlsx | K95: 本線駆動部（ラインシャフト）マイタギアBOX破損 | L95: 設備的原因 1.長期使用により、チェーンが伸びていた。 2. チェーンレール部分がＲ加工されていないかった。 管理的な原因 1. 検査ブース内に関する点検が行われなかった。 | M95: 1. 伸びたチェーン交換実施 2. 変形したスプロケットベース修正 3. 破損したギアBOX交換 4. チェーンレールのＲ加工 5. 駆動部確認点検周期を選定 6. パトロールチェックシート内容を修正する | N95: 初回 | O95: 175 | P95: 4498 | R95: 要 | S95: 要 | T95: 要 | U95: 要 | V95: 要 | W95: - | X95: - | Y95: 請於工事日重新確認一次鍊條護蓋是否有導角 、惰輪調整具合(狀況) | Z95: 完了 | AA95: 完了 | AB95: 完了 | AC95: 完了 | AD95: 完了 | AE95: - | AF95: - | AG95: =IF(Y95="","","CLOSE") -> CLOSE | AH95: =IF(E95="","",IF(COUNTIF(Z95:AE95,"未")=0,"CLOSE","")) -> CLOSE | AI95: =COUNTIF(Z95:AF95,"完了")/COUNTIF(R95:X95,"要") -> 1
A96: =A95+1 -> 1490 | B96: 42330 | C96: ADT | D96: JF | E96: 鄭吉勝 | F96: 檢查系 | G96: TOM3 | H96: 他拠点報告 | I96: 異常報告書（中文）共有フォルダ\201501以降\20151123_JF-TOM畫處PC20_HDD故障.xlsx | K96: TOM3 画処PC 20 HDD故障 | L96: ハードがBad Trackしたため、資料と転送の効率が異常になり、Image PCが特定の条件で遅延と資料転送不可となり、 1/100 Inch Pulse 異常が発生した。 | M96: 1. TOM3 Image20 PC更換預備HDD。 2.更換硬碟後參數確認及欠點檢出確認。 | N96: 再発 | O96: 0 | P96: 46 | R96: 情報 | S96: 情報 | T96: 情報 | U96: 情報 | V96: 情報 | W96: - | X96: - | Y96: 情報共有 | Z96: - | AA96: - | AB96: - | AC96: - | AD96: - | AE96: - | AF96: - | AG96: =IF(Y96="","","CLOSE") -> CLOSE | AH96: =IF(E96="","",IF(COUNTIF(Z96:AE96,"未")=0,"CLOSE","")) -> CLOSE | AI96: =COUNTIF(Z96:AF96,"完了")/COUNTIF(R96:X96,"要") -> #DIV/0!
A97: =A96+1 -> 1491 | B97: 42290 | C97: 高砂 | D97: GF | E97: 何坤擇 | F97: 電氣系 | G97: 紙巻機 | H97: ADT以外 | I97: 異常報告書（中文）共有フォルダ\201501以降\20151013GF 紙巻機排出皮帶伺服馬達異常.xls | K97: 紙巻機排出皮帶Servo馬達異常 | L97: 1.分解馬達時、發現内部有很多鐵粉，推測 馬達軸心經過長時間的運轉後 發生偏移、Shaft與Bearing摩擦 導致Bearing產生摩耗才會出現鐵粉出現。 2.Shaft軸心偏移・Bearing不良導致馬達負荷上升、致使發生這次的異常。 3.未定期確認Servo負荷率。 | M97: 1.更換Servo馬達新規、並實施對芯調整。 2.針對現場使用Servo馬達的機器整理列表、每週確認1回負荷率。(10/15起實施) | N97: 初回 | O97: 131 | P97: 3602 | R97: 情報 | S97: 情報 | T97: 情報 | U97: 要 | V97: 要 | W97: 要 | X97: - | Y97: 1.定期確認Servo馬達負荷率並記錄。 2.發生如有逐漸偏高聯絡設備技術確認。 | Z97: - | AA97: - | AB97: - | AC97: 完了 | AD97: 完了 | AE97: 完了 | AF97: - | AG97: =IF(Y97="","","CLOSE") -> CLOSE | AH97: =IF(E97="","",IF(COUNTIF(Z97:AE97,"未")=0,"CLOSE","")) -> CLOSE | AI97: =COUNTIF(Z97:AF97,"完了")/COUNTIF(R97:X97,"要") -> 1
A98: =A97+1 -> 1492 | B98: 42334 | C98: AFK | D98: LF | E98: 何坤擇 | F98: 機械系 | G98: 紙巻機 | H98: ADT以外 | I98: 異常報告書（中文）共有フォルダ\201501以降\20151126LF 1Br IZUMI製紙巻機 排出Belt駆動部中間軸破損.xls | K98: 紙巻機出紙皮帶驅動Coupling中間軸 Key 溝槽破損 | L98: 1. 推測 出紙皮帶在回轉、停止之際發生反復荷重、 中間軸的Key 溝槽發生疲勞破壞 （中間軸的強度不足） 2. 出紙皮帶停止之際產生了後座力、但當下僅針對Coupling進行目視點檢、未察覺中間軸已有所磨耗 ※2015年9月10日變更了Coupling Type, 相關位置也有所改變, 設置了中間軸 變更理由：板彈簧破裂頻度上升（1回/年 左右）Line 速度為3600m/Hr、推測彈簧負荷過大 導致 | M98: 重新審視並製作中間軸的外徑Size [參照圖1]※ 設置改良品之後、解決了在皮帶停止時所產生的後座力 今後對策: 於每回工事日進行 中間軸 Key Set Bolt鎖緊及動作狀態確認 | N98: 初回 | P98: 327 | R98: - | S98: - | T98: - | U98: 要 | V98: 要 | W98: 要 | X98: - | Y98: 1.與設備技術確認ADT使用型號是否相同。並與對應。 2.工事日時進行鎖固確認。 | Z98: - | AA98: - | AB98: - | AC98: 完了 | AD98: 完了 | AE98: 完了 | AF98: - | AG98: =IF(Y98="","","CLOSE") -> CLOSE | AH98: =IF(E98="","",IF(COUNTIF(Z98:AE98,"未")=0,"CLOSE","")) -> CLOSE | AI98: =COUNTIF(Z98:AF98,"完了")/COUNTIF(R98:X98,"要") -> 1
A99: =A98+1 -> 1493 | B99: 42303 | C99: ADT | D99: ZF | E99: 何坤擇 | F99: 機械系 | G99: P詰め機 | H99: 他拠点報告 | I99: 異常報告書（中文）共有フォルダ\201501以降\20151026ZF 1P P詰め板倒し油圧ホース破損報告（中日文版）.xlsx | K99: 1P P詰板倒油管破損 | L99: P詰起倒時，P詰台車之架台與油壓軟管發生接觸進而產生磨耗 | M99: 1. 暫定對策: 軟管更換後、與架台會發生接觸的位置以橡膠墊塊包覆養生 2. 恒久對策: 為使軟管部與機架不再發生接觸，將岐管部之接頭改為45°的形式，再裝設軟管 其他有使用油壓軟管的地方也已建側列表、會依此實施軟管的點檢作業 ※下次工事日進行點檢、之後以 1回/六個月的頻率實施、列入定期點檢的項目內） | N99: 初回 | P99: 1283.5 | R99: 要 | S99: 要 | T99: 要 | U99: 情報 | V99: 情報 | W99: - | X99: - | Y99: 1.對策項目恆展開實施。 2.列入定期點檢確實實施。 | Z99: 完了 | AA99: 完了 | AB99: 完了 | AC99: - | AD99: - | AE99: - | AF99: - | AG99: =IF(Y99="","","CLOSE") -> CLOSE | AH99: =IF(E99="","",IF(COUNTIF(Z99:AE99,"未")=0,"CLOSE","")) -> CLOSE | AI99: =COUNTIF(Z99:AF99,"完了")/COUNTIF(R99:X99,"要") -> 1
A100: =A99+1 -> 1494 | B100: 42331 | C100: ADT | D100: JF | E100: 何坤擇 | F100: 檢查系 | G100: TOM3 | H100: 他拠点報告 | I100: 異常報告書（中文）共有フォルダ\201501以降\20151123_JF-TOM畫處PC20_HDD故障.xlsx | K100: JF TOM3 畫處PC 20 HDD故障 | L100: 因為硬碟壞軌造成資料及傳輸效率異常,導致Image PC 在特定條件下延遲或無法傳送資料,造成1/100 Inch Pulse 異常。 | M100: 1. TOM3 Image20 PC更換預備HDD。 2.更換硬碟後參數確認及欠點檢出確認。 | N100: 再発 | O100: 0 | P100: 46 | R100: 要 | S100: 要 | T100: 要 | U100: 要 | V100: 要 | W100: - | X100: - | Y100: 1.工事日定期會確認 TOM3 各硬碟 SMART 狀態。 2.對策項目恆展開實施。 | Z100: 完了 | AA100: 完了 | AB100: 完了 | AC100: 完了 | AD100: 完了 | AE100: - | AF100: - | AG100: =IF(Y100="","","CLOSE") -> CLOSE | AH100: =IF(E100="","",IF(COUNTIF(Z100:AE100,"未")=0,"CLOSE","")) -> CLOSE | AI100: =COUNTIF(Z100:AF100,"完了")/COUNTIF(R100:X100,"要") -> 1
A101: =A100+1 -> 1495 | B101: 42351 | C101: ADT | D101: JF | E101: 何坤擇 | F101: 檢查系 | G101: TOM3 | H101: 他拠点報告 | I101: 異常報告書（中文）共有フォルダ\201501以降\20151213JF TOM_MCCTR=0トラブル報告rev1.xlsx | K101: JF TOM MCCTR =0 異常 | L101: 1. ATSC 一濑先生的見解說明到 MCCTR=0 偶爾會遇到，但這在正常容許範圍內，所以推測是TOM檢查軟體的問題。 2. ENG 佐野先生調查的結果，之前在ZF、FF也有發生過，但記錄上是寫著已對策完畢，所以先排除了ACE方面的問題。 3. NTC 業者TEST後的答覆證實是 TOM Host 軟體內部有不具合。 | M101: TOM3 Host PC Software 已經由 NTC 業者在進行修正的準備。 ENG 佐野先生的說明:發生機率是「MCCTR=0 1/10000」×「Ring Buffer 先端約 1/10」的微乎其微的機會才會發生。 | N101: 初回 | O101: 0 | P101: 9 | R101: 情報 | S101: 情報 | T101: 情報 | U101: 情報 | V101: 情報 | W101: - | X101: - | Y101: 情報共有 | Z101: - | AA101: - | AB101: - | AC101: - | AD101: - | AE101: - | AF101: - | AG101: =IF(Y101="","","CLOSE") -> CLOSE | AH101: =IF(E101="","",IF(COUNTIF(Z101:AE101,"未")=0,"CLOSE","")) -> CLOSE | AI101: =COUNTIF(Z101:AF101,"完了")/COUNTIF(R101:X101,"要") -> #DIV/0!
A102: =A101+1 -> 1496 | B102: 42359 | C102: AFK | D102: FF | E102: 何坤擇 | F102: 機械系 | G102: C/V | H102: ADT以外 | I102: 異常報告書（中文）共有フォルダ\201501以降\20151221FF 本線増速CV№5凸輪離合器異常.xlsx | K102: 本線増速conv'#5停止異常 | L102: 推測為離合器內的凸輪磨耗影響回轉不良，拆解後才確認到、光憑外觀無法確認到明顯的磨耗。 設 置：2008年3月（冷修時） 歷 經：6年9個月 | M102: 1. 更換備品 2. 由於本線増速C/V ＃5、＃6時常保持一定的速度，以撤除為方針。 3. MZ Ｔｙｐｅ原本已經準備好要更新了、不過這個部分也檢討要撤掉。 | N102: 初回 | O102: 55 | P102: 1414 | R102: 要 | S102: 要 | T102: 要 | U102: 要 | V102: 要 | W102: - | X102: - | Y102: 工事日進行點檢確認。 | Z102: 完了 | AA102: 完了 | AB102: 完了 | AC102: 完了 | AD102: 完了 | AE102: - | AF102: - | AG102: =IF(Y102="","","CLOSE") -> CLOSE | AH102: =IF(E102="","",IF(COUNTIF(Z102:AE102,"未")=0,"CLOSE","")) -> CLOSE | AI102: =COUNTIF(Z102:AF102,"完了")/COUNTIF(R102:X102,"要") -> 1
A103: =A102+1 -> 1497 | B103: 42381 | C103: 高砂 | D103: TAS | E103: 何坤擇 | F103: 機械系 | G103: 投入ラクラクハンド | H103: ADT以外 | I103: 異常報告書（中文）共有フォルダ\201601以降\20160112TAS WIT_1 LINE連結投入機HAND與ARM的HAND側的焊接部位龜裂.xls | K103: WIT#1 LINE 投入機ＨＡＮＤ與ARM 靠近HAND側的焊接部位發生龜裂 | L103: 1. 經年累月重複來回走行、導致疲勞龜裂。（約7年） 2. 龜裂看起來從很久以前就開始有了。 3. 由於該部位並未列入點檢項目，所以從來沒有點檢過、才會發生這次的異常。 | M103: 1. 針對龜裂處重新進行焊接對應。 2. 1年實施1回焊接部探傷試驗。 | N103: 初回 | O103: 120 | P103: 3158 | R103: - | S103: - | T103: - | U103: 要 | V103: 要 | W103: 要 | X103: - | Y103: 1.對策項目恆展開實施。 2.列入定期點檢確實實施。 | Z103: - | AA103: - | AB103: - | AC103: 完了 | AD103: 完了 | AE103: 完了 | AF103: - | AG103: =IF(Y103="","","CLOSE") -> CLOSE | AH103: =IF(E103="","",IF(COUNTIF(Z103:AE103,"未")=0,"CLOSE","")) -> CLOSE | AI103: =COUNTIF(Z103:AF103,"完了")/COUNTIF(R103:X103,"要") -> 1
A104: =A103+1 -> 1498 | B104: 42374 | C104: AFK | D104: TAS | E104: 何坤擇 | F104: 機械系 | G104: 紙巻機 | H104: ADT以外 | I104: 異常報告書（中文）共有フォルダ\201601以降\20160105GUT GUT2紙巻機切刀昇降TIME OVER.xlsx | K104: 紙巻機切刀動作異常（起動刃昇降TIME OVER） | L104: 在10天以前已經實施過定期更換 (之前發生過異常)，於機械室進行維修保養後，才剛剛針對每處UNIT進行了更換。 接觸痕跡附近的固定螺絲也沒有鬆脫的現象，所以推測是在維修保養上的調整不具合，導致上下刀刃持續磨擦使溝槽的間距變大，切刀上升時有困難，才會發生此異常。 | M104: ＜管理面＞ 1. 日常巡檢時持續確認動作及異音。 ＜設備面＞ 1.確認起動刃有無彎曲變形。 2.針對LM-Guide的Bearing Block及CYL的托架精度進行確認。 3.實施除鏽及手動切斷測試。 | N104: 初回 | O104: 175 | P104: 859 | R104: - | S104: - | T104: - | U104: 要 | V104: 要 | W104: 要 | X104: - | Y104: 1.對策項目恆展開實施。 2.列入定期點檢確實實施。 3.與設備技術討論往後更換方案方式。 | Z104: - | AA104: - | AB104: - | AC104: 完了 | AD104: 完了 | AE104: 完了 | AF104: - | AG104: =IF(Y104="","","CLOSE") -> CLOSE | AH104: =IF(E104="","",IF(COUNTIF(Z104:AE104,"未")=0,"CLOSE","")) -> CLOSE | AI104: =COUNTIF(Z104:AF104,"完了")/COUNTIF(R104:X104,"要") -> 1
A105: =A104+1 -> 1499 | B105: 42388 | C105: 尼崎 | D105: XF | E105: 何坤擇 | F105: 機械系 | G105: C/V | H105: ADT以外 | I105: 異常報告書（中文）共有フォルダ\201601以降\20160119XF 本線増速CV NO5 CAM CLUTCH離合器打滑異常.xlsx | K105: 本線増速C/V NO5 Cam Clutch 離合器打滑異常 | L105: 設技見解判斷為經年累月所致之劣化※從XF2的START開始約使用6年 | M105: 永久對應，要先確認技開及ENG方面的回覆之後再對應 | N105: 初回 | O105: 5.5 | P105: 66 | R105: 要 | S105: 要 | T105: 要 | U105: 要 | V105: 要 | W105: - | X105: - | Y105: 工事日進行點檢確認。 | Z105: 完了 | AA105: 完了 | AB105: 完了 | AC105: 完了 | AD105: 完了 | AE105: - | AF105: - | AG105: =IF(Y105="","","CLOSE") -> CLOSE | AH105: =IF(E105="","",IF(COUNTIF(Z105:AE105,"未")=0,"CLOSE","")) -> CLOSE | AI105: =COUNTIF(Z105:AF105,"完了")/COUNTIF(R105:X105,"要") -> 1
A106: =A105+1 -> 1500 | B106: 42404 | C106: AFK | D106: TAS | E106: 何坤擇 | F106: 電氣系 | G106: T/T №2 | H106: ADT以外 | I106: 異常報告書（中文）共有フォルダ\201601以降\20160204GUT PL與RB發生衝撞.xlsx | K106: P/L與RB發生衝撞 | L106: 1. 在未設置G5.5 PL檢知Senser的狀態下 直接使用設備。 2. 於PL檢知Senser設置磁鐵，解除Interlock後生產。 3. 誤以為只要在T/P上面選取PL TYPE就可以在自動補正的狀態下採板。 | M106: 1. 因為G5.5出貨時有G6和G5.5兩種積載PL的類型，將檢討 不同的PL TYPE 的補正值能不能直接在T/P 被反映出來。 | N106: 初回 | O106: 148 | P106: 1289 | R106: - | S106: 要 | T106: 要 | U106: 要 | V106: 要 | W106: 要 | X106: - | Y106: 1. 確認現狀設備是否有各型式PL的感應SENSOR。 2. 確認軟體Interlock是否正常。 | Z106: - | AA106: 完了 | AB106: 完了 | AC106: 完了 | AD106: 完了 | AE106: 完了 | AF106: - | AG106: =IF(Y106="","","CLOSE") -> CLOSE | AH106: =IF(E106="","",IF(COUNTIF(Z106:AE106,"未")=0,"CLOSE","")) -> CLOSE | AI106: =COUNTIF(Z106:AF106,"完了")/COUNTIF(R106:X106,"要") -> 1
A107: =A106+1 -> 1501 | B107: 42405 | C107: 尼崎 | D107: XF | E107: 何坤擇 | F107: 機械系 | G107: 採板設備 | H107: ADT以外 | I107: 異常報告書（中文）共有フォルダ\201601以降\20160205XF 2BR 5POS BDS塞車警報異常.xlsx | K107: 2BR 5POS 塞車警報異常 | L107: 5P異常時的塞車警報在2/5 導入，原本5P的採板C/V在4P重故障時 應該必須停止，但是軟體的條件 卻是設定 當4POS發生輕故障or重故障 下會停止，所以第一次發生5P 吸著異常時，因4P發生了行先異常(輕故障)，警報也未解除的狀況下，才會在5P發生吸著異常警報之後，接著發生了 | M107: 1. 導入軟體之際確認軟體内容（確認變更內容） 2. 另行與設技商量輕故障時的警報如何設置 3. 須針對軟體導入時的測試項目由製造設技進行軟體導入之異常 KY | N107: 初回 | O107: 57.5 | P107: 1731 | R107: 情報 | S107: 情報 | T107: 情報 | U107: 情報 | V107: 情報 | W107: - | X107: - | Y107: 1. 情報聯絡。 2. 有進行軟體修改後，要確實進行相關測試。 | Z107: - | AA107: - | AB107: - | AC107: - | AD107: - | AE107: - | AF107: - | AG107: =IF(Y107="","","CLOSE") -> CLOSE | AH107: =IF(E107="","",IF(COUNTIF(Z107:AE107,"未")=0,"CLOSE","")) -> CLOSE | AI107: =COUNTIF(Z107:AF107,"完了")/COUNTIF(R107:X107,"要") -> #DIV/0!
A108: =A107+1 -> 1502 | B108: 42423 | C108: 尼崎 | D108: XF | E108: 何坤擇 | F108: 機械系 | G108: C/V | H108: ADT以外 | I108: 異常報告書（中文）共有フォルダ\201601以降\20160223XF 2BR 4POS 旋回CV SWIVEL JOINT旋轉接頭 配管漏油異常.xlsx | K108: 2BR 4POS 旋回C/VSWIVEL JOINT旋轉接頭部配管漏油 | L108: 更換配管時，袋型螺帽部的Sleeve套筒部分未確實裝入就直接鎖上螺栓，在經過幾次的動作確認之後，該部位受到擠壓，以致配管呈現稍微鬆脫的狀態，從縫隙處發生漏油 | M108: 1. 重新審視配管連接時螺帽固定之確認方式※連接後重新進行了內部確認，拆除配管並確認內部鉚接加工的部位 | N108: 初回 | O108: 0 | P108: 0 | R108: 情報 | S108: 情報 | T108: 情報 | U108: 情報 | V108: 情報 | W108: - | X108: - | Y108: 1.進行管路更後要確實是否鎖固OK。 2.要進行試運轉確認沒有問題後才可恢復生產。 | Z108: - | AA108: - | AB108: - | AC108: - | AD108: - | AE108: - | AF108: - | AG108: =IF(Y108="","","CLOSE") -> CLOSE | AH108: =IF(E108="","",IF(COUNTIF(Z108:AE108,"未")=0,"CLOSE","")) -> CLOSE | AI108: =COUNTIF(Z108:AF108,"完了")/COUNTIF(R108:X108,"要") -> #DIV/0!
A109: =A108+1 -> 1503 | B109: 42442 | C109: 高砂 | D109: BF | E109: 何坤擇 | F109: 機械系 | G109: 紙巻機 | H109: ADT以外 | I109: 異常報告書（中文）共有フォルダ\201601以降\20160313BF窯 1BR紙巻機エアシャフト折損（追記）.xlsx | K109: 1BR紙巻機AIR SHAFT折損 | L109: ■紙巻機Ready OFF的原因 推測AIR SHAFT的軸端斷裂後，運轉時振動變大，平台的位置跑掉 近接Senser 才會OFF。 ■Airshaft的折損原因 由折損部位的斷裂狀況看起來，推測是從M10固定用螺絲部位開始斷掉。 | M109: ・恒久對策的部分會另外與設技協議 暫定對策：由製造針對預備AIR SHAFT的軸端部進行點檢。 進行吊掛作業時, 軸端部位不與尼龍束帶干涉。 ※降低對軸端部的負荷 | N109: 初回 | P109: 3523 | R109: 要 | S109: 要 | T109: 要 | U109: 要 | V109: 要 | W109: - | X109: - | Y109: 1.對策項目恆展開實施。 | Z109: 完了 | AA109: 完了 | AB109: 完了 | AC109: 完了 | AD109: 完了 | AE109: - | AF109: - | AG109: =IF(Y109="","","CLOSE") -> CLOSE | AH109: =IF(E109="","",IF(COUNTIF(Z109:AE109,"未")=0,"CLOSE","")) -> CLOSE | AI109: =COUNTIF(Z109:AF109,"完了")/COUNTIF(R109:X109,"要") -> 1
A110: =A109+1 -> 1504 | B110: 42454 | C110: ADT | D110: KF | E110: 曾隆盛 | F110: 機械系 | G110: C/V | H110: 他拠点報告 | I110: 異常報告書（中文）共有フォルダ\201601以降\20160325KF 2BR採板CV3-3 SERVO異常.xls | K110: 2Br採板CV 3-3 SERVO異常 | L110: SERVO Motor 軸承不良。 (上回更換日 2013/5/9 ) | M110: 1. 確認並檢討SERVO Motor 軸承的壽命及 更換週期。 2. 定期確認SERVO Motor實效負荷率（1回 /週） 3. 實效負荷率到了警示等級，且該設備無 法停止的話，須每日進行實效負荷率的 確認。 4. 實效負荷率達到異常等級時，須立即點 檢更換。 | N110: 初回 | O110: 162 | P110: 532 | R110: 要 | S110: 要 | T110: 要 | U110: 要 | V110: 要 | W110: 要 | X110: - | Y110: 1.對策項目恆展開實施。 | Z110: 完了 | AA110: 完了 | AB110: 完了 | AC110: 完了 | AD110: 完了 | AE110: 完了 | AF110: - | AG110: =IF(Y110="","","CLOSE") -> CLOSE | AH110: =IF(E110="","",IF(COUNTIF(Z110:AE110,"未")=0,"CLOSE","")) -> CLOSE | AI110: =COUNTIF(Z110:AF110,"完了")/COUNTIF(R110:X110,"要") -> 1
A111: =A110+1 -> 1505 | B111: 42496 | C111: ADT | D111: ZF | E111: 曾隆盛 | F111: 電氣系 | G111: ACE | H111: 他拠点報告 | I111: 異常報告書（中文）共有フォルダ\201601以降\20160506ZF ACE NO1PC異常報告.xlsx | K111: ACE #1異常 | L111: ・這次故障的PC是2世代前舊型DELL製PC。 ※SIEMENS製PC在之前故障的時候，有請MAKER修理，進行Running Test。實施後，有送回ADT，但是沒有做更換。 ・因為PC POWER SUPPLY故障，電源無法供給，就將PC關機了。 ※每3個月實施一次定期的#1PC（舊型DELL）跟#2PC（舊型DELL）的切替。（SIEMENS製當作#3預備來保管著） | M111: ・雖然這次切替的預備PC是1世代前的舊型PC（SIEMENS製），但是POWER SAPPLY是2系統，就算1系統故障了，PC還是不會DOWN，還是可以使用的，所以打算在下次冷修時，替換成最新型DELL製PC，在那之前還是先使用SIEMENS製PC。 ※SIEMENS製PC在POWER SUPPLY1系統故障時， 警報聲會響起，所以巡檢時是可以發現的。 ・設備技術課的見解 ※如果現行的新型ＡＣＥ的電源故障多發的話，需要實施電源冗長化等的改善。 | N111: 初回 | O111: 39 | P111: 820 | R111: 情報 | S111: 情報 | T111: 情報 | U111: 情報 | V111: 情報 | W111: - | X111: - | Y111: 今回のACE PC異常は古いPCを使用しているZFだけの問題でした。 他LINEはPCが新しいため問題ありません。 他窯情報聯絡 | Z111: - | AA111: - | AB111: - | AC111: - | AD111: - | AE111: - | AF111: - | AG111: =IF(Y111="","","CLOSE") -> CLOSE | AH111: =IF(E111="","",IF(COUNTIF(Z111:AE111,"未")=0,"CLOSE","")) -> CLOSE | AI111: =COUNTIF(Z111:AF111,"完了")/COUNTIF(R111:X111,"要") -> #DIV/0!
A112: =A111+1 -> 1506 | B112: 42507 | C112: AFK | D112: HF | E112: 董明成 | F112: 機械系 | G112: 横切機 | H112: ADT以外 | I112: 異常報告書（中文）共有フォルダ\201601以降\20160517HF 横切機No2カッター走行駆動ベルト断裂.xlsx | K112: 横切機No.2切刀走行驅動皮帶斷裂 | L112: 疑為 Pulley軸芯偏移、皮帶鬆弛。 | M112: 1. 實施定期點檢以確認有無異常。(1回/6個月) 2. 更換時規皮帶 - 主要設備冷修時更換 | N112: 初回 | O112: 0 | P112: 0 | R112: 要 | S112: 要 | T112: 要 | U112: 要 | V112: 要 | W112: 情報 | X112: - | Y112: 1.各切機點檢確認 2.更換TIMING及基準確認 | Z112: 完了 | AA112: 完了 | AB112: 完了 | AC112: 完了 | AD112: 完了 | AE112: - | AF112: - | AG112: =IF(Y112="","","CLOSE") -> CLOSE | AH112: =IF(E112="","",IF(COUNTIF(Z112:AE112,"未")=0,"CLOSE","")) -> CLOSE | AI112: =COUNTIF(Z112:AF112,"完了")/COUNTIF(R112:X112,"要") -> 1
A113: =A112+1 -> 1507 | B113: 42509 | C113: AFK | D113: HF | E113: 董明成 | F113: 電氣系 | G113: 採板設備 | H113: ADT以外 | I113: 異常報告書（中文）共有フォルダ\201601以降\20160519HF 2Br2Pos採板ロボット重故障停止.xlsx | K113: 2BR 2POS 採板ROBOT異常停止 | L113: 疑為Encoder Cable 斷線 * Robot發生Communication Error (T軸Encoder Error) (Alarm Code :T軸 1325通信異常(Encoder) | M113: Cable事前點檢有困難、會進行管理以確保Spare Cable數量 (目前保管2個) | N113: 初回 | O113: 0 | P113: 0 | R113: - | S113: 情報 | T113: 情報 | U113: 情報 | V113: 情報 | W113: 情報 | X113: - | Y113: 1.JF類似異常(CABLEVEYOR與業者確認改善狀況) 2.備品確認 | Z113: - | AA113: - | AB113: - | AC113: - | AD113: - | AE113: - | AF113: - | AG113: =IF(Y113="","","CLOSE") -> CLOSE | AH113: =IF(E113="","",IF(COUNTIF(Z113:AE113,"未")=0,"CLOSE","")) -> CLOSE | AI113: =COUNTIF(Z113:AF113,"完了")/COUNTIF(R113:X113,"要") -> #DIV/0!
A114: =A113+1 -> 1508 | B114: 42511 | C114: AFK | D114: IF | E114: 董明成 | F114: 機械系 | G114: P詰め機 | H114: ADT以外 | I114: 異常報告書（中文）共有フォルダ\201601以降\20160521IF 2Br_P詰機板揃えシリンダー油圧ホースリーク.xlsx | K114: 2Br P詰機板齊Cylinder油壓Hose漏油 | L114: 推測 長期使用下（9年程度）産生劣化所致。 | M114: ●強化整備及３交代巡檢 ●調査長期使用的設備項目並依序交換 | N114: 初回 | O114: 0 | P114: 0 | R114: 要 | S114: 要 | T114: 要 | U114: - | V114: - | W114: - | X114: - | Y114: 1.P詰機及T/T油壓管路油漏確認 2.目前使用年數及更換基準確認 | Z114: 完了 | AA114: 完了 | AB114: 完了 | AC114: - | AD114: - | AE114: - | AF114: - | AG114: =IF(Y114="","","CLOSE") -> CLOSE | AH114: =IF(E114="","",IF(COUNTIF(Z114:AE114,"未")=0,"CLOSE","")) -> CLOSE | AI114: =COUNTIF(Z114:AF114,"完了")/COUNTIF(R114:X114,"要") -> 1
A115: =A114+1 -> 1509 | B115: 42516 | C115: 高砂 | D115: BF | E115: 何坤擇 | F115: 電氣系 | G115: 採板設備 | H115: ADT以外 | I115: 異常報告書（中文）共有フォルダ\201601以降\20160526BF窯 1BR_11POS Encoder Cable斷線.xlsx | K115: 1BR#11POS Encoder Cable斷線 | L115: 電纜護蓋因金屬疲勞而發生破損、Cable斷線。 BF的Robot裡面 只有從WIT移設到11POS的電纜護蓋是同款的 。 ※破損處的鐵板厚度為3mmt | M115: 1. 檢討電纜護蓋的補強方式。 2. 定期進行工事日點檢。 | N115: 初回 | P115: 83 | R115: 情報 | S115: 要 | T115: 要 | U115: 要 | V115: 要 | W115: 要 | X115: - | Y115: 1. 每回工事日進行點檢確認。 2. 請機械及電氣進行現狀相關設備是否有異常。 3. 整備人員每回點檢要確實注意作動是否有異常。 | Z115: - | AA115: 完了 | AB115: 完了 | AC115: 完了 | AD115: 完了 | AE115: 完了 | AF115: - | AG115: =IF(Y115="","","CLOSE") -> CLOSE | AH115: =IF(E115="","",IF(COUNTIF(Z115:AE115,"未")=0,"CLOSE","")) -> CLOSE | AI115: =COUNTIF(Z115:AF115,"完了")/COUNTIF(R115:X115,"要") -> 1 | AJ115: \\172.18.154.189\mfg_public\00 製造一部共通\横展開確認\03 設備(冷修)活動相關\2016年設備活動Team資料\01 ADT設備異常情報橫展開\TAS&OFF 寫真補充資料夾
A116: =A115+1 -> 1510 | B116: 42522 | C116: AFK | D116: DF | E116: 董明成 | F116: 機械系 | G116: C/V | H116: ADT以外 | I116: 異常報告書（中文）共有フォルダ\201601以降\20160601DF 2Br引入No.2 PAD CHAIN軌道折損.xlsx | K116: No.2Br引入No.2FT C/V 鍊條 軌道の折損 | L116: 鍊條軌道下降時撞到固定架台。 -針對0.3ｔ搬送對應 進行了PAD LEVEL調降作業、昇降cylinder的軌道下限Stopper也有鬆開向下調整、然而經過調整之後的高度 會干涉到固定架台。 | M116: - 預定重新審視鍊條軌道的構造。 | N116: 初回 | O116: 2.89 | P116: 62.54 | R116: 要 | S116: 要 | T116: 要 | U116: 要 | V116: 要 | W116: - | X116: - | Y116: CF窯類似異常橫展開進度確認 | Z116: 完了 | AA116: 完了 | AB116: 完了 | AC116: 完了 | AD116: 完了 | AE116: - | AF116: - | AG116: =IF(Y116="","","CLOSE") -> CLOSE | AH116: =IF(E116="","",IF(COUNTIF(Z116:AE116,"未")=0,"CLOSE","")) -> CLOSE | AI116: =COUNTIF(Z116:AF116,"完了")/COUNTIF(R116:X116,"要") -> 1
A117: =A116+1 -> 1511 | B117: 42543 | C117: 高砂 | D117: BF | E117: 董明成 | F117: 機械系 | G117: 紙巻機 | H117: ADT以外 | I117: 異常報告書（中文）共有フォルダ\201601以降\20160622BF窯 1BR紙巻機エアシャフト軸受固定用金具脱落.xlsx | K117: 1BR紙巻機Air Shaft軸受固定用金具脱落 | L117: ・軸承摩耗 使得Air Shaft 軸端與軸承之間的 距離變大、推測 固定用的Pin 受到回轉振動影響而脱落、以致Bolt發生折損。 | M117: ・更換軸承備品 ・工事日定期確認Pin・Bolt有無脱落。 ※頻度的部分需與設技再次商談。 | N117: 初回 | P117: 0 | R117: 要 | S117: 要 | T117: 要 | U117: 要 | V117: 要 | W117: - | X117: - | Y117: 1.各窯AIR SHAFT軸受點檢確認 2.備品確認 | Z117: 完了 | AA117: 完了 | AB117: 完了 | AC117: 完了 | AD117: 完了 | AE117: - | AF117: - | AG117: =IF(Y117="","","CLOSE") -> CLOSE | AH117: =IF(E117="","",IF(COUNTIF(Z117:AE117,"未")=0,"CLOSE","")) -> CLOSE | AI117: =COUNTIF(Z117:AF117,"完了")/COUNTIF(R117:X117,"要") -> 1
A118: =A117+1 -> 1512 | B118: 42548 | C118: 高砂 | D118: BF | E118: 董明成 | F118: 其它 | G118: 採板設備 | H118: ADT以外 | I118: 異常報告書（中文）共有フォルダ\201601以降\20160627【客訴對策書】BF窯素板破裂(束帶混入)最終.xlsx | K118: 素板割れ(インシュロック混入) | L118: ・インシュロックに繰り返し曲げ応力が掛かり破断した。 | M118: ・下流移載機についてインシュロックの全更新を実施。 | N118: 初回 | O118: 0 | P118: 0 | R118: 要 | S118: 要 | T118: 要 | U118: 要 | V118: 要 | W118: 要 | X118: - | Y118: 1.BDS/RB採板機/移載機點檢 (重點為支點會晃動之處所) | Z118: 完了 | AA118: 完了 | AB118: 完了 | AC118: 完了 | AD118: 完了 | AE118: 完了 | AF118: - | AG118: =IF(Y118="","","CLOSE") -> CLOSE | AH118: =IF(E118="","",IF(COUNTIF(Z118:AE118,"未")=0,"CLOSE","")) -> CLOSE | AI118: =COUNTIF(Z118:AF118,"完了")/COUNTIF(R118:X118,"要") -> 1
...

Sheet 横展開フロー（TPM) 
A1: [ＴＰＭ] 他拠点との情報交換 | P1: 42558 | R1: rev2

Sheet Sheet1
B9: № | C9: 横展開内容 | D9: 横展開未ライン
B10: 15 | C10: ・チェーンの交換記録有無の確認 ・定期定修の頻度を担当者会議で機械Gと各窯討論 | D10: KF
B11: 20 | C11: ・シンクライアントHUBのケーブル抜け防止処置。 ・HUB周辺の清掃 | D11: KF | E11: 目前精查hub電回收，待稼動前實施
B12: 22 | C12: ・本線増速C/V№4のアイドラーシャフト材質変更（SCM435) | D12: KF | E12: 機械購入中！
B13: 28 | C13: ・縦切り機PLC故障の際も本線マスタPLCから警報出力されるようソフト改造 | D13: YF/ZF | E13: 設備依賴書已經提出！
B14: 30 | C14: ・カッター昇降CYL及びLMガイドの点検。 ・昇降動作に左右バラツキが発生した時は製造で調整せず機械へ連絡する事を徹底。 | D14: KF/TAS | E14: 週間會議時向機械提出依賴點檢
B15: 32 | C15: ・アイアンラバーベルト（時規皮帶）の点検（SAMP） | D15: KF | E15: 週間會議時向機械提出依賴點檢
B16: 34 | C16: ・定寸送り用サーボMで過負荷異常が発生する際は、ベルトの偏りによる可能性がある事を オペレーターへ教育実施。 | D16: KF | E16: 10/2異常發生案例實施教育（股長教育說明OK）
B17: 38 | C17: ・BURベースの固定ボルトの緩み確認 | D17: CF/KF | E17: 10/2進行點檢（點檢OK）
B18: 16 | C18: ・採板Robot UPS電源異常
B20: 11/4會議中AI
B21: 1.ADT橫展開SHEET有部份內容希望日文化

Sheet 工作表1

Sheet Sheet2
D10: 窯別 | E10: 橫展開（未實施）項目
D11: YF | E11: 第7、8、46、52、53
D12: ZF | E12: 第7、8、29、37、46、53
D13: CF | E13: 第7、16、29、46、50、53
D14: EF | E14: 第7、13、16、29、46、53
D15: JF | E15: 第7、8、16、46、50、53
D16: KF | E16: 第4、16、28、29、46、53
D17: TAS | E17: 第16、30、36、47
D18: OFF | E18: 第36、47

Sheet 横展開フロー（ADT)
A1: [ADT] 他窯との情報交換 | P1: 41827 | R1: rev1

Sheet 2018~設技･製造担当者_OLD
A1: 設備横展開担当者（担当者会議） | I1: 43115
G3: 横展開必要時聯絡先(必須）
A6: （敬称略）
G7: 日籍
B8: アドバイス | C8: 機械 林文勇 | G8: アドバイス | H8: 機械 ： 久野 | I8: 服部
B9: アドバイス | C9: 電気 黃深儀 | H9: 電気 ： 伊藤 | I9: 木村
A11: 台籍 | B11: リーダー | H11: 機械 | I11: 電気
B12: 機：黃奮志 | G12: 日籍 | H12: 後藤 | I12: 池田
B13: 電：許景晨
A14: 窯別 | B14: 主担当 | C14: 副担当
A15: YZ | B15: 機：林聖景 | C15: 機：廖得亨
B16: 電：黃瓘峻 | C16: 電：林逸樺
A17: CE （TAS含） | B17: 機：莊森為 | C17: 機：曾孟文
B18: 電：廖士智 | C18: 電：張水亮
A19: JK （TAS含） | B19: 機：高銘壕 | C19: 機：蔡志明
B20: 電：許俊彬 | C20: 電：邱文仁
G24: 日籍
B25: アドバイス | C25: 吳 清池 | G25: アドバイス | H25: 古閑 | I25: 三宅
B26: アドバイス | C26: 鄭 吉勝 | H26: 八尾 | I26: 藤原
H27: 主担当 | I27: 副担当
A28: 台籍 | B28: ﾘｰﾀﾞｰ | C28: ｻﾌﾞ | G28: 日籍 | H28: 切原 | I28: 中谷 | J28: 深町
B29: 陳 勝立 | C29: 邱 世文
A30: 窯別 | B30: LINE擔當 | C30: 主担当 | D30: 副担当
A31: YF | B31: 劉芳全 | C31: 許仕明 | D31: 林診輝
A32: CF | B32: 吳得祿 | C32: 吳學典 | D32: 曾隆盛
A33: EF | B33: 李炳興 | C33: 王文佑 | D33: 許建生
A34: JF | B34: 謝坤瀚 | C34: 朱峰謀 | D34: 吳洺偉
A35: KF | B35: 黃乙原 | C35: 張崇慶 | D35: 賴勃伸
A36: TAS | B36: 楊焜旭(劉佳明) | C36: 陳振遠 | D36: 邱信翔

Sheet 進捗確認シート (2)
A1: ADT 設備異常・設備改善 横展開進捗確認Sheet | H1: =SUM(H17:H152) -> 0 | S1: ★ADT各ライン | T1: 横展開対応状況
A2: ★ADT全ライン | T2: YF | X2: ZF | AB2: CF | AF2: EF | AJ2: JF | AN2: KF | AR2: TAS | AV2: OFF切
B3: 件数 | D3: 方針完了 | S3: 横展開必要件数 全拠点 | T3: =COUNTIF(T153:T453,"要") -> 9 | X3: =COUNTIF(X153:X453,"要") -> 0 | AB3: =COUNTIF(AB153:AB453,"要") -> 12 | AF3: =COUNTIF(AF153:AF453,"要") -> 11 | AJ3: =COUNTIF(AJ153:AJ453,"要") -> 12 | AN3: =COUNTIF(AN153:AN453,"要") -> 12 | AR3: =COUNTIF(AR153:AR453,"要") -> 4 | AV3: =COUNTIF(AV153:AV453,"要") -> 3
A4: 他拠点 | B4: =COUNTIF($J$153:$J$453,1) -> 4 | D4: =COUNTIF(L153:L453,2) -> 4 | E4: =D4/B4 -> 1 | S4: 横展開完了件数 全拠点 | T4: =COUNTIF(BB153:BB453,"完了") -> 8 | X4: =COUNTIF(BF153:BF453,"完了") -> 0 | AB4: =COUNTIF(BJ153:BJ453,"完了") -> 11 | AF4: =COUNTIF(BN153:BN453,"完了") -> 11 | AJ4: =COUNTIF(BR153:BR453,"完了") -> 13 | AN4: =COUNTIF(BV153:BV453,"完了") -> 13 | AR4: =COUNTIF(BZ153:BZ453,"完了") -> 4 | AV4: =COUNTIF(CD153:CD453,"完了") -> 3
A5: ADT内 | B5: =COUNTIF($J$153:$J$453,2) -> 11 | D5: =COUNTIF(L153:L453,3) -> 11 | E5: =D5/B5 -> 1 | S5: 横展開完了率 全拠点 | T5: =T4/T3 -> 0.88888889 | X5: =X4/X3 -> #DIV/0! | AB5: =AB4/AB3 -> 0.91666667 | AF5: =AF4/AF3 -> 1 | AJ5: =AJ4/AJ3 -> 1.0833333 | AN5: =AN4/AN3 -> 1.0833333 | AR5: =AR4/AR3 -> 1 | AV5: =AV4/AV3 -> 1 | CL5: 異常報告書（中文）共有フォルダ
A6: 全拠点 | B6: =COUNTIF(H$153:H$453,"1") -> 15 | D6: =D4+D5 -> 15 | E6: =D6/B6 -> 1 | T6: =SUM(T4:AY4)/SUM(T3:AY3) -> 1
B8: 件数 | D8: 対応完了 | S8: 横展開必要件数 ADT内 | T8: =COUNTIF(W153:W453,2) -> 6 | X8: =COUNTIF(AA153:AA453,2) -> 0 | AB8: =COUNTIF(AE153:AE453,2) -> 9 | AF8: =COUNTIF(AI153:AI453,2) -> 8 | AJ8: =COUNTIF(AM153:AM453,2) -> 8 | AN8: =COUNTIF(AQ153:AQ453,2) -> 8 | AR8: =COUNTIF(AU153:AU453,2) -> 3 | AV8: =COUNTIF(AY153:AY453,2) -> 2 | CL8: 異常報告書（日文）共有フォルダ
A9: 他拠点 | B9: =COUNTIF($J$153:$J$453,1) -> 4 | D9: =COUNTIF(N153:N453,2) -> 4 | E9: =D9/B9 -> 1 | S9: 横展開完了件数 ADT内 | T9: =COUNTIF(BE153:BE453,2) -> 5 | X9: =COUNTIF(BI153:BI453,2) -> 0 | AB9: =COUNTIF(BM153:BM453,2) -> 8 | AF9: =COUNTIF(BQ153:BQ453,2) -> 8 | AJ9: =COUNTIF(BU153:BU453,2) -> 9 | AN9: =COUNTIF(BY153:BY453,2) -> 9 | AR9: =COUNTIF(CC153:CC453,2) -> 3 | AV9: =COUNTIF(CG153:CG453,2) -> 2
A10: ADT内 | B10: =COUNTIF($J$153:$J$453,2) -> 11 | D10: =COUNTIF(N153:N453,3) -> 10 | E10: =D10/B10 -> 0.90909091 | S10: 横展開完了率 ADT内 | T10: =T9/T8 -> 0.83333333 | X10: =X9/X8 -> #DIV/0! | AB10: =AB9/AB8 -> 0.88888889 | AF10: =AF9/AF8 -> 1 | AJ10: =AJ9/AJ8 -> 1.125 | AN10: =AN9/AN8 -> 1.125 | AR10: =AR9/AR8 -> 1 | AV10: =AV9/AV8 -> 1
A11: 全拠点 | B11: =COUNTIF(H$153:H$453,"1") -> 15 | D11: =D9+D10 -> 14 | E11: =D11/B11 -> 0.93333333 | T11: =SUM(T9:AY9)/SUM(T8:AY8) -> 1
CQ12: 橫展開完成率=
CN13: =COUNTIF(CN153:CN252,"CLOSE") -> 20 | CQ13: =CN13/C15 -> 0.95238095
C15: =COUNTA(C153:C252) -> 21 | T15: 横展開必要ライン | BB15: 横展開対応進捗 | CH15: 資料保存先 | CM15: 方針 | CN15: 対応 | CQ15: 対応進捗状況の詳細コメント
A16: № | B16: 日付 | C16: 月份 | D16: 場所（1） | E16: 場所（2） | F16: 担当者 | G16: 要フラグ | H16: 要フラグ2 | I16: ADT+要 | J16: ADTor他拠点 | K16: 方針完了 フラグ | L16: 方針完了 フラグ2 | M16: 対応完了 フラグ | N16: 対応完了 フラグ2 | O16: 種別 | P16: 設備名 | Q16: 内容 | R16: 原因調査結果 | S16: 対策内容 | T16: YF | U16: YF | V16: YF | W16: YF | X16: ZF | Y16: ZF | Z16: ZF | AA16: ZF | AB16: CF | AC16: CF | AD16: CF | AE16: CF | AF16: EF | AG16: EF | AH16: EF | AI16: EF | AJ16: JF | AK16: JF | AL16: JF | AM16: JF | AN16: KF | AO16: KF | AP16: KF | AQ16: KF | AR16: TAS | AS16: TAS | AT16: TAS | AU16: TAS | AV16: OFF切 | AW16: OFF切 | AX16: OFF切 | AY16: OFF切 | AZ16: 横展開対応内容 | BA16: 目標期限 | BB16: YF | BC16: YF | BD16: YF | BE16: YF | BF16: ZF | BG16: ZF | BH16: ZF | BI16: ZF | BJ16: CF | BK16: CF | BL16: CF | BM16: CF | BN16: EF | BO16: EF | BP16: EF | BQ16: EF | BR16: JF | BS16: JF | BT16: JF | BU16: JF | BV16: KF | BW16: KF | BX16: KF | BY16: KF | BZ16: TAS | CA16: TAS | CB16: TAS | CC16: TAS | CD16: OFF切 | CE16: OFF切 | CF16: OFF切 | CG16: OFF切 | CH16: 日文 | CI16: 初回/ 再發 | CJ16: 中文 | CK16: LOSS m2 | CL16: 関係資料 | CM16: CLOSE | CN16: CLOSE | CO16: 停止 時間 (MIN) | CP16: 機會 損失 (m2) | CQ16: YF | CR16: ZF | CS16: CF | CT16: EF | CU16: JF | CV16: KF | CW16: TAS | CX16: OFF | CY16: コメント
A17: 1 | B17: 41798 | C17: =MONTH(B17) -> 6 | D17: ADT | E17: JF | F17: 三路 | G17: =COUNTIF(T17:AV17,"要") -> 5 | H17: =IF(G17>0,"1","0") -> 1 | I17: =IF(AND(D17="ADT",H17="1"),"1","0") -> 1 | J17: =H17+I17 -> 2 | K17: =IF(CM17="CLOSE",1,"") -> 1 | L17: =J17+K17 -> 3 | M17: =IF(CN17="CLOSE",1,"") -> 1 | N17: =J17+M17 -> 3 | O17: 検査機系異常 | P17: TOM3 | Q17: ・歪CAMERA#4 故障 | R17: ・第4TAP發生鬍鬚状的雜訊。 ※推測是歪CAMERA内部的接点不良。 | S17: ・CAMERA更換 ・在歪CAMERA的異常発現用處作成#970GATE ・作成和教育光量異常警報発生時，異常画像発現時的作業流程。 | T17: 要 | U17: =IF($D17="ADT","1","") -> 1 | V17: =IF(T17="要","1","") -> 1 | W17: =U17+V17 -> 2 | X17: 要 | Y17: =IF($D17="ADT","1","") -> 1 | Z17: =IF(X17="要","1","") -> 1 | AA17: =Y17+Z17 -> 2 | AB17: 要 | AC17: =IF($D17="ADT","1","") -> 1 | AD17: =IF(AB17="要","1","") -> 1 | AE17: =AC17+AD17 -> 2 | AF17: 要 | AG17: =IF($D17="ADT","1","") -> 1 | AH17: =IF(AF17="要","1","") -> 1 | AI17: =AG17+AH17 -> 2 | AJ17: － | AK17: =IF($D17="ADT","1","") -> 1 | AL17: =IF(AJ17="要","1","") | AM17: =AK17+AL17 -> #VALUE! | AN17: 要 | AO17: =IF($D17="ADT","1","") -> 1 | AP17: =IF(AN17="要","1","") -> 1 | AQ17: =AO17+AP17 -> 2 | AR17: － | AS17: =IF($D17="ADT","1","") -> 1 | AT17: =IF(AR17="要","1","") | AU17: =AS17+AT17 -> #VALUE! | AV17: － | AW17: =IF($D17="ADT","1","") -> 1 | AX17: =IF(AV17="要","1","") | AY17: =AW17+AX17 -> #VALUE! | AZ17: ・追加#970GATE ・教育光量異常警報発生時，異常画像発現時的作業流程。 | BA17: 41851 | BB17: 完了 | BC17: =IF($D17="ADT","1","") -> 1 | BD17: =IF(BB17="完了","1","") -> 1 | BE17: =BC17+BD17 -> 2 | BF17: 完了 | BG17: =IF($D17="ADT","1","") -> 1 | BH17: =IF(BF17="完了","1","") -> 1 | BI17: =BG17+BH17 -> 2 | BJ17: 完了 | BK17: =IF($D17="ADT","1","") -> 1 | BL17: =IF(BJ17="完了","1","") -> 1 | BM17: =BK17+BL17 -> 2 | BN17: 完了 | BO17: =IF($D17="ADT","1","") -> 1 | BP17: =IF(BN17="完了","1","") -> 1 | BQ17: =BO17+BP17 -> 2 | BR17: － | BS17: =IF($D17="ADT","1","") -> 1 | BT17: =IF(BR17="完了","1","") | BU17: =BS17+BT17 -> #VALUE! | BV17: 完了 | BW17: =IF($D17="ADT","1","") -> 1 | BX17: =IF(BV17="完了","1","") -> 1 | BY17: =BW17+BX17 -> 2 | BZ17: － | CA17: =IF($D17="ADT","1","") -> 1 | CB17: =IF(BZ17="完了","1","") | CC17: =CA17+CB17 -> #VALUE! | CD17: － | CE17: =IF($D17="ADT","1","") -> 1 | CF17: =IF(CD17="完了","1","") | CG17: =CE17+CF17 -> #VALUE! | CH17: O:\00 製造一部共通\横展開確認\設備異常報告\異常報告書(日文)\201406 | CI17: 0 | CK17: 259 | CM17: =IF(AZ17="","","CLOSE") -> CLOSE | CN17: =IF(F17="","",IF(COUNTIF(BB17:CE17,"未")=0,"CLOSE","")) -> CLOSE | CO17: 10 | CQ17: CLOSE | CR17: CLOSE | CS17: CLOSE | CT17: CLOSE | CU17: CLOSE | CV17: CLOSE | CW17: CLOSE | CX17: CLOSE
A18: 2 | B18: 41812 | C18: =MONTH(B18) -> 6 | D18: ADT | E18: JF | F18: 蔡明建 三路 | G18: =COUNTIF(T18:AV18,"要") -> 5 | H18: =IF(G18>0,"1","0") -> 1 | I18: =IF(AND(D18="ADT",H18="1"),"1","0") -> 1 | J18: =H18+I18 -> 2 | K18: =IF(CM18="CLOSE",1,"") -> 1 | L18: =J18+K18 -> 3 | M18: =IF(CN18="CLOSE",1,"") -> 1 | N18: =J18+M18 -> 3 | O18: 検査機系異常 | P18: WI | Q18: ・WI CAMERA#11波形異常 | R18: ・推測有落下物掉在CAMERA或光原條紋片上。 ※造成波形異常,影響了平坦度值。 | S18: ・拖出WI光源CAMERA基座,用AIR清除灰塵異物 ・制定連續平坦度惡化時確認流程並教育訓練 ・制定WI光源CAMERA基座拖出的手順並教育訓練. | T18: 要 | U18: =IF($D18="ADT","1","") -> 1 | V18: =IF(T18="要","1","") -> 1 | W18: =U18+V18 -> 2 | X18: 要 | Y18: =IF($D18="ADT","1","") -> 1 | Z18: =IF(X18="要","1","") -> 1 | AA18: =Y18+Z18 -> 2 | AB18: 要 | AC18: =IF($D18="ADT","1","") -> 1 | AD18: =IF(AB18="要","1","") -> 1 | AE18: =AC18+AD18 -> 2 | AF18: 要 | AG18: =IF($D18="ADT","1","") -> 1 | AH18: =IF(AF18="要","1","") -> 1 | AI18: =AG18+AH18 -> 2 | AJ18: － | AK18: =IF($D18="ADT","1","") -> 1 | AL18: =IF(AJ18="要","1","") | AM18: =AK18+AL18 -> #VALUE! | AN18: 要 | AO18: =IF($D18="ADT","1","") -> 1 | AP18: =IF(AN18="要","1","") -> 1 | AQ18: =AO18+AP18 -> 2 | AR18: － | AS18: =IF($D18="ADT","1","") -> 1 | AT18: =IF(AR18="要","1","") | AU18: =AS18+AT18 -> #VALUE! | AV18: － | AW18: =IF($D18="ADT","1","") -> 1 | AX18: =IF(AV18="要","1","") | AY18: =AW18+AX18 -> #VALUE! | AZ18: ・制定連續平坦度惡化時確認流程並教育訓練。 ・制定WI光源CAMERA基座拖出的手順並教育訓練. | BA18: 41838 | BB18: 完了 | BC18: =IF($D18="ADT","1","") -> 1 | BD18: =IF(BB18="完了","1","") -> 1 | BE18: =BC18+BD18 -> 2 | BF18: 完了 | BG18: =IF($D18="ADT","1","") -> 1 | BH18: =IF(BF18="完了","1","") -> 1 | BI18: =BG18+BH18 -> 2 | BJ18: 完了 | BK18: =IF($D18="ADT","1","") -> 1 | BL18: =IF(BJ18="完了","1","") -> 1 | BM18: =BK18+BL18 -> 2 | BN18: 完了 | BO18: =IF($D18="ADT","1","") -> 1 | BP18: =IF(BN18="完了","1","") -> 1 | BQ18: =BO18+BP18 -> 2 | BR18: － | BS18: =IF($D18="ADT","1","") -> 1 | BT18: =IF(BR18="完了","1","") | BU18: =BS18+BT18 -> #VALUE! | BV18: 完了 | BW18: =IF($D18="ADT","1","") -> 1 | BX18: =IF(BV18="完了","1","") -> 1 | BY18: =BW18+BX18 -> 2 | BZ18: － | CA18: =IF($D18="ADT","1","") -> 1 | CB18: =IF(BZ18="完了","1","") | CC18: =CA18+CB18 -> #VALUE! | CD18: － | CE18: =IF($D18="ADT","1","") -> 1 | CF18: =IF(CD18="完了","1","") | CG18: =CE18+CF18 -> #VALUE! | CH18: O:\00 製造一部共通\横展開確認\設備異常報告\異常報告書(日文) | CI18: 0 | CJ18: O:\00 製造一部共通\横展開確認\設備異常報告\異常報告書(日文) | CK18: 0 | CL18: O:\00 製造一部共通\横展開確認\設備異常報告\異常報告書(日文)\201406\WI台車抜き出しマニュアル | CM18: =IF(AZ18="","","CLOSE") -> CLOSE | CN18: =IF(F18="","",IF(COUNTIF(BB18:CE18,"未")=0,"CLOSE","")) -> CLOSE | CO18: 0 | CQ18: CLOSE | CR18: CLOSE | CS18: CLOSE | CT18: CLOSE | CU18: CLOSE | CV18: CLOSE | CW18: CLOSE | CX18: CLOSE
A19: 3 | B19: 41798 | C19: =MONTH(B19) -> 6 | D19: AFK | E19: LF | F19: 鄭吉勝 | G19: =COUNTIF(T19:AV19,"要") -> 7 | H19: =IF(G19>0,"1","0") -> 1 | I19: =IF(AND(D19="ADT",H19="1"),"1","0") -> 0 | J19: =H19+I19 -> 1 | K19: =IF(CM19="CLOSE",1,"") -> 1 | L19: =J19+K19 -> 2 | M19: =IF(CN19="CLOSE",1,"") -> 1 | N19: =J19+M19 -> 2 | O19: 電気系異常 | P19: 帯電Bar | Q19: ・LF 帯電装置過電流Trip異常 | R19: ・現場濕度高（65%）的状態下、電荷從帶電Bar樹脂部之裂縫、或是樹脂部的髒污處流竄到支架上，導致過電流並跳脫。 ・由於使用高電壓、絶縁部多少都會因為電氣流動的因素產生裂縫。 | S19: ・工事日時都針對帶電Bar樹脂部實施掃除。 ・裂縫實施Silicon Caulking。 ・帶電Bar的下方設置傳導體（SUS pipe） | T19: 要 | U19: =IF($D19="ADT","1","") | V19: =IF(T19="要","1","") -> 1 | W19: =U19+V19 -> #VALUE! | X19: 要 | Y19: =IF($D19="ADT","1","") | Z19: =IF(X19="要","1","") -> 1 | AA19: =Y19+Z19 -> #VALUE! | AB19: 要 | AC19: =IF($D19="ADT","1","") | AD19: =IF(AB19="要","1","") -> 1 | AE19: =AC19+AD19 -> #VALUE! | AF19: 要 | AG19: =IF($D19="ADT","1","") | AH19: =IF(AF19="要","1","") -> 1 | AI19: =AG19+AH19 -> #VALUE! | AJ19: 要 | AK19: =IF($D19="ADT","1","") | AL19: =IF(AJ19="要","1","") -> 1 | AM19: =AK19+AL19 -> #VALUE! | AN19: 要 | AO19: =IF($D19="ADT","1","") | AP19: =IF(AN19="要","1","") -> 1 | AQ19: =AO19+AP19 -> #VALUE! | AR19: 要 | AS19: =IF($D19="ADT","1","") | AT19: =IF(AR19="要","1","") -> 1 | AU19: =AS19+AT19 -> #VALUE! | AV19: － | AW19: =IF($D19="ADT","1","") | AX19: =IF(AV19="要","1","") | AY19: =AW19+AX19 -> #VALUE! | AZ19: ・帶電Bar數量確認 ・帶電Bar本體點檢 ・掃除/點檢頻度確認 | BA19: 41820 | BB19: 完了 | BC19: =IF($D19="ADT","1","") | BD19: =IF(BB19="完了","1","") -> 1 | BE19: =BC19+BD19 -> #VALUE! | BF19: 完了 | BG19: =IF($D19="ADT","1","") | BH19: =IF(BF19="完了","1","") -> 1 | BI19: =BG19+BH19 -> #VALUE! | BJ19: 完了 | BK19: =IF($D19="ADT","1","") | BL19: =IF(BJ19="完了","1","") -> 1 | BM19: =BK19+BL19 -> #VALUE! | BN19: 完了 | BO19: =IF($D19="ADT","1","") | BP19: =IF(BN19="完了","1","") -> 1 | BQ19: =BO19+BP19 -> #VALUE! | BR19: 完了 | BS19: =IF($D19="ADT","1","") | BT19: =IF(BR19="完了","1","") -> 1 | BU19: =BS19+BT19 -> #VALUE! | BV19: 完了 | BW19: =IF($D19="ADT","1","") | BX19: =IF(BV19="完了","1","") -> 1 | BY19: =BW19+BX19 -> #VALUE! | BZ19: 完了 | CA19: =IF($D19="ADT","1","") | CB19: =IF(BZ19="完了","1","") -> 1 | CC19: =CA19+CB19 -> #VALUE! | CD19: － | CE19: =IF($D19="ADT","1","") | CF19: =IF(CD19="完了","1","") | CG19: =CE19+CF19 -> #VALUE! | CH19: 異常報告書（日文）共有フォルダ\20140608 LF帯電装置過電流Trip異常_.xlsx | CI19: 0 | CK19: 2820 | CL19: ..\..\異常報告書(中文)\201406\●LF帯電装置過電流Trip異常-(C_E_J_K_Y_Z)帶電Bar確認.xls | CM19: =IF(AZ19="","","CLOSE") -> CLOSE | CN19: =IF(F19="","",IF(COUNTIF(BB19:CE19,"未")=0,"CLOSE","")) -> CLOSE | CO19: 95 | CQ19: CLOSE | CR19: CLOSE | CS19: CLOSE | CT19: CLOSE | CU19: CLOSE | CV19: CLOSE | CW19: CLOSE | CX19: CLOSE
A20: 4 | B20: 41820 | C20: =MONTH(B20) -> 6 | D20: 全拠点 | E20: 全ライン | F20: 三路 | G20: =COUNTIF(T20:AV20,"要") -> 6 | H20: =IF(G20>0,"1","0") -> 1 | I20: =IF(AND(D20="ADT",H20="1"),"1","0") -> 0 | J20: =H20+I20 -> 1 | K20: =IF(CM20="CLOSE",1,"") -> 1 | L20: =J20+K20 -> 2 | M20: =IF(CN20="CLOSE",1,"") -> 1 | N20: =J20+M20 -> 2 | O20: システム系異常 | P20: PAM | Q20: ・PL№無法連結 | R20: ・相同的生産指示書號碼進行2次以上J/C時，發生與PAM内部所持有的號碼不一致，造成PLNo無法連結的現象。 | S20: ・修正版的發行 | T20: 要 | U20: =IF($D20="ADT","1","") | V20: =IF(T20="要","1","") -> 1 | W20: =U20+V20 -> #VALUE! | X20: 要 | Y20: =IF($D20="ADT","1","") | Z20: =IF(X20="要","1","") -> 1 | AA20: =Y20+Z20 -> #VALUE! | AB20: 要 | AC20: =IF($D20="ADT","1","") | AD20: =IF(AB20="要","1","") -> 1 | AE20: =AC20+AD20 -> #VALUE! | AF20: 要 | AG20: =IF($D20="ADT","1","") | AH20: =IF(AF20="要","1","") -> 1 | AI20: =AG20+AH20 -> #VALUE! | AJ20: 要 | AK20: =IF($D20="ADT","1","") | AL20: =IF(AJ20="要","1","") -> 1 | AM20: =AK20+AL20 -> #VALUE! | AN20: 要 | AO20: =IF($D20="ADT","1","") | AP20: =IF(AN20="要","1","") -> 1 | AQ20: =AO20+AP20 -> #VALUE! | AR20: － | AS20: =IF($D20="ADT","1","") | AT20: =IF(AR20="要","1","") | AU20: =AS20+AT20 -> #VALUE! | AV20: － | AW20: =IF($D20="ADT","1","") | AX20: =IF(AV20="要","1","") | AY20: =AW20+AX20 -> #VALUE! | AZ20: ・修正版的發行 | BB20: 完了 | BC20: =IF($D20="ADT","1","") | BD20: =IF(BB20="完了","1","") -> 1 | BE20: =BC20+BD20 -> #VALUE! | BF20: 完了 | BG20: =IF($D20="ADT","1","") | BH20: =IF(BF20="完了","1","") -> 1 | BI20: =BG20+BH20 -> #VALUE! | BJ20: 完了 | BK20: =IF($D20="ADT","1","") | BL20: =IF(BJ20="完了","1","") -> 1 | BM20: =BK20+BL20 -> #VALUE! | BN20: 完了 | BO20: =IF($D20="ADT","1","") | BP20: =IF(BN20="完了","1","") -> 1 | BQ20: =BO20+BP20 -> #VALUE! | BR20: 完了 | BS20: =IF($D20="ADT","1","") | BT20: =IF(BR20="完了","1","") -> 1 | BU20: =BS20+BT20 -> #VALUE! | BV20: 完了 | BW20: =IF($D20="ADT","1","") | BX20: =IF(BV20="完了","1","") -> 1 | BY20: =BW20+BX20 -> #VALUE! | BZ20: － | CA20: =IF($D20="ADT","1","") | CB20: =IF(BZ20="完了","1","") | CC20: =CA20+CB20 -> #VALUE! | CD20: － | CE20: =IF($D20="ADT","1","") | CF20: =IF(CD20="完了","1","") | CG20: =CE20+CF20 -> #VALUE! | CH20: O:\00 製造一部共通\横展開確認\設備異常報告\異常報告書(日文)\201406\20140630 PAM改修.xls | CI20: 0 | CK20: 0 | CL20: O:\00 製造一部共通\横展開確認\設備異常報告\異常報告書(日文)\201406\20140630 PAM改修.xls | CM20: =IF(AZ20="","","CLOSE") -> CLOSE | CN20: =IF(F20="","",IF(COUNTIF(BB20:CE20,"未")=0,"CLOSE","")) -> CLOSE | CO20: 0 | CQ20: CLOSE | CR20: CLOSE | CS20: CLOSE | CT20: CLOSE | CU20: CLOSE | CV20: KF冷修導入預定！方針已決定一時COLSE | CW20: CLOSE | CX20: CLOSE
A21: 5 | B21: 41823 | C21: =MONTH(B21) -> 7 | D21: ADT | E21: CF | F21: 蔵光 | G21: =COUNTIF(T21:AV21,"要") -> 6 | H21: =IF(G21>0,"1","0") -> 1 | I21: =IF(AND(D21="ADT",H21="1"),"1","0") -> 1 | J21: =H21+I21 -> 2 | K21: =IF(CM21="CLOSE",1,"") -> 1 | L21: =J21+K21 -> 3 | M21: =IF(CN21="CLOSE",1,"") -> 1 | N21: =J21+M21 -> 3 | O21: 機械系異常 | P21: 本線C/V | Q21: ・CHAIN断裂異常 (2014/05/22) | R21: ・漏掉冷修後、初期伸長等的点検・確認 | S21: ・CHAIN鬆弛部位的可視化 | T21: 要 | U21: =IF($D21="ADT","1","") -> 1 | V21: =IF(T21="要","1","") -> 1 | W21: =U21+V21 -> 2 | X21: 要 | Y21: =IF($D21="ADT","1","") -> 1 | Z21: =IF(X21="要","1","") -> 1 | AA21: =Y21+Z21 -> 2 | AB21: 要 | AC21: =IF($D21="ADT","1","") -> 1 | AD21: =IF(AB21="要","1","") -> 1 | AE21: =AC21+AD21 -> 2 | AF21: 要 | AG21: =IF($D21="ADT","1","") -> 1 | AH21: =IF(AF21="要","1","") -> 1 | AI21: =AG21+AH21 -> 2 | AJ21: 要 | AK21: =IF($D21="ADT","1","") -> 1 | AL21: =IF(AJ21="要","1","") -> 1 | AM21: =AK21+AL21 -> 2 | AN21: 要 | AO21: =IF($D21="ADT","1","") -> 1 | AP21: =IF(AN21="要","1","") -> 1 | AQ21: =AO21+AP21 -> 2 | AR21: － | AS21: =IF($D21="ADT","1","") -> 1 | AT21: =IF(AR21="要","1","") | AU21: =AS21+AT21 -> #VALUE! | AV21: － | AW21: =IF($D21="ADT","1","") -> 1 | AX21: =IF(AV21="要","1","") | AY21: =AW21+AX21 -> #VALUE! | AZ21: ・CHAIN鬆弛部位的可視化 ・LINE SHAFT駆動部的可視化 ※（2014/7/24追記） | BB21: 完了 | BC21: =IF($D21="ADT","1","") -> 1 | BD21: =IF(BB21="完了","1","") -> 1 | BE21: =BC21+BD21 -> 2 | BF21: 完了 | BG21: =IF($D21="ADT","1","") -> 1 | BH21: =IF(BF21="完了","1","") -> 1 | BI21: =BG21+BH21 -> 2 | BJ21: 完了 | BK21: =IF($D21="ADT","1","") -> 1 | BL21: =IF(BJ21="完了","1","") -> 1 | BM21: =BK21+BL21 -> 2 | BN21: 完了 | BO21: =IF($D21="ADT","1","") -> 1 | BP21: =IF(BN21="完了","1","") -> 1 | BQ21: =BO21+BP21 -> 2 | BR21: 完了 | BS21: =IF($D21="ADT","1","") -> 1 | BT21: =IF(BR21="完了","1","") -> 1 | BU21: =BS21+BT21 -> 2 | BV21: 完了 | BW21: =IF($D21="ADT","1","") -> 1 | BX21: =IF(BV21="完了","1","") -> 1 | BY21: =BW21+BX21 -> 2 | BZ21: － | CA21: =IF($D21="ADT","1","") -> 1 | CB21: =IF(BZ21="完了","1","") | CC21: =CA21+CB21 -> #VALUE! | CD21: － | CE21: =IF($D21="ADT","1","") -> 1 | CF21: =IF(CD21="完了","1","") | CG21: =CE21+CF21 -> #VALUE! | CH21: 異常報告書（日文）共有フォルダ\20140522CF 本線CV駆動チェーン断裂異常.xlsx | CI21: 0 | CK21: 5531 | CL21: \\172.18.154.188\adt_public\08_部門情報\8552_素板製造-設備技術\【設備技術修繕紀錄】\03機械\各窯情報資料\20140522 CF本線段ROLL停止--各窯橫展開2014.0606.xls | CM21: =IF(AZ21="","","CLOSE") -> CLOSE | CN21: =IF(F21="","",IF(COUNTIF(BB21:CE21,"未")=0,"CLOSE","")) -> CLOSE | CO21: 259 | CQ21: CLOSE | CR21: CLOSE | CS21: CLOSE | CT21: CLOSE | CU21: CLOSE | CV21: CLOSE | CW21: CLOSE | CX21: CLOSE
A22: 6 | B22: 41823 | C22: =MONTH(B22) -> 7 | D22: ADT | E22: CF | F22: 蔵光 | G22: =COUNTIF(T22:AV22,"要") -> 6 | H22: =IF(G22>0,"1","0") -> 1 | I22: =IF(AND(D22="ADT",H22="1"),"1","0") -> 1 | J22: =H22+I22 -> 2 | K22: =IF(CM22="CLOSE",1,"") -> 1 | L22: =J22+K22 -> 3 | M22: =IF(CN22="CLOSE",1,"") -> 1 | N22: =J22+M22 -> 3 | O22: 機械系異常 | P22: 本線C/V | Q22: ・CHAIN断裂異常 (2014/05/22) | R22: ・漏掉冷修後、初期伸長等的点検・確認 | S22: ・CHAIN GUIDE的改造 | T22: 要 | U22: =IF($D22="ADT","1","") -> 1 | V22: =IF(T22="要","1","") -> 1 | W22: =U22+V22 -> 2 | X22: 要 | Y22: =IF($D22="ADT","1","") -> 1 | Z22: =IF(X22="要","1","") -> 1 | AA22: =Y22+Z22 -> 2 | AB22: 要 | AC22: =IF($D22="ADT","1","") -> 1 | AD22: =IF(AB22="要","1","") -> 1 | AE22: =AC22+AD22 -> 2 | AF22: 要 | AG22: =IF($D22="ADT","1","") -> 1 | AH22: =IF(AF22="要","1","") -> 1 | AI22: =AG22+AH22 -> 2 | AJ22: 要 | AK22: =IF($D22="ADT","1","") -> 1 | AL22: =IF(AJ22="要","1","") -> 1 | AM22: =AK22+AL22 -> 2 | AN22: 要 | AO22: =IF($D22="ADT","1","") -> 1 | AP22: =IF(AN22="要","1","") -> 1 | AQ22: =AO22+AP22 -> 2 | AR22: － | AS22: =IF($D22="ADT","1","") -> 1 | AT22: =IF(AR22="要","1","") | AU22: =AS22+AT22 -> #VALUE! | AV22: － | AW22: =IF($D22="ADT","1","") -> 1 | AX22: =IF(AV22="要","1","") | AY22: =AW22+AX22 -> #VALUE! | AZ22: ・CHAIN GUIDE的改造 | BB22: 完了 | BC22: =IF($D22="ADT","1","") -> 1 | BD22: =IF(BB22="完了","1","") -> 1 | BE22: =BC22+BD22 -> 2 | BF22: 完了 | BG22: =IF($D22="ADT","1","") -> 1 | BH22: =IF(BF22="完了","1","") -> 1 | BI22: =BG22+BH22 -> 2 | BJ22: 完了 | BK22: =IF($D22="ADT","1","") -> 1 | BL22: =IF(BJ22="完了","1","") -> 1 | BM22: =BK22+BL22 -> 2 | BN22: 完了 | BO22: =IF($D22="ADT","1","") -> 1 | BP22: =IF(BN22="完了","1","") -> 1 | BQ22: =BO22+BP22 -> 2 | BR22: 完了 | BS22: =IF($D22="ADT","1","") -> 1 | BT22: =IF(BR22="完了","1","") -> 1 | BU22: =BS22+BT22 -> 2 | BV22: 完了 | BW22: =IF($D22="ADT","1","") -> 1 | BX22: =IF(BV22="完了","1","") -> 1 | BY22: =BW22+BX22 -> 2 | BZ22: － | CA22: =IF($D22="ADT","1","") -> 1 | CB22: =IF(BZ22="完了","1","") | CC22: =CA22+CB22 -> #VALUE! | CD22: － | CE22: =IF($D22="ADT","1","") -> 1 | CF22: =IF(CD22="完了","1","") | CG22: =CE22+CF22 -> #VALUE! | CH22: \\172.18.154.189\mfg_public\00 製造一部共通\横展開確認\設備異常報告\異常報告書(日文)\201405\20140522CF 本線CV駆動チェーン断裂異常.xls | CL22: \\172.18.154.188\adt_public\08_部門情報\8552_素板製造-設備技術\【設備技術修繕紀錄】\03機械\各窯情報資料\20140522 CF本線段ROLL停止--各窯橫展開2014.0606.xls | CM22: =IF(AZ22="","","CLOSE") -> CLOSE | CN22: =IF(F22="","",IF(COUNTIF(BB22:CE22,"未")=0,"CLOSE","")) -> CLOSE | CQ22: CLOSE | CR22: CLOSE | CS22: CLOSE | CT22: CLOSE | CU22: CLOSE | CV22: CLOSE | CW22: CLOSE | CX22: CLOSE
A23: 7 | B23: 41823 | C23: =MONTH(B23) -> 7 | D23: ADT | E23: EF | F23: 万代 | G23: =COUNTIF(T23:AV23,"要") -> 6 | H23: =IF(G23>0,"1","0") -> 1 | I23: =IF(AND(D23="ADT",H23="1"),"1","0") -> 1 | J23: =H23+I23 -> 2 | K23: =IF(CM23="CLOSE",1,"") -> 1 | L23: =J23+K23 -> 3 | M23: =IF(CN23="CLOSE",1,"") -> 1 | N23: =J23+M23 -> 3 | O23: 機械系異常 | P23: 本線C/V | Q23: ・増速SHAFT折損 | R23: ・強度不足 | S23: ・本線増速立起部的CV-Roll SHAFT材質由SS400 25φ變更為SCM435 40φ | T23: 要 | U23: =IF($D23="ADT","1","") -> 1 | V23: =IF(T23="要","1","") -> 1 | W23: =U23+V23 -> 2 | X23: 要 | Y23: =IF($D23="ADT","1","") -> 1 | Z23: =IF(X23="要","1","") -> 1 | AA23: =Y23+Z23 -> 2 | AB23: 要 | AC23: =IF($D23="ADT","1","") -> 1 | AD23: =IF(AB23="要","1","") -> 1 | AE23: =AC23+AD23 -> 2 | AF23: 要 | AG23: =IF($D23="ADT","1","") -> 1 | AH23: =IF(AF23="要","1","") -> 1 | AI23: =AG23+AH23 -> 2 | AJ23: 要 | AK23: =IF($D23="ADT","1","") -> 1 | AL23: =IF(AJ23="要","1","") -> 1 | AM23: =AK23+AL23 -> 2 | AN23: 要 | AO23: =IF($D23="ADT","1","") -> 1 | AP23: =IF(AN23="要","1","") -> 1 | AQ23: =AO23+AP23 -> 2 | AR23: － | AS23: =IF($D23="ADT","1","") -> 1 | AT23: =IF(AR23="要","1","") | AU23: =AS23+AT23 -> #VALUE! | AV23: － | AW23: =IF($D23="ADT","1","") -> 1 | AX23: =IF(AV23="要","1","") | AY23: =AW23+AX23 -> #VALUE! | AZ23: ・更換SHAFT材質変更的roll | BB23: 完了 | BC23: =IF($D23="ADT","1","") -> 1 | BD23: =IF(BB23="完了","1","") -> 1 | BE23: =BC23+BD23 -> 2 | BF23: 完了 | BG23: =IF($D23="ADT","1","") -> 1 | BH23: =IF(BF23="完了","1","") -> 1 | BI23: =BG23+BH23 -> 2 | BJ23: 完了 | BK23: =IF($D23="ADT","1","") -> 1 | BL23: =IF(BJ23="完了","1","") -> 1 | BM23: =BK23+BL23 -> 2 | BN23: 完了 | BO23: =IF($D23="ADT","1","") -> 1 | BP23: =IF(BN23="完了","1","") -> 1 | BQ23: =BO23+BP23 -> 2 | BR23: 完了 | BS23: =IF($D23="ADT","1","") -> 1 | BT23: =IF(BR23="完了","1","") -> 1 | BU23: =BS23+BT23 -> 2 | BV23: 完了 | BW23: =IF($D23="ADT","1","") -> 1 | BX23: =IF(BV23="完了","1","") -> 1 | BY23: =BW23+BX23 -> 2 | BZ23: － | CA23: =IF($D23="ADT","1","") -> 1 | CB23: =IF(BZ23="完了","1","") | CC23: =CA23+CB23 -> #VALUE! | CD23: － | CE23: =IF($D23="ADT","1","") -> 1 | CF23: =IF(CD23="完了","1","") | CG23: =CE23+CF23 -> #VALUE! | CH23: \\172.18.154.189\mfg_public\00 製造一部共通\横展開確認\設備異常報告\異常報告書(日文)\201406\20140612EF EF本線増速CV＃4駆動ロールシャフト折損.xls | CI23: 1 | CK23: 0 | CM23: =IF(AZ23="","","CLOSE") -> CLOSE | CN23: =IF(F23="","",IF(COUNTIF(BB23:CE23,"未")=0,"CLOSE","")) -> CLOSE | CO23: 120 | CQ23: 機械回應：備品已到貨預定於1月份之工事日進行。 (因為YZ ROLL較短預計冷修時更換) | CR23: 機械回應：備品已到貨；因ZF工事日以0.2T相關改造優先，預定於4月份0.2T採板結束後之工事日進行。 (因為YZ ROLL較短預計冷修時更換) | CS23: CLOSE | CT23: 預計12/08擔當者會議提出討論，待會議後進行進度更新 | CU23: CLOSE | CV23: CLOSE | CW23: CLOSE | CX23: CLOSE | CY23: 方針CLOSE（冷修対応、来年費用など）
A24: 8 | B24: 41827 | C24: =MONTH(B24) -> 7 | D24: ADT | E24: EF | F24: 鄭吉勝 | G24: =COUNTIF(T24:AV24,"要") -> 6 | H24: =IF(G24>0,"1","0") -> 1 | I24: =IF(AND(D24="ADT",H24="1"),"1","0") -> 1 | J24: =H24+I24 -> 2 | K24: =IF(CM24="CLOSE",1,"") -> 1 | L24: =J24+K24 -> 3 | M24: =IF(CN24="CLOSE",1,"") -> 1 | N24: =J24+M24 -> 3 | O24: 機械系異常 | P24: BrC/V | Q24: 2Br増速C/V SHAFT破損異常 | R24: ・強度不足 | S24: ・由於現在R5加工的東西變為主流所以實施横展開。(入荷状況要確認） | T24: 要 | U24: =IF($D24="ADT","1","") -> 1 | V24: =IF(T24="要","1","") -> 1 | W24: =U24+V24 -> 2 | X24: 要 | Y24: =IF($D24="ADT","1","") -> 1 | Z24: =IF(X24="要","1","") -> 1 | AA24: =Y24+Z24 -> 2 | AB24: 要 | AC24: =IF($D24="ADT","1","") -> 1 | AD24: =IF(AB24="要","1","") -> 1 | AE24: =AC24+AD24 -> 2 | AF24: 要 | AG24: =IF($D24="ADT","1","") -> 1 | AH24: =IF(AF24="要","1","") -> 1 | AI24: =AG24+AH24 -> 2 | AJ24: 要 | AK24: =IF($D24="ADT","1","") -> 1 | AL24: =IF(AJ24="要","1","") -> 1 | AM24: =AK24+AL24 -> 2 | AN24: 要 | AO24: =IF($D24="ADT","1","") -> 1 | AP24: =IF(AN24="要","1","") -> 1 | AQ24: =AO24+AP24 -> 2 | AR24: － | AS24: =IF($D24="ADT","1","") -> 1 | AT24: =IF(AR24="要","1","") | AU24: =AS24+AT24 -> #VALUE! | AV24: － | AW24: =IF($D24="ADT","1","") -> 1 | AX24: =IF(AV24="要","1","") | AY24: =AW24+AX24 -> #VALUE! | AZ24: ・更換為SHAFT材質変更的roll (個別駆動後連結駆動的第一支（増速No.5）→SCM435（shaft径維持現狀） 利用全窯工事日時進行更新) | BB24: 完了 | BC24: =IF($D24="ADT","1","") -> 1 | BD24: =IF(BB24="完了","1","") -> 1 | BE24: =BC24+BD24 -> 2 | BF24: 完了 | BG24: =IF($D24="ADT","1","") -> 1 | BH24: =IF(BF24="完了","1","") -> 1 | BI24: =BG24+BH24 -> 2 | BJ24: 完了 | BK24: =IF($D24="ADT","1","") -> 1 | BL24: =IF(BJ24="完了","1","") -> 1 | BM24: =BK24+BL24 -> 2 | BN24: 完了 | BO24: =IF($D24="ADT","1","") -> 1 | BP24: =IF(BN24="完了","1","") -> 1 | BQ24: =BO24+BP24 -> 2 | BR24: 完了 | BS24: =IF($D24="ADT","1","") -> 1 | BT24: =IF(BR24="完了","1","") -> 1 | BU24: =BS24+BT24 -> 2 | BV24: 完了 | BW24: =IF($D24="ADT","1","") -> 1 | BX24: =IF(BV24="完了","1","") -> 1 | BY24: =BW24+BX24 -> 2 | BZ24: － | CA24: =IF($D24="ADT","1","") -> 1 | CB24: =IF(BZ24="完了","1","") | CC24: =CA24+CB24 -> #VALUE! | CD24: － | CE24: =IF($D24="ADT","1","") -> 1 | CF24: =IF(CD24="完了","1","") | CG24: =CE24+CF24 -> #VALUE! | CH24: 異常報告書（日文）共有フォルダ\其他\20130813EF (改定版）2Br増速CVシャフト破損トラフ゛ル.xlsx | CI24: 1 | CK24: 2.8 | CM24: =IF(AZ24="","","CLOSE") -> CLOSE | CN24: =IF(F24="","",IF(COUNTIF(BB24:CE24,"未")=0,"CLOSE","")) -> CLOSE | CQ24: 機械回應：備品已到貨預定於1月份之工事日進行。 (再確認更換時間) 冷修対応 10/1~所以先行結案完了 | CR24: 機械回應：備品已到貨；因ZF工事日以0.2T相關改造優先，預定於4月份0.2T採板結束後之工事日進行。 6/8已經更換完成 | CS24: CLOSE | CT24: CLOSE | CU24: CLOSE | CV24: CLOSE | CW24: CLOSE | CX24: CLOSE | CY24: 方針CLOSE（冷修対応、来年費用など）
A25: 9 | B25: 41809 | C25: =MONTH(B25) -> 6 | D25: AFK | E25: AFK OFF#2 | F25: 鄭吉勝 | G25: =COUNTIF(T25:AV25,"要") -> 8 | H25: =IF(G25>0,"1","0") -> 1 | I25: =IF(AND(D25="ADT",H25="1"),"1","0") -> 0 | J25: =H25+I25 -> 1 | K25: =IF(CM25="CLOSE",1,"") -> 1 | L25: =J25+K25 -> 2 | M25: =IF(CN25="CLOSE",1,"") -> 1 | N25: =J25+M25 -> 2 | O25: 電気系異常 | P25: OFF#2Line | Q25: X軸（電纜線燒毀）伺服機構異常 | R25: ・原因調查確認中！ | S25: ・電纜線的更換。 ・次回定修點檢確認 | T25: 要 | U25: =IF($D25="ADT","1","") | V25: =IF(T25="要","1","") -> 1 | W25: =U25+V25 -> #VALUE! | X25: 要 | Y25: =IF($D25="ADT","1","") | Z25: =IF(X25="要","1","") -> 1 | AA25: =Y25+Z25 -> #VALUE! | AB25: 要 | AC25: =IF($D25="ADT","1","") | AD25: =IF(AB25="要","1","") -> 1 | AE25: =AC25+AD25 -> #VALUE! | AF25: 要 | AG25: =IF($D25="ADT","1","") | AH25: =IF(AF25="要","1","") -> 1 | AI25: =AG25+AH25 -> #VALUE! | AJ25: 要 | AK25: =IF($D25="ADT","1","") | AL25: =IF(AJ25="要","1","") -> 1 | AM25: =AK25+AL25 -> #VALUE! | AN25: 要 | AO25: =IF($D25="ADT","1","") | AP25: =IF(AN25="要","1","") -> 1 | AQ25: =AO25+AP25 -> #VALUE! | AR25: 要 | AS25: =IF($D25="ADT","1","") | AT25: =IF(AR25="要","1","") -> 1 | AU25: =AS25+AT25 -> #VALUE! | AV25: 要 | AW25: =IF($D25="ADT","1","") | AX25: =IF(AV25="要","1","") -> 1 | AY25: =AW25+AX25 -> #VALUE! | AZ25: ・確認橫切機CABLEVEYOR 1.電纜線於CABLEVEYOR中排列是否整齊。 2.CABLEVEYOR中電纜線有無破損狀態。 3.CABLEVEYOR中電纜線有無皺摺或彎曲變形。 4.綑綁電纜線的線材（束帶）是否有斷掉。 | BA25: 41871 | BB25: 完了 | BC25: =IF($D25="ADT","1","") | BD25: =IF(BB25="完了","1","") -> 1 | BE25: =BC25+BD25 -> #VALUE! | BF25: 完了 | BG25: =IF($D25="ADT","1","") | BH25: =IF(BF25="完了","1","") -> 1 | BI25: =BG25+BH25 -> #VALUE! | BJ25: 完了 | BK25: =IF($D25="ADT","1","") | BL25: =IF(BJ25="完了","1","") -> 1 | BM25: =BK25+BL25 -> #VALUE! | BN25: 完了 | BO25: =IF($D25="ADT","1","") | BP25: =IF(BN25="完了","1","") -> 1 | BQ25: =BO25+BP25 -> #VALUE! | BR25: 完了 | BS25: =IF($D25="ADT","1","") | BT25: =IF(BR25="完了","1","") -> 1 | BU25: =BS25+BT25 -> #VALUE! | BV25: 完了 | BW25: =IF($D25="ADT","1","") | BX25: =IF(BV25="完了","1","") -> 1 | BY25: =BW25+BX25 -> #VALUE! | BZ25: 完了 | CA25: =IF($D25="ADT","1","") | CB25: =IF(BZ25="完了","1","") -> 1 | CC25: =CA25+CB25 -> #VALUE! | CD25: 完了 | CE25: =IF($D25="ADT","1","") | CF25: =IF(CD25="完了","1","") -> 1 | CG25: =CE25+CF25 -> #VALUE! | CH25: 異常報告書（日文）共有フォルダ\其他\20140619OFF切 OFF切2LineX軸（ケーブル焼損）サーボ異常.xlsx | CI25: 0 | CK25: 615 | CL25: 異常報告書（日文）共有フォルダ\其他\●AFK-OFF切#2LineX軸(電纜線焼毀)伺服機構異常-(C_E_J_K_Y_Z)CABLE Bear確認.xlsx | CM25: =IF(AZ25="","","CLOSE") -> CLOSE | CN25: =IF(F25="","",IF(COUNTIF(BB25:CE25,"未")=0,"CLOSE","")) -> CLOSE | CO25: 165 | CQ25: CLOSE | CR25: CLOSE | CS25: CLOSE | CT25: CLOSE | CU25: CLOSE | CV25: CLOSE | CW25: CLOSE | CX25: CLOSE
A26: 10 | B26: 41837 | C26: =MONTH(B26) -> 7 | D26: ADT | E26: YF | F26: 佐倉 曾志宏 | G26: =COUNTIF(T26:AV26,"要") -> 6 | H26: =IF(G26>0,"1","0") -> 1 | I26: =IF(AND(D26="ADT",H26="1"),"1","0") -> 1 | J26: =H26+I26 -> 2 | K26: =IF(CM26="CLOSE",1,"") -> 1 | L26: =J26+K26 -> 3 | M26: =IF(CN26="CLOSE",1,"") -> 1 | N26: =J26+M26 -> 3 | O26: その他改善 | P26: BR FTC/V | Q26: PAD捲起造成板厚計波形異常 | R26: PAD的末端剥落 | S26: ・在PAD貼付作業標準書追加記載貼付方式的使用須知 ・在設備点検作業標準書的PAD点検部位追加關於剥落的內容 | T26: 要 | U26: =IF($D26="ADT","1","") -> 1 | V26: =IF(T26="要","1","") -> 1 | W26: =U26+V26 -> 2 | X26: 要 | Y26: =IF($D26="ADT","1","") -> 1 | Z26: =IF(X26="要","1","") -> 1 | AA26: =Y26+Z26 -> 2 | AB26: 要 | AC26: =IF($D26="ADT","1","") -> 1 | AD26: =IF(AB26="要","1","") -> 1 | AE26: =AC26+AD26 -> 2 | AF26: 要 | AG26: =IF($D26="ADT","1","") -> 1 | AH26: =IF(AF26="要","1","") -> 1 | AI26: =AG26+AH26 -> 2 | AJ26: 要 | AK26: =IF($D26="ADT","1","") -> 1 | AL26: =IF(AJ26="要","1","") -> 1 | AM26: =AK26+AL26 -> 2 | AN26: 要 | AO26: =IF($D26="ADT","1","") -> 1 | AP26: =IF(AN26="要","1","") -> 1 | AQ26: =AO26+AP26 -> 2 | AR26: － | AS26: =IF($D26="ADT","1","") -> 1 | AT26: =IF(AR26="要","1","") | AU26: =AS26+AT26 -> #VALUE! | AV26: － | AW26: =IF($D26="ADT","1","") -> 1 | AX26: =IF(AV26="要","1","") | AY26: =AW26+AX26 -> #VALUE! | AZ26: 讓整備班、三交代看一遍発生状況的資料，也在巡檢時讓他們看Br板厚計下PAD末端部是否有剥落狀況。 | BA26: 41845 | BB26: 完了 | BC26: =IF($D26="ADT","1","") -> 1 | BD26: =IF(BB26="完了","1","") -> 1 | BE26: =BC26+BD26 -> 2 | BF26: 完了 | BG26: =IF($D26="ADT","1","") -> 1 | BH26: =IF(BF26="完了","1","") -> 1 | BI26: =BG26+BH26 -> 2 | BJ26: 完了 | BK26: =IF($D26="ADT","1","") -> 1 | BL26: =IF(BJ26="完了","1","") -> 1 | BM26: =BK26+BL26 -> 2 | BN26: 完了 | BO26: =IF($D26="ADT","1","") -> 1 | BP26: =IF(BN26="完了","1","") -> 1 | BQ26: =BO26+BP26 -> 2 | BR26: 完了 | BS26: =IF($D26="ADT","1","") -> 1 | BT26: =IF(BR26="完了","1","") -> 1 | BU26: =BS26+BT26 -> 2 | BV26: 完了 | BW26: =IF($D26="ADT","1","") -> 1 | BX26: =IF(BV26="完了","1","") -> 1 | BY26: =BW26+BX26 -> 2 | BZ26: － | CA26: =IF($D26="ADT","1","") -> 1 | CB26: =IF(BZ26="完了","1","") | CC26: =CA26+CB26 -> #VALUE! | CD26: － | CE26: =IF($D26="ADT","1","") -> 1 | CF26: =IF(CD26="完了","1","") | CG26: =CE26+CF26 -> #VALUE! | CH26: \\172.18.154.189\mfg_public\00 製造一部共通\横展開確認\設備異常報告\異常報告書(日文)\201407\20140701 YF1Br板厚計波形異常.xls | CI26: 1 | CK26: 0 | CM26: =IF(AZ26="","","CLOSE") -> CLOSE | CN26: =IF(F26="","",IF(COUNTIF(BB26:CE26,"未")=0,"CLOSE","")) -> CLOSE | CO26: 0 | CQ26: CLOSE | CR26: CLOSE | CS26: CLOSE | CT26: CLOSE | CU26: CLOSE | CV26: CLOSE | CW26: CLOSE | CX26: CLOSE
A27: 11 | B27: 41838 | C27: =MONTH(B27) -> 7 | D27: ADT | E27: KF | F27: 鄭吉勝 | G27: =COUNTIF(T27:AV27,"要") -> 6 | H27: =IF(G27>0,"1","0") -> 1 | I27: =IF(AND(D27="ADT",H27="1"),"1","0") -> 1 | J27: =H27+I27 -> 2 | K27: =IF(CM27="CLOSE",1,"") -> 1 | L27: =J27+K27 -> 3 | M27: =IF(CN27="CLOSE",1,"") -> 1 | N27: =J27+M27 -> 3 | O27: 機械系異常 | P27: 循環C/V | Q27: KF循環系CV CARRIER ROLL磨損 | R27: ・碎玻璃或粉塵堆積 | S27: ・定期巡檢時發現CARRIER ROLL有碎玻璃堆積 立即依賴機械G協助掃除 ・制定聯絡的程序 | T27: 要 | U27: =IF($D27="ADT","1","") -> 1 | V27: =IF(T27="要","1","") -> 1 | W27: =U27+V27 -> 2 | X27: 要 | Y27: =IF($D27="ADT","1","") -> 1 | Z27: =IF(X27="要","1","") -> 1 | AA27: =Y27+Z27 -> 2 | AB27: 要 | AC27: =IF($D27="ADT","1","") -> 1 | AD27: =IF(AB27="要","1","") -> 1 | AE27: =AC27+AD27 -> 2 | AF27: 要 | AG27: =IF($D27="ADT","1","") -> 1 | AH27: =IF(AF27="要","1","") -> 1 | AI27: =AG27+AH27 -> 2 | AJ27: 要 | AK27: =IF($D27="ADT","1","") -> 1 | AL27: =IF(AJ27="要","1","") -> 1 | AM27: =AK27+AL27 -> 2 | AN27: 要 | AO27: =IF($D27="ADT","1","") -> 1 | AP27: =IF(AN27="要","1","") -> 1 | AQ27: =AO27+AP27 -> 2 | AR27: － | AS27: =IF($D27="ADT","1","") -> 1 | AT27: =IF(AR27="要","1","") | AU27: =AS27+AT27 -> #VALUE! | AV27: － | AW27: =IF($D27="ADT","1","") -> 1 | AX27: =IF(AV27="要","1","") | AY27: =AW27+AX27 -> #VALUE! | AZ27: ・CARRIER ROLL點檢對應流程說明。 ・ 對應作業步驟說明。 | BA27: 41852 | BB27: 完了 | BC27: =IF($D27="ADT","1","") -> 1 | BD27: =IF(BB27="完了","1","") -> 1 | BE27: =BC27+BD27 -> 2 | BF27: 完了 | BG27: =IF($D27="ADT","1","") -> 1 | BH27: =IF(BF27="完了","1","") -> 1 | BI27: =BG27+BH27 -> 2 | BJ27: 完了 | BK27: =IF($D27="ADT","1","") -> 1 | BL27: =IF(BJ27="完了","1","") -> 1 | BM27: =BK27+BL27 -> 2 | BN27: 完了 | BO27: =IF($D27="ADT","1","") -> 1 | BP27: =IF(BN27="完了","1","") -> 1 | BQ27: =BO27+BP27 -> 2 | BR27: 完了 | BS27: =IF($D27="ADT","1","") -> 1 | BT27: =IF(BR27="完了","1","") -> 1 | BU27: =BS27+BT27 -> 2 | BV27: 完了 | BW27: =IF($D27="ADT","1","") -> 1 | BX27: =IF(BV27="完了","1","") -> 1 | BY27: =BW27+BX27 -> 2 | BZ27: － | CA27: =IF($D27="ADT","1","") -> 1 | CB27: =IF(BZ27="完了","1","") | CC27: =CA27+CB27 -> #VALUE! | CD27: － | CE27: =IF($D27="ADT","1","") -> 1 | CF27: =IF(CD27="完了","1","") | CG27: =CE27+CF27 -> #VALUE! | CI27: 0 | CK27: 0 | CL27: 異常報告書（日文）共有フォルダ\其他\20140718 KF循環系CVキャリアROLL磨損橫展開連絡.xlsx | CM27: =IF(AZ27="","","CLOSE") -> CLOSE | CN27: =IF(F27="","",IF(COUNTIF(BB27:CE27,"未")=0,"CLOSE","")) -> CLOSE | CO27: 0 | CQ27: CLOSE | CR27: CLOSE | CS27: CLOSE | CT27: CLOSE | CU27: CLOSE | CV27: CLOSE | CW27: CLOSE | CX27: CLOSE
A28: 12 | B28: 41824 | C28: =MONTH(B28) -> 7 | D28: AFK | E28: HF | F28: 浅原 | G28: =COUNTIF(T28:AV28,"要") -> 2 | H28: =IF(G28>0,"1","0") -> 1 | I28: =IF(AND(D28="ADT",H28="1"),"1","0") -> 0 | J28: =H28+I28 -> 1 | K28: =IF(CM28="CLOSE",1,"") -> 1 | L28: =J28+K28 -> 2 | M28: =IF(CN28="CLOSE",1,"") -> 1 | N28: =J28+M28 -> 2 | O28: システム系異常 | P28: ACE | Q28: ACE通信異常 | R28: LAN驅動程序問題 | S28: LAN驅動程序更新 | T28: 要 | U28: =IF($D28="ADT","1","") | V28: =IF(T28="要","1","") -> 1 | W28: =U28+V28 -> #VALUE! | X28: 要 | Y28: =IF($D28="ADT","1","") | Z28: =IF(X28="要","1","") -> 1 | AA28: =Y28+Z28 -> #VALUE! | AB28: 不要 | AC28: =IF($D28="ADT","1","") | AD28: =IF(AB28="要","1","") | AE28: =AC28+AD28 -> #VALUE! | AF28: 不要 | AG28: =IF($D28="ADT","1","") | AH28: =IF(AF28="要","1","") | AI28: =AG28+AH28 -> #VALUE! | AJ28: 不要 | AK28: =IF($D28="ADT","1","") | AL28: =IF(AJ28="要","1","") | AM28: =AK28+AL28 -> #VALUE! | AN28: 不要 | AO28: =IF($D28="ADT","1","") | AP28: =IF(AN28="要","1","") | AQ28: =AO28+AP28 -> #VALUE! | AR28: － | AS28: =IF($D28="ADT","1","") | AT28: =IF(AR28="要","1","") | AU28: =AS28+AT28 -> #VALUE! | AV28: － | AW28: =IF($D28="ADT","1","") | AX28: =IF(AV28="要","1","") | AY28: =AW28+AX28 -> #VALUE! | AZ28: LAN驅動程序更新。 8/11再発。対策未定。 | BB28: 完了 | BC28: =IF($D28="ADT","1","") | BD28: =IF(BB28="完了","1","") -> 1 | BE28: =BC28+BD28 -> #VALUE! | BF28: 完了 | BG28: =IF($D28="ADT","1","") | BH28: =IF(BF28="完了","1","") -> 1 | BI28: =BG28+BH28 -> #VALUE! | BJ28: － | BK28: =IF($D28="ADT","1","") | BL28: =IF(BJ28="完了","1","") | BM28: =BK28+BL28 -> #VALUE! | BN28: － | BO28: =IF($D28="ADT","1","") | BP28: =IF(BN28="完了","1","") | BQ28: =BO28+BP28 -> #VALUE! | BR28: － | BS28: =IF($D28="ADT","1","") | BT28: =IF(BR28="完了","1","") | BU28: =BS28+BT28 -> #VALUE! | BV28: － | BW28: =IF($D28="ADT","1","") | BX28: =IF(BV28="完了","1","") | BY28: =BW28+BX28 -> #VALUE! | BZ28: － | CA28: =IF($D28="ADT","1","") | CB28: =IF(BZ28="完了","1","") | CC28: =CA28+CB28 -> #VALUE! | CD28: － | CE28: =IF($D28="ADT","1","") | CF28: =IF(CD28="完了","1","") | CG28: =CE28+CF28 -> #VALUE! | CH28: 異常報告書（日文）共有フォルダ\其他\20140704HF ACE通信異常.xlsx | CI28: 0 | CJ28: 異常報告書（日文）共有フォルダ\其他\20140704HF ACE通信異常.xlsx | CK28: 0 | CM28: =IF(AZ28="","","CLOSE") -> CLOSE | CN28: =IF(F28="","",IF(COUNTIF(BB28:CE28,"未")=0,"CLOSE","")) -> CLOSE | CO28: 18 | CQ28: CLOSE | CR28: CLOSE | CS28: CLOSE | CT28: CLOSE | CU28: CLOSE | CV28: CLOSE | CW28: CLOSE | CX28: CLOSE
A29: 13 | B29: 41836 | C29: =MONTH(B29) -> 7 | D29: ADT | E29: CF | F29: 俊良 | G29: =COUNTIF(T29:AV29,"要") -> 2 | H29: =IF(G29>0,"1","0") -> 1 | I29: =IF(AND(D29="ADT",H29="1"),"1","0") -> 1 | J29: =H29+I29 -> 2 | K29: =IF(CM29="CLOSE",1,"") -> 1 | L29: =J29+K29 -> 3 | M29: =IF(CN29="CLOSE",1,"") -> 1 | N29: =J29+M29 -> 3 | O29: 機械系異常 | P29: RB LINE 採板CV | Q29: BEARING破損異常 | R29: ・RB LINE的CV点検作業有在定期項目中，雖然有進行点検但是從 安全柵欄外以目視点検，所以沒能発現 | S29: ・点検頻度変更（点検無し→ＪＣ時/工事日点検） ・該部位的可視化 | T29: 不要 | U29: =IF($D29="ADT","1","") -> 1 | V29: =IF(T29="要","1","") | W29: =U29+V29 -> #VALUE! | X29: 不要 | Y29: =IF($D29="ADT","1","") -> 1 | Z29: =IF(X29="要","1","") | AA29: =Y29+Z29 -> #VALUE! | AB29: 要 | AC29: =IF($D29="ADT","1","") -> 1 | AD29: =IF(AB29="要","1","") -> 1 | AE29: =AC29+AD29 -> 2 | AF29: 要 | AG29: =IF($D29="ADT","1","") -> 1 | AH29: =IF(AF29="要","1","") -> 1 | AI29: =AG29+AH29 -> 2 | AJ29: 不要 | AK29: =IF($D29="ADT","1","") -> 1 | AL29: =IF(AJ29="要","1","") | AM29: =AK29+AL29 -> #VALUE! | AN29: 不要 | AO29: =IF($D29="ADT","1","") -> 1 | AP29: =IF(AN29="要","1","") | AQ29: =AO29+AP29 -> #VALUE! | AR29: － | AS29: =IF($D29="ADT","1","") -> 1 | AT29: =IF(AR29="要","1","") | AU29: =AS29+AT29 -> #VALUE! | AV29: － | AW29: =IF($D29="ADT","1","") -> 1 | AX29: =IF(AV29="要","1","") | AY29: =AW29+AX29 -> #VALUE! | AZ29: 等待設技見解（CF預定進行BEARING2層化的測試 ～8/末） | BB29: － | BC29: =IF($D29="ADT","1","") -> 1 | BD29: =IF(BB29="完了","1","") | BE29: =BC29+BD29 -> #VALUE! | BF29: － | BG29: =IF($D29="ADT","1","") -> 1 | BH29: =IF(BF29="完了","1","") | BI29: =BG29+BH29 -> #VALUE! | BJ29: 完了 | BK29: =IF($D29="ADT","1","") -> 1 | BL29: =IF(BJ29="完了","1","") -> 1 | BM29: =BK29+BL29 -> 2 | BN29: 完了 | BO29: =IF($D29="ADT","1","") -> 1 | BP29: =IF(BN29="完了","1","") -> 1 | BQ29: =BO29+BP29 -> 2 | BR29: － | BS29: =IF($D29="ADT","1","") -> 1 | BT29: =IF(BR29="完了","1","") | BU29: =BS29+BT29 -> #VALUE! | BV29: － | BW29: =IF($D29="ADT","1","") -> 1 | BX29: =IF(BV29="完了","1","") | BY29: =BW29+BX29 -> #VALUE! | BZ29: － | CA29: =IF($D29="ADT","1","") -> 1 | CB29: =IF(BZ29="完了","1","") | CC29: =CA29+CB29 -> #VALUE! | CD29: － | CE29: =IF($D29="ADT","1","") -> 1 | CF29: =IF(CD29="完了","1","") | CG29: =CE29+CF29 -> #VALUE! | CH29: \\172.18.154.189\mfg_public\00 製造一部共通\横展開確認\設備異常報告\異常報告書(日文)\201407\20140716CF RB採板CV7 ベアリング異常.xls | CI29: 0 | CJ29: 異常報告書（日文）共有フォルダ\其他\20140716CF RB採板CV7 ベアリング異常.xlsx | CK29: 50 | CM29: =IF(AZ29="","","CLOSE") -> CLOSE | CN29: =IF(F29="","",IF(COUNTIF(BB29:CE29,"未")=0,"CLOSE","")) -> CLOSE | CO29: 90 | CQ29: CLOSE | CR29: CLOSE | CS29: CLOSE | CT29: CLOSE | CU29: CLOSE | CV29: CLOSE | CW29: CLOSE | CX29: CLOSE
A30: 14 | B30: 41856 | C30: =MONTH(B30) -> 8 | D30: ADT | E30: ZF | F30: 炳興 | G30: =COUNTIF(T30:AV30,"要") -> 6 | H30: =IF(G30>0,"1","0") -> 1 | I30: =IF(AND(D30="ADT",H30="1"),"1","0") -> 1 | J30: =H30+I30 -> 2 | K30: =IF(CM30="CLOSE",1,"") -> 1 | L30: =J30+K30 -> 3 | M30: =IF(CN30="CLOSE",1,"") -> 1 | N30: =J30+M30 -> 3 | O30: 電気系異常 | P30: №4循環系 | Q30: 上游軸承部Slip Sensor感度不良 | R30: 1.Sensor處玻璃粉塵堆積 2.Sensor感應位置不佳 | S30: 1.工事日定期清掃(清掃頻度討論待) 2.工事日全數Sensor感應距離確認(8/14) | T30: 要 | U30: =IF($D30="ADT","1","") -> 1 | V30: =IF(T30="要","1","") -> 1 | W30: =U30+V30 -> 2 | X30: 要 | Y30: =IF($D30="ADT","1","") -> 1 | Z30: =IF(X30="要","1","") -> 1 | AA30: =Y30+Z30 -> 2 | AB30: 要 | AC30: =IF($D30="ADT","1","") -> 1 | AD30: =IF(AB30="要","1","") -> 1 | AE30: =AC30+AD30 -> 2 | AF30: 要 | AG30: =IF($D30="ADT","1","") -> 1 | AH30: =IF(AF30="要","1","") -> 1 | AI30: =AG30+AH30 -> 2 | AJ30: 要 | AK30: =IF($D30="ADT","1","") -> 1 | AL30: =IF(AJ30="要","1","") -> 1 | AM30: =AK30+AL30 -> 2 | AN30: 要 | AO30: =IF($D30="ADT","1","") -> 1 | AP30: =IF(AN30="要","1","") -> 1 | AQ30: =AO30+AP30 -> 2 | AR30: － | AS30: =IF($D30="ADT","1","") -> 1 | AT30: =IF(AR30="要","1","") | AU30: =AS30+AT30 -> #VALUE! | AV30: － | AW30: =IF($D30="ADT","1","") -> 1 | AX30: =IF(AV30="要","1","") | AY30: =AW30+AX30 -> #VALUE! | AZ30: 1.工事日定期清掃(清掃頻度討論待) 2.工事日全數Sensor感應距離確認(8/14) | BB30: 完了 | BC30: =IF($D30="ADT","1","") -> 1 | BD30: =IF(BB30="完了","1","") -> 1 | BE30: =BC30+BD30 -> 2 | BF30: 完了 | BG30: =IF($D30="ADT","1","") -> 1 | BH30: =IF(BF30="完了","1","") -> 1 | BI30: =BG30+BH30 -> 2 | BJ30: 完了 | BK30: =IF($D30="ADT","1","") -> 1 | BL30: =IF(BJ30="完了","1","") -> 1 | BM30: =BK30+BL30 -> 2 | BN30: 完了 | BO30: =IF($D30="ADT","1","") -> 1 | BP30: =IF(BN30="完了","1","") -> 1 | BQ30: =BO30+BP30 -> 2 | BR30: 完了 | BS30: =IF($D30="ADT","1","") -> 1 | BT30: =IF(BR30="完了","1","") -> 1 | BU30: =BS30+BT30 -> 2 | BV30: 完了 | BW30: =IF($D30="ADT","1","") -> 1 | BX30: =IF(BV30="完了","1","") -> 1 | BY30: =BW30+BX30 -> 2 | BZ30: － | CA30: =IF($D30="ADT","1","") -> 1 | CB30: =IF(BZ30="完了","1","") | CC30: =CA30+CB30 -> #VALUE! | CD30: － | CE30: =IF($D30="ADT","1","") -> 1 | CF30: =IF(CD30="完了","1","") | CG30: =CE30+CF30 -> #VALUE! | CH30: \\172.18.154.189\mfg_public\00 製造一部共通\横展開確認\設備異常報告\異常報告書(日文)\201407\20140716CF RB採板CV7 ベアリング異常.xls | CI30: 0 | CJ30: 異常報告書（日文）共有フォルダ\其他\20140805 ZF包裝循環4 CULLET BC SLIP異常報告.xlsx | CK30: 0 | CM30: =IF(AZ30="","","CLOSE") -> CLOSE | CN30: =IF(F30="","",IF(COUNTIF(BB30:CE30,"未")=0,"CLOSE","")) -> CLOSE | CO30: 0 | CQ30: CLOSE | CR30: CLOSE | CS30: CLOSE | CT30: CLOSE | CU30: CLOSE | CV30: CLOSE | CW30: CLOSE | CX30: CLOSE
A31: 15 | B31: 41822 | C31: =MONTH(B31) -> 7 | D31: 高砂 | E31: GF | F31: 浅原 | G31: =COUNTIF(T31:AV31,"要") -> 8 | H31: =IF(G31>0,"1","0") -> 1 | I31: =IF(AND(D31="ADT",H31="1"),"1","0") -> 0 | J31: =H31+I31 -> 1 | K31: =IF(CM31="CLOSE",1,"") -> 1 | L31: =J31+K31 -> 2 | M31: =IF(CN31="CLOSE",1,"") -> 1 | N31: =J31+M31 -> 2 | O31: 機械系異常 | P31: 引込みC/V | Q31: 駆動CHAIN接頭部破損 | R31: 接頭的定期更換延遅 | S31: 徹底實施定期更換，使用CHAIN更換清冊。 | T31: 要 | U31: =IF($D31="ADT","1","") | V31: =IF(T31="要","1","") -> 1 | W31: =U31+V31 -> #VALUE! | X31: 要 | Y31: =IF($D31="ADT","1","") | Z31: =IF(X31="要","1","") -> 1 | AA31: =Y31+Z31 -> #VALUE! | AB31: 要 | AC31: =IF($D31="ADT","1","") | AD31: =IF(AB31="要","1","") -> 1 | AE31: =AC31+AD31 -> #VALUE! | AF31: 要 | AG31: =IF($D31="ADT","1","") | AH31: =IF(AF31="要","1","") -> 1 | AI31: =AG31+AH31 -> #VALUE! | AJ31: 要 | AK31: =IF($D31="ADT","1","") | AL31: =IF(AJ31="要","1","") -> 1 | AM31: =AK31+AL31 -> #VALUE! | AN31: 要 | AO31: =IF($D31="ADT","1","") | AP31: =IF(AN31="要","1","") -> 1 | AQ31: =AO31+AP31 -> #VALUE! | AR31: 要 | AS31: =IF($D31="ADT","1","") | AT31: =IF(AR31="要","1","") -> 1 | AU31: =AS31+AT31 -> #VALUE! | AV31: 要 | AW31: =IF($D31="ADT","1","") | AX31: =IF(AV31="要","1","") -> 1 | AY31: =AW31+AX31 -> #VALUE! | AZ31: 日常点検、週末点検、工事日点検、異常時交換。檢討導入自動給油器(SIMALUBE)。實施1回/半年的定修。CHAIN更換記録以管理清冊作管理。 | BB31: 完了 | BC31: =IF($D31="ADT","1","") | BD31: =IF(BB31="完了","1","") -> 1 | BE31: =BC31+BD31 -> #VALUE! | BF31: 完了 | BG31: =IF($D31="ADT","1","") | BH31: =IF(BF31="完了","1","") -> 1 | BI31: =BG31+BH31 -> #VALUE! | BJ31: 完了 | BK31: =IF($D31="ADT","1","") | BL31: =IF(BJ31="完了","1","") -> 1 | BM31: =BK31+BL31 -> #VALUE! | BN31: 完了 | BO31: =IF($D31="ADT","1","") | BP31: =IF(BN31="完了","1","") -> 1 | BQ31: =BO31+BP31 -> #VALUE! | BR31: 完了 | BS31: =IF($D31="ADT","1","") | BT31: =IF(BR31="完了","1","") -> 1 | BU31: =BS31+BT31 -> #VALUE! | BV31: 完了 | BW31: =IF($D31="ADT","1","") | BX31: =IF(BV31="完了","1","") -> 1 | BY31: =BW31+BX31 -> #VALUE! | BZ31: 完了 | CA31: =IF($D31="ADT","1","") | CB31: =IF(BZ31="完了","1","") -> 1 | CC31: =CA31+CB31 -> #VALUE! | CD31: 完了 | CE31: =IF($D31="ADT","1","") | CF31: =IF(CD31="完了","1","") -> 1 | CG31: =CE31+CF31 -> #VALUE! | CH31: \\172.18.154.189\mfg_public\00 製造一部共通\横展開確認\設備異常報告\異常報告書(日文)\201408以降 | CI31: 0 | CJ31: 異常報告書（中文）共有フォルダ\201408以降\20140702GF B-LINE FT部引込CV驅動鏈條斷裂.xls | CK31: 161 | CM31: =IF(AZ31="","","CLOSE") -> CLOSE | CN31: =IF(F31="","",IF(COUNTIF(BB31:CE31,"未")=0,"CLOSE","")) -> CLOSE | CO31: 0 | CQ31: CLOSE | CR31: CLOSE | CS31: CLOSE | CT31: CLOSE | CU31: CLOSE | CV31: CLOSE | CW31: CLOSE | CX31: CLOSE
A32: 16 | B32: 41841 | C32: =MONTH(B32) -> 7 | D32: ADT | E32: JF | F32: 峯謀 | G32: =COUNTIF(T32:AV32,"要") -> 5 | H32: =IF(G32>0,"1","0") -> 1 | I32: =IF(AND(D32="ADT",H32="1"),"1","0") -> 1 | J32: =H32+I32 -> 2 | K32: =IF(CM32="CLOSE",1,"") -> 1 | L32: =J32+K32 -> 3 | M32: =IF(CN32="CLOSE",1,"") -> 1 | N32: =J32+M32 -> 3 | O32: 電気系異常 | P32: 採板Robot | Q32: 因對應瞬停用UPS的故障造成電源装置的保險絲破損，使得電源無法開啟。 | R32: UPS基板內部的電容器因為長時間過電壓。溫度過高的關係.電容器絕緣失效爆裂.導致UPS故障。 | S32: ・UPS内、電容器耐電圧規格的変更請依賴業者進行更換。以更換後的部分來進行測試，如果沒有問題的話，就依序更換電容器。 ・如果電容器更換前再次發生異常的話，以不會影響UPS電源的配線變更做対応。 | T32: 不要 | U32: =IF($D32="ADT","1","") -> 1 | V32: =IF(T32="要","1","") | W32: =U32+V32 -> #VALUE! | X32: 不要 | Y32: =IF($D32="ADT","1","") -> 1 | Z32: =IF(X32="要","1","") | AA32: =Y32+Z32 -> #VALUE! | AB32: 要 | AC32: =IF($D32="ADT","1","") -> 1 | AD32: =IF(AB32="要","1","") -> 1 | AE32: =AC32+AD32 -> 2 | AF32: 要 | AG32: =IF($D32="ADT","1","") -> 1 | AH32: =IF(AF32="要","1","") -> 1 | AI32: =AG32+AH32 -> 2 | AJ32: 要 | AK32: =IF($D32="ADT","1","") -> 1 | AL32: =IF(AJ32="要","1","") -> 1 | AM32: =AK32+AL32 -> 2 | AN32: 要 | AO32: =IF($D32="ADT","1","") -> 1 | AP32: =IF(AN32="要","1","") -> 1 | AQ32: =AO32+AP32 -> 2 | AR32: 要 | AS32: =IF($D32="ADT","1","") -> 1 | AT32: =IF(AR32="要","1","") -> 1 | AU32: =AS32+AT32 -> 2 | AV32: － | AW32: =IF($D32="ADT","1","") -> 1 | AX32: =IF(AV32="要","1","") | AY32: =AW32+AX32 -> #VALUE! | AZ32: 1.電氣測試中.待判定OK後將陸續展開交換作業。 | BA32: 4/E | BB32: － | BC32: =IF($D32="ADT","1","") -> 1 | BD32: =IF(BB32="完了","1","") | BE32: =BC32+BD32 -> #VALUE! | BF32: － | BG32: =IF($D32="ADT","1","") -> 1 | BH32: =IF(BF32="完了","1","") | BI32: =BG32+BH32 -> #VALUE! | BJ32: 完了 | BK32: =IF($D32="ADT","1","") -> 1 | BL32: =IF(BJ32="完了","1","") -> 1 | BM32: =BK32+BL32 -> 2 | BN32: 完了 | BO32: =IF($D32="ADT","1","") -> 1 | BP32: =IF(BN32="完了","1","") -> 1 | BQ32: =BO32+BP32 -> 2 | BR32: 完了 | BS32: =IF($D32="ADT","1","") -> 1 | BT32: =IF(BR32="完了","1","") -> 1 | BU32: =BS32+BT32 -> 2 | BV32: 完了 | BW32: =IF($D32="ADT","1","") -> 1 | BX32: =IF(BV32="完了","1","") -> 1 | BY32: =BW32+BX32 -> 2 | BZ32: 完了 | CA32: =IF($D32="ADT","1","") -> 1 | CB32: =IF(BZ32="完了","1","") -> 1 | CC32: =CA32+CB32 -> 2 | CD32: － | CE32: =IF($D32="ADT","1","") -> 1 | CF32: =IF(CD32="完了","1","") | CG32: =CE32+CF32 -> #VALUE! | CH32: \\172.18.154.189\mfg_public\00 製造一部共通\横展開確認\設備異常報告\異常報告書(日文)\201407 | CI32: 0 | CJ32: 異常報告書（中文）共有フォルダ\201407\20140721JF 採板ROBOT制御盤電源異常.xls | CK32: 106 | CM32: =IF(AZ32="","","CLOSE") -> CLOSE | CN32: =IF(F32="","",IF(COUNTIF(BB32:CE32,"未")=0,"CLOSE","")) -> CLOSE | CO32: 5 | CQ32: CLOSE | CR32: CLOSE | CS32: 因為目前尚有問題目前BY PASS對應，新品UPS購入 | CT32: 因為目前尚有問題目前BY PASS對應，新品UPS購入 | CU32: 電氣G新品導入(待KF測試)6/2 更換新品完成 | CV32: 8/26 JF 3POS新型電容器導入測試中！最終評估OK後導入；冷修計劃預定一時CLOSE | CW32: CLOSE 12/18#5及#7號機安裝完畢。 | CX32: CLOSE | CY32: →最終評価はいつまでに出すの？それを決めないと進まない！！ →最終評価は電気G周さんよりOKとの連絡有り。 →J/K冷修導入横展開スケジュール計画有り。(指摘修繕計畫列入)一時CLOSE
A33: 17 | B33: 41863 | C33: =MONTH(B33) -> 8 | D33: AFK | E33: FF | F33: 三路 | G33: =COUNTIF(T33:AV33,"要") -> 3 | H33: =IF(G33>0,"1","0") -> 1 | I33: =IF(AND(D33="ADT",H33="1"),"1","0") -> 0 | J33: =H33+I33 -> 1 | K33: =IF(CM33="CLOSE",1,"") -> 1 | L33: =J33+K33 -> 2 | M33: =IF(CN33="CLOSE",1,"") -> 1 | N33: =J33+M33 -> 2 | O33: 機械系異常 | P33: PL-changer | Q33: 実際PL搬送用伺服的馬達連軸器的KEY脱落，造成実際PL搬送的停止位置偏移。 | R33: 連軸器的KEY脱落 | S33: ・KEY加工変更（AFK詢問中？） ・在実際PL搬送（払出側）追加停止位置確認PR | T33: 不要 | U33: =IF($D33="ADT","1","") | V33: =IF(T33="要","1","") | W33: =U33+V33 -> #VALUE! | X33: 不要 | Y33: =IF($D33="ADT","1","") | Z33: =IF(X33="要","1","") | AA33: =Y33+Z33 -> #VALUE! | AB33: 要 | AC33: =IF($D33="ADT","1","") | AD33: =IF(AB33="要","1","") -> 1 | AE33: =AC33+AD33 -> #VALUE! | AF33: 要 | AG33: =IF($D33="ADT","1","") | AH33: =IF(AF33="要","1","") -> 1 | AI33: =AG33+AH33 -> #VALUE! | AJ33: 要 | AK33: =IF($D33="ADT","1","") | AL33: =IF(AJ33="要","1","") -> 1 | AM33: =AK33+AL33 -> #VALUE! | AN33: 不要 | AO33: =IF($D33="ADT","1","") | AP33: =IF(AN33="要","1","") | AQ33: =AO33+AP33 -> #VALUE! | AR33: 不要 | AS33: =IF($D33="ADT","1","") | AT33: =IF(AR33="要","1","") | AU33: =AS33+AT33 -> #VALUE! | AV33: 不要 | AW33: =IF($D33="ADT","1","") | AX33: =IF(AV33="要","1","") | AY33: =AW33+AX33 -> #VALUE! | AZ33: ・機械G点検後檢討対策 ・在実際PL搬送（払出側）追加停止位置確認PR | BB33: － | BC33: =IF($D33="ADT","1","") | BD33: =IF(BB33="完了","1","") | BE33: =BC33+BD33 -> #VALUE! | BF33: － | BG33: =IF($D33="ADT","1","") | BH33: =IF(BF33="完了","1","") | BI33: =BG33+BH33 -> #VALUE! | BJ33: 完了 | BK33: =IF($D33="ADT","1","") | BL33: =IF(BJ33="完了","1","") -> 1 | BM33: =BK33+BL33 -> #VALUE! | BN33: 完了 | BO33: =IF($D33="ADT","1","") | BP33: =IF(BN33="完了","1","") -> 1 | BQ33: =BO33+BP33 -> #VALUE! | BR33: 完了 | BS33: =IF($D33="ADT","1","") | BT33: =IF(BR33="完了","1","") -> 1 | BU33: =BS33+BT33 -> #VALUE! | BV33: － | BW33: =IF($D33="ADT","1","") | BX33: =IF(BV33="完了","1","") | BY33: =BW33+BX33 -> #VALUE! | BZ33: － | CA33: =IF($D33="ADT","1","") | CB33: =IF(BZ33="完了","1","") | CC33: =CA33+CB33 -> #VALUE! | CD33: － | CE33: =IF($D33="ADT","1","") | CF33: =IF(CD33="完了","1","") | CG33: =CE33+CF33 -> #VALUE! | CH33: O:\00 製造一部共通\横展開確認\設備異常報告\異常報告書(日文)\201408以降 | CI33: 0 | CJ33: 異常報告書（中文）共有フォルダ\201408以降\20140805_AFK_FF_PL ChangerPL空PL衝突異常.xls | CK33: 350 | CM33: =IF(AZ33="","","CLOSE") -> CLOSE | CN33: =IF(F33="","",IF(COUNTIF(BB33:CE33,"未")=0,"CLOSE","")) -> CLOSE | CO33: 13 | CQ33: CLOSE | CR33: CLOSE | CS33: CLOSE | CT33: CLOSE | CU33: CLOSE | CV33: CLOSE | CW33: CLOSE | CX33: CLOSE
A34: 18 | B34: 41854 | C34: =MONTH(B34) -> 8 | D34: AFK | E34: GUT | F34: 浅原 | G34: =COUNTIF(T34:AV34,"要") -> 8 | H34: =IF(G34>0,"1","0") -> 1 | I34: =IF(AND(D34="ADT",H34="1"),"1","0") -> 0 | J34: =H34+I34 -> 1 | K34: =IF(CM34="CLOSE",1,"") -> 1 | L34: =J34+K34 -> 2 | M34: =IF(CN34="CLOSE",1,"") -> 1 | N34: =J34+M34 -> 2 | O34: 電気系異常 | P34: 搬送C/V | Q34: 基板檢查結束後, 未正常移載至採板側, Though (直接通過)造成廢棄Loss（1枚）。之後還是間斷出現Though廢棄, 於是Line停機並呼出設技。 | R34: 就解決了, 所以原因推測為反射板或Senser起霧的關係。 | S34: 持續工事日定期點檢掃除。 | T34: 要 | U34: =IF($D34="ADT","1","") | V34: =IF(T34="要","1","") -> 1 | W34: =U34+V34 -> #VALUE! | X34: 要 | Y34: =IF($D34="ADT","1","") | Z34: =IF(X34="要","1","") -> 1 | AA34: =Y34+Z34 -> #VALUE! | AB34: 要 | AC34: =IF($D34="ADT","1","") | AD34: =IF(AB34="要","1","") -> 1 | AE34: =AC34+AD34 -> #VALUE! | AF34: 要 | AG34: =IF($D34="ADT","1","") | AH34: =IF(AF34="要","1","") -> 1 | AI34: =AG34+AH34 -> #VALUE! | AJ34: 要 | AK34: =IF($D34="ADT","1","") | AL34: =IF(AJ34="要","1","") -> 1 | AM34: =AK34+AL34 -> #VALUE! | AN34: 要 | AO34: =IF($D34="ADT","1","") | AP34: =IF(AN34="要","1","") -> 1 | AQ34: =AO34+AP34 -> #VALUE! | AR34: 要 | AS34: =IF($D34="ADT","1","") | AT34: =IF(AR34="要","1","") -> 1 | AU34: =AS34+AT34 -> #VALUE! | AV34: 要 | AW34: =IF($D34="ADT","1","") | AX34: =IF(AV34="要","1","") -> 1 | AY34: =AW34+AX34 -> #VALUE! | AZ34: 定期地清掃傳感器。 定期地調整傳感器的靈敏度。 | BA34: 41882 | BB34: 完了 | BC34: =IF($D34="ADT","1","") | BD34: =IF(BB34="完了","1","") -> 1 | BE34: =BC34+BD34 -> #VALUE! | BF34: 完了 | BG34: =IF($D34="ADT","1","") | BH34: =IF(BF34="完了","1","") -> 1 | BI34: =BG34+BH34 -> #VALUE! | BJ34: 完了 | BK34: =IF($D34="ADT","1","") | BL34: =IF(BJ34="完了","1","") -> 1 | BM34: =BK34+BL34 -> #VALUE! | BN34: 完了 | BO34: =IF($D34="ADT","1","") | BP34: =IF(BN34="完了","1","") -> 1 | BQ34: =BO34+BP34 -> #VALUE! | BR34: 完了 | BS34: =IF($D34="ADT","1","") | BT34: =IF(BR34="完了","1","") -> 1 | BU34: =BS34+BT34 -> #VALUE! | BV34: 完了 | BW34: =IF($D34="ADT","1","") | BX34: =IF(BV34="完了","1","") -> 1 | BY34: =BW34+BX34 -> #VALUE! | BZ34: 完了 | CA34: =IF($D34="ADT","1","") | CB34: =IF(BZ34="完了","1","") -> 1 | CC34: =CA34+CB34 -> #VALUE! | CD34: 完了 | CE34: =IF($D34="ADT","1","") | CF34: =IF(CD34="完了","1","") -> 1 | CG34: =CE34+CF34 -> #VALUE! | CH34: O:\00 製造一部共通\横展開確認\設備異常報告\異常報告書(日文)\201408以降 | CI34: 0 | CJ34: 異常報告書（中文）共有フォルダ\201408以降\20140803 Glass檢知Senser異常.xls | CK34: 218 | CL34: 異常報告書（中文）共有フォルダ\201408以降\20140803 Glass檢知Senser異常.xls | CM34: =IF(AZ34="","","CLOSE") -> CLOSE | CN34: =IF(F34="","",IF(COUNTIF(BB34:CE34,"未")=0,"CLOSE","")) -> CLOSE | CO34: 38 | CQ34: CLOSE | CR34: CLOSE | CS34: CLOSE | CT34: CLOSE | CU34: CLOSE | CV34: CLOSE | CW34: CLOSE | CX34: CLOSE
A35: 19 | B35: 41837 | C35: =MONTH(B35) -> 7 | D35: AFK | E35: GUT | F35: 浅原 | G35: =COUNTIF(T35:AV35,"要") -> 8 | H35: =IF(G35>0,"1","0") -> 1 | I35: =IF(AND(D35="ADT",H35="1"),"1","0") -> 0 | J35: =H35+I35 -> 1 | K35: =IF(CM35="CLOSE",1,"") -> 1 | L35: =J35+K35 -> 2 | M35: =IF(CN35="CLOSE",1,"") -> 1 | N35: =J35+M35 -> 2 | O35: 機械系異常 | P35: 真空Pump | Q35: 發生Glass吸著異常発生。真空Pump 由原本使用的#1切替到 #1#2同時使用，也無良化。切替至真空Pump#2單獨使用後 異常才解除。 | R35: 碳片出現部分破損導致壓力低下。推測碳片的磨耗致使失衡, 並發生碳片破損。 | S35: 更換真空Pump #1（7/18實施）。將真空Pump 安全柵内⇒安全柵外 以利保養。改善更換作業性（7/21完成）。檢討定期更換等預防措施可行性 | T35: 要 | U35: =IF($D35="ADT","1","") | V35: =IF(T35="要","1","") -> 1 | W35: =U35+V35 -> #VALUE! | X35: 要 | Y35: =IF($D35="ADT","1","") | Z35: =IF(X35="要","1","") -> 1 | AA35: =Y35+Z35 -> #VALUE! | AB35: 要 | AC35: =IF($D35="ADT","1","") | AD35: =IF(AB35="要","1","") -> 1 | AE35: =AC35+AD35 -> #VALUE! | AF35: 要 | AG35: =IF($D35="ADT","1","") | AH35: =IF(AF35="要","1","") -> 1 | AI35: =AG35+AH35 -> #VALUE! | AJ35: 要 | AK35: =IF($D35="ADT","1","") | AL35: =IF(AJ35="要","1","") -> 1 | AM35: =AK35+AL35 -> #VALUE! | AN35: 要 | AO35: =IF($D35="ADT","1","") | AP35: =IF(AN35="要","1","") -> 1 | AQ35: =AO35+AP35 -> #VALUE! | AR35: 要 | AS35: =IF($D35="ADT","1","") | AT35: =IF(AR35="要","1","") -> 1 | AU35: =AS35+AT35 -> #VALUE! | AV35: 要 | AW35: =IF($D35="ADT","1","") | AX35: =IF(AV35="要","1","") -> 1 | AY35: =AW35+AX35 -> #VALUE! | AZ35: 確認真空泵的檢查記錄。 確認真空泵的交換記錄。 確認真空泵的設置位置。 | BA35: 41873 | BB35: 完了 | BC35: =IF($D35="ADT","1","") | BD35: =IF(BB35="完了","1","") -> 1 | BE35: =BC35+BD35 -> #VALUE! | BF35: 完了 | BG35: =IF($D35="ADT","1","") | BH35: =IF(BF35="完了","1","") -> 1 | BI35: =BG35+BH35 -> #VALUE! | BJ35: 完了 | BK35: =IF($D35="ADT","1","") | BL35: =IF(BJ35="完了","1","") -> 1 | BM35: =BK35+BL35 -> #VALUE! | BN35: 完了 | BO35: =IF($D35="ADT","1","") | BP35: =IF(BN35="完了","1","") -> 1 | BQ35: =BO35+BP35 -> #VALUE! | BR35: 完了 | BS35: =IF($D35="ADT","1","") | BT35: =IF(BR35="完了","1","") -> 1 | BU35: =BS35+BT35 -> #VALUE! | BV35: 完了 | BW35: =IF($D35="ADT","1","") | BX35: =IF(BV35="完了","1","") -> 1 | BY35: =BW35+BX35 -> #VALUE! | BZ35: 完了 | CA35: =IF($D35="ADT","1","") | CB35: =IF(BZ35="完了","1","") -> 1 | CC35: =CA35+CB35 -> #VALUE! | CD35: 完了 | CE35: =IF($D35="ADT","1","") | CF35: =IF(CD35="完了","1","") -> 1 | CG35: =CE35+CF35 -> #VALUE! | CH35: 異常報告書（日文）共有フォルダ\201407\20140717GUT OFF切NO1真空P圧力異常.xls | CI35: 0 | CJ35: 異常報告書（中文）共有フォルダ\201407\20140717GUT OFF切NO1真空P力異常.xls | CK35: 554 | CL35: ..\..\異常報告書(中文)\201407\●AFK-GUT OFF切#1真空Pump壓力異常-(C_E_J_K_Y_Z)真空Pump確認.xls | CM35: =IF(AZ35="","","CLOSE") -> CLOSE | CN35: =IF(F35="","",IF(COUNTIF(BB35:CE35,"未")=0,"CLOSE","")) -> CLOSE | CO35: 143 | CQ35: CLOSE | CR35: CLOSE | CS35: CLOSE | CT35: CLOSE | CU35: CLOSE | CV35: CLOSE | CW35: CLOSE | CX35: CLOSE
A36: 20 | B36: 41843 | C36: =MONTH(B36) -> 7 | D36: ADT | E36: ZF | F36: 浅原 | G36: =COUNTIF(T36:AV36,"要") -> 6 | H36: =IF(G36>0,"1","0") -> 1 | I36: =IF(AND(D36="ADT",H36="1"),"1","0") -> 1 | J36: =H36+I36 -> 2 | K36: =IF(CM36="CLOSE",1,"") -> 1 | L36: =J36+K36 -> 3 | M36: =IF(CN36="CLOSE",1,"") -> 1 | N36: =J36+M36 -> 3 | O36: 検査機系異常 | P36: 精査thin client用HUB | Q36: 精査thin client異常。T/P畫面上顯示『remote esktop 沒有接上 remote computer』重新啟動精査判定SERVER,但無法登入。因為精査thin client用的HUB LED 燈號熄滅所以拔掉HUB的電源線後重新插上就回復正常了。之後異常就沒再發生過了。 | R36: ①推測是HUB的電源線鬆脫。 ②重要的檢查機附帶設備的維持管理不足。 | S36: 原因①的對策 固定好HUB電源線,使其不鬆脫。 變更HUB的電源設置位置。 原因②的對策 實施詳查室的處理整頓。 為整備班的檢查表追加HUB確認項目。 | T36: 要 | U36: =IF($D36="ADT","1","") -> 1 | V36: =IF(T36="要","1","") -> 1 | W36: =U36+V36 -> 2 | X36: 要 | Y36: =IF($D36="ADT","1","") -> 1 | Z36: =IF(X36="要","1","") -> 1 | AA36: =Y36+Z36 -> 2 | AB36: 要 | AC36: =IF($D36="ADT","1","") -> 1 | AD36: =IF(AB36="要","1","") -> 1 | AE36: =AC36+AD36 -> 2 | AF36: 要 | AG36: =IF($D36="ADT","1","") -> 1 | AH36: =IF(AF36="要","1","") -> 1 | AI36: =AG36+AH36 -> 2 | AJ36: 要 | AK36: =IF($D36="ADT","1","") -> 1 | AL36: =IF(AJ36="要","1","") -> 1 | AM36: =AK36+AL36 -> 2 | AN36: 要 | AO36: =IF($D36="ADT","1","") -> 1 | AP36: =IF(AN36="要","1","") -> 1 | AQ36: =AO36+AP36 -> 2 | AR36: 情報 | AS36: =IF($D36="ADT","1","") -> 1 | AT36: =IF(AR36="要","1","") | AU36: =AS36+AT36 -> #VALUE! | AV36: 情報 | AW36: =IF($D36="ADT","1","") -> 1 | AX36: =IF(AV36="要","1","") | AY36: =AW36+AX36 -> #VALUE! | AZ36: 固定好HUB電源線,使其不鬆脫。 變更HUB的電源設置位置。 實施詳查室的處理整頓。 為整備班的檢查表追加HUB確認項目。 | BA36: 41882 | BB36: 完了 | BC36: =IF($D36="ADT","1","") -> 1 | BD36: =IF(BB36="完了","1","") -> 1 | BE36: =BC36+BD36 -> 2 | BF36: 完了 | BG36: =IF($D36="ADT","1","") -> 1 | BH36: =IF(BF36="完了","1","") -> 1 | BI36: =BG36+BH36 -> 2 | BJ36: 完了 | BK36: =IF($D36="ADT","1","") -> 1 | BL36: =IF(BJ36="完了","1","") -> 1 | BM36: =BK36+BL36 -> 2 | BN36: 完了 | BO36: =IF($D36="ADT","1","") -> 1 | BP36: =IF(BN36="完了","1","") -> 1 | BQ36: =BO36+BP36 -> 2 | BR36: 完了 | BS36: =IF($D36="ADT","1","") -> 1 | BT36: =IF(BR36="完了","1","") -> 1 | BU36: =BS36+BT36 -> 2 | BV36: 完了 | BW36: =IF($D36="ADT","1","") -> 1 | BX36: =IF(BV36="完了","1","") -> 1 | BY36: =BW36+BX36 -> 2 | BZ36: － | CA36: =IF($D36="ADT","1","") -> 1 | CB36: =IF(BZ36="完了","1","") | CC36: =CA36+CB36 -> #VALUE! | CD36: － | CE36: =IF($D36="ADT","1","") -> 1 | CF36: =IF(CD36="完了","1","") | CG36: =CE36+CF36 -> #VALUE! | CH36: \\172.18.154.189\mfg_public\00 製造一部共通\横展開確認\設備異常報告\異常報告書(日文)\201408以降 | CI36: 0 | CJ36: 異常報告書（中文）共有フォルダ\201408以降\複本 20140723ZF 精査ｼﾝｸﾗｲｱﾝﾄ用HUB異常報告.xls | CK36: 112 | CM36: =IF(AZ36="","","CLOSE") -> CLOSE | CN36: =IF(F36="","",IF(COUNTIF(BB36:CE36,"未")=0,"CLOSE","")) -> CLOSE | CO36: 6 | CQ36: CLOSE | CR36: CLOSE | CS36: CLOSE | CT36: CLOSE | CU36: CLOSE | CV36: CLOSE | CW36: CLOSE | CX36: CLOSE
A37: 21 | B37: 41857 | C37: =MONTH(B37) -> 8 | D37: AFK | E37: IF | F37: 浅原 | G37: =COUNTIF(T37:AV37,"要") -> 0 | H37: =IF(G37>0,"1","0") -> 0 | I37: =IF(AND(D37="ADT",H37="1"),"1","0") -> 0 | J37: =H37+I37 -> 0 | K37: =IF(CM37="CLOSE",1,"") -> 1 | L37: =J37+K37 -> 1 | M37: =IF(CN37="CLOSE",1,"") -> 1 | N37: =J37+M37 -> 1 | O37: 機械系異常 | P37: 本線C/V | Q37: 巡檢發現到，本線CV Roll#238的驅動側，防止sprocket key鬆脫的end plate脫落，sprocket外移了10mm左右。呼出設備技術，Guillotine處理開始。修復完成。Guillotine解除。F1採版開始 | R37: 冷修時的旋緊不足。因roll的連續回轉的震動，螺絲鬆脫、掉落。現在使用Nord-Lock墊圈的緣故，如果正確地鎖好的話，不太可能輕易地就鬆脫。 | S37: 下次工事日時增強旋緊度 （在工事日之前，從點檢窗做目視點檢） | T37: 情報 | U37: =IF($D37="ADT","1","") | V37: =IF(T37="要","1","") | W37: =U37+V37 -> #VALUE! | X37: 情報 | Y37: =IF($D37="ADT","1","") | Z37: =IF(X37="要","1","") | AA37: =Y37+Z37 -> #VALUE! | AB37: 情報 | AC37: =IF($D37="ADT","1","") | AD37: =IF(AB37="要","1","") | AE37: =AC37+AD37 -> #VALUE! | AF37: 情報 | AG37: =IF($D37="ADT","1","") | AH37: =IF(AF37="要","1","") | AI37: =AG37+AH37 -> #VALUE! | AJ37: 情報 | AK37: =IF($D37="ADT","1","") | AL37: =IF(AJ37="要","1","") | AM37: =AK37+AL37 -> #VALUE! | AN37: 情報 | AO37: =IF($D37="ADT","1","") | AP37: =IF(AN37="要","1","") | AQ37: =AO37+AP37 -> #VALUE! | AR37: 情報 | AS37: =IF($D37="ADT","1","") | AT37: =IF(AR37="要","1","") | AU37: =AS37+AT37 -> #VALUE! | AV37: 情報 | AW37: =IF($D37="ADT","1","") | AX37: =IF(AV37="要","1","") | AY37: =AW37+AX37 -> #VALUE! | AZ37: 工事日時、檢查實施。增強旋緊度。 能看見的化。 使用Nord-Lock墊圈。 8/6再発、対策未定。 | BB37: － | BC37: =IF($D37="ADT","1","") | BD37: =IF(BB37="完了","1","") | BE37: =BC37+BD37 -> #VALUE! | BF37: － | BG37: =IF($D37="ADT","1","") | BH37: =IF(BF37="完了","1","") | BI37: =BG37+BH37 -> #VALUE! | BJ37: － | BK37: =IF($D37="ADT","1","") | BL37: =IF(BJ37="完了","1","") | BM37: =BK37+BL37 -> #VALUE! | BN37: － | BO37: =IF($D37="ADT","1","") | BP37: =IF(BN37="完了","1","") | BQ37: =BO37+BP37 -> #VALUE! | BR37: － | BS37: =IF($D37="ADT","1","") | BT37: =IF(BR37="完了","1","") | BU37: =BS37+BT37 -> #VALUE! | BV37: － | BW37: =IF($D37="ADT","1","") | BX37: =IF(BV37="完了","1","") | BY37: =BW37+BX37 -> #VALUE! | BZ37: － | CA37: =IF($D37="ADT","1","") | CB37: =IF(BZ37="完了","1","") | CC37: =CA37+CB37 -> #VALUE! | CD37: － | CE37: =IF($D37="ADT","1","") | CF37: =IF(CD37="完了","1","") | CG37: =CE37+CF37 -> #VALUE! | CH37: \\172.18.154.189\mfg_public\00 製造一部共通\横展開確認\設備異常報告\異常報告書(日文)\201408以降 | CI37: 1 | CJ37: 異常報告書（中文）共有フォルダ\201408以降\20140806IF 本線CVロールシャフトエンドプレート脱落異常(中文).xls | CK37: 952 | CM37: =IF(AZ37="","","CLOSE") -> CLOSE | CN37: =IF(F37="","",IF(COUNTIF(BB37:CE37,"未")=0,"CLOSE","")) -> CLOSE | CO37: 35 | CQ37: CLOSE | CR37: CLOSE | CS37: CLOSE | CT37: CLOSE | CU37: CLOSE | CV37: CLOSE | CW37: CLOSE | CX37: CLOSE
A38: 22 | B38: 41859 | C38: =MONTH(B38) -> 8 | D38: AFK | E38: LF | F38: 浅原 | G38: =COUNTIF(T38:AV38,"要") -> 1 | H38: =IF(G38>0,"1","0") -> 1 | I38: =IF(AND(D38="ADT",H38="1"),"1","0") -> 0 | J38: =H38+I38 -> 1 | K38: =IF(CM38="CLOSE",1,"") -> 1 | L38: =J38+K38 -> 2 | M38: =IF(CN38="CLOSE",1,"") -> 1 | N38: =J38+M38 -> 2 | O38: 機械系異常 | P38: 本線C/V | Q38: 製造三交代發現惰輪Idler出現晃動情形。呼出設技機械Team, 確認時發現惰輪Ider的固定Plate折損。（雖然整個斷掉了, 但是沒有脫落還是一直回轉。）開啟Guillotine該處實施焊接補強生産再開 | R38: 増速C/V＃4減速及＃5加速時、推測負荷集中在該處的惰輪Idler而斷裂。同樣規格的惰輪Idler目前使用在増速C/V＃5＃6間、増速C/V＃6＃7間、仍追加一片Plate並進行了焊接補強（LF建設時） | S38: 緊急對應內側追加一片Plate並進行焊接補強對策製作一整片的新的Plate、於下回工事日進行設置 | T38: 不要 | U38: =IF($D38="ADT","1","") | V38: =IF(T38="要","1","") | W38: =U38+V38 -> #VALUE! | X38: 不要 | Y38: =IF($D38="ADT","1","") | Z38: =IF(X38="要","1","") | AA38: =Y38+Z38 -> #VALUE! | AB38: 不要 | AC38: =IF($D38="ADT","1","") | AD38: =IF(AB38="要","1","") | AE38: =AC38+AD38 -> #VALUE! | AF38: 不要 | AG38: =IF($D38="ADT","1","") | AH38: =IF(AF38="要","1","") | AI38: =AG38+AH38 -> #VALUE! | AJ38: 不要 | AK38: =IF($D38="ADT","1","") | AL38: =IF(AJ38="要","1","") | AM38: =AK38+AL38 -> #VALUE! | AN38: 要 | AO38: =IF($D38="ADT","1","") | AP38: =IF(AN38="要","1","") -> 1 | AQ38: =AO38+AP38 -> #VALUE! | AR38: 不要 | AS38: =IF($D38="ADT","1","") | AT38: =IF(AR38="要","1","") | AU38: =AS38+AT38 -> #VALUE! | AV38: 不要 | AW38: =IF($D38="ADT","1","") | AX38: =IF(AV38="要","1","") | AY38: =AW38+AX38 -> #VALUE! | AZ38: KF 本線№4 C/V。 Idler軸的材質變更為SCM435。 （利用冷修工事進行） | BB38: － | BC38: =IF($D38="ADT","1","") | BD38: =IF(BB38="完了","1","") | BE38: =BC38+BD38 -> #VALUE! | BF38: － | BG38: =IF($D38="ADT","1","") | BH38: =IF(BF38="完了","1","") | BI38: =BG38+BH38 -> #VALUE! | BJ38: － | BK38: =IF($D38="ADT","1","") | BL38: =IF(BJ38="完了","1","") | BM38: =BK38+BL38 -> #VALUE! | BN38: － | BO38: =IF($D38="ADT","1","") | BP38: =IF(BN38="完了","1","") | BQ38: =BO38+BP38 -> #VALUE! | BR38: － | BS38: =IF($D38="ADT","1","") | BT38: =IF(BR38="完了","1","") | BU38: =BS38+BT38 -> #VALUE! | BV38: 完了 | BW38: =IF($D38="ADT","1","") | BX38: =IF(BV38="完了","1","") -> 1 | BY38: =BW38+BX38 -> #VALUE! | BZ38: － | CA38: =IF($D38="ADT","1","") | CB38: =IF(BZ38="完了","1","") | CC38: =CA38+CB38 -> #VALUE! | CD38: － | CE38: =IF($D38="ADT","1","") | CF38: =IF(CD38="完了","1","") | CG38: =CE38+CF38 -> #VALUE! | CH38: \\172.18.154.189\mfg_public\00 製造一部共通\横展開確認\設備異常報告\異常報告書(日文)\201408以降 | CI38: 0 | CJ38: 異常報告書（中文）共有フォルダ\201408以降\20140808LF 本線増速No 4No 5共用惰輪(Idler)固定Plate折損.xls | CK38: 1234 | CM38: =IF(AZ38="","","CLOSE") -> CLOSE | CN38: =IF(F38="","",IF(COUNTIF(BB38:CE38,"未")=0,"CLOSE","")) -> CLOSE | CO38: 60 | CQ38: CLOSE | CR38: CLOSE | CS38: CLOSE | CT38: CLOSE | CU38: CLOSE | CV38: CLOSE | CW38: CLOSE | CX38: CLOSE
A39: 23 | B39: 41855 | C39: =MONTH(B39) -> 8 | D39: 高砂 | E39: GF | F39: 浅原 | G39: =COUNTIF(T39:AV39,"要") -> 4 | H39: =IF(G39>0,"1","0") -> 1 | I39: =IF(AND(D39="ADT",H39="1"),"1","0") -> 0 | J39: =H39+I39 -> 1 | K39: =IF(CM39="CLOSE",1,"") -> 1 | L39: =J39+K39 -> 2 | M39: =IF(CN39="CLOSE",1,"") -> 1 | N39: =J39+M39 -> 2 | O39: 電気系異常 | P39: 洗淨機風刀吹散Blower | Q39: B-LINE洗浄機Air_Knife_INV異常発生(2Br全採中, 因此無Loss)Thermal(積熱繼電器)跳脫無法復歸, 因此呼出設技實施Blower更換B-LINE刮傷檢查後開始採板 | R39: Blower_Motor過熱融解導致Bearing卡住、再加上Motor的熱度影響到 Motor冷却用Fan的樹脂Blade(葉片)融解※GF1 ON-TAS Start時(2008年～)起持續使用。 無更換& Overhaul(大檢修)。 | S39: ・毎月工事日更換2台備品, 並依序實施 Overhaul(大檢修)。(※9台+預備2台 約需4個月可全數更換) | T39: 不要 | U39: =IF($D39="ADT","1","") | V39: =IF(T39="要","1","") | W39: =U39+V39 -> #VALUE! | X39: 不要 | Y39: =IF($D39="ADT","1","") | Z39: =IF(X39="要","1","") | AA39: =Y39+Z39 -> #VALUE! | AB39: 不要 | AC39: =IF($D39="ADT","1","") | AD39: =IF(AB39="要","1","") | AE39: =AC39+AD39 -> #VALUE! | AF39: 不要 | AG39: =IF($D39="ADT","1","") | AH39: =IF(AF39="要","1","") | AI39: =AG39+AH39 -> #VALUE! | AJ39: 要 | AK39: =IF($D39="ADT","1","") | AL39: =IF(AJ39="要","1","") -> 1 | AM39: =AK39+AL39 -> #VALUE! | AN39: 要 | AO39: =IF($D39="ADT","1","") | AP39: =IF(AN39="要","1","") -> 1 | AQ39: =AO39+AP39 -> #VALUE! | AR39: 要 | AS39: =IF($D39="ADT","1","") | AT39: =IF(AR39="要","1","") -> 1 | AU39: =AS39+AT39 -> #VALUE! | AV39: 要 | AW39: =IF($D39="ADT","1","") | AX39: =IF(AV39="要","1","") -> 1 | AY39: =AW39+AX39 -> #VALUE! | AZ39: 並依序實施 Overhaul。 （設備技術相談待） ADT OFF-TAS・・・1回/3年 ON-TAS・・・1回/冷修 | BB39: － | BC39: =IF($D39="ADT","1","") | BD39: =IF(BB39="完了","1","") | BE39: =BC39+BD39 -> #VALUE! | BF39: － | BG39: =IF($D39="ADT","1","") | BH39: =IF(BF39="完了","1","") | BI39: =BG39+BH39 -> #VALUE! | BJ39: － | BK39: =IF($D39="ADT","1","") | BL39: =IF(BJ39="完了","1","") | BM39: =BK39+BL39 -> #VALUE! | BN39: － | BO39: =IF($D39="ADT","1","") | BP39: =IF(BN39="完了","1","") | BQ39: =BO39+BP39 -> #VALUE! | BR39: 完了 | BS39: =IF($D39="ADT","1","") | BT39: =IF(BR39="完了","1","") -> 1 | BU39: =BS39+BT39 -> #VALUE! | BV39: 完了 | BW39: =IF($D39="ADT","1","") | BX39: =IF(BV39="完了","1","") -> 1 | BY39: =BW39+BX39 -> #VALUE! | BZ39: 完了 | CA39: =IF($D39="ADT","1","") | CB39: =IF(BZ39="完了","1","") -> 1 | CC39: =CA39+CB39 -> #VALUE! | CD39: 完了 | CE39: =IF($D39="ADT","1","") | CF39: =IF(CD39="完了","1","") -> 1 | CG39: =CE39+CF39 -> #VALUE! | CH39: \\172.18.154.189\mfg_public\00 製造一部共通\横展開確認\設備異常報告\異常報告書(日文)\201408以降 | CI39: 0 | CJ39: 異常報告書（中文）共有フォルダ\201408以降\20140804 GF B-LINE洗浄機Air_Knife_INV異常.xls | CK39: 0 | CM39: =IF(AZ39="","","CLOSE") -> CLOSE | CN39: =IF(F39="","",IF(COUNTIF(BB39:CE39,"未")=0,"CLOSE","")) -> CLOSE | CO39: 0 | CQ39: CLOSE | CR39: CLOSE | CS39: CLOSE | CT39: CLOSE | CU39: CLOSE | CV39: CLOSE | CW39: CLOSE | CX39: CLOSE
A40: 24 | B40: 41851 | C40: =MONTH(B40) -> 7 | D40: AFK | E40: GUT | F40: 浅原 | G40: =COUNTIF(T40:AV40,"要") -> 8 | H40: =IF(G40>0,"1","0") -> 1 | I40: =IF(AND(D40="ADT",H40="1"),"1","0") -> 0 | J40: =H40+I40 -> 1 | K40: =IF(CM40="CLOSE",1,"") -> 1 | L40: =J40+K40 -> 2 | M40: =IF(CN40="CLOSE",1,"") -> 1 | N40: =J40+M40 -> 2 | O40: 電気系異常 | P40: 水處理場電源供應器 | Q40: 於GUT全產線純水發生桶槽缺水預報及缺水警報、產線依序停止。由於水處理場制御盤警報畫面之2B3T №2 PUMP有出現停止警報（№1PUMP稼働）、因此呼出設技。由於洗滌器的電源是由FF窯供給的，因此沒有停止。以臨時電源來讓純水桶槽得以往產線供給（生産再開）。制御盤内之電源供應器（1台）確認故障、更換為予備品。設備復舊。 | R40: 由於主電源的制御盤電源發生停止因此警報沒能響起。由於使用壽命可達10年因此未進行更換。（DF：GUT 2005年8月量産開始）由於緊急用的純水Back Up供給手順未能準備妥當因此耽擱到生産之再開。 | S40: 8/24 伴隨著DF3的冷修工事計劃於停電時將水處理場的電源供應器進行全數更換。其他、關於各產線之制御電源計畫藉由明年度的起業申請、依序進行更換。關於水處理場的警報因為對於人體、環境都有很顯著的影響、有依賴希望能從上位階層來發報，但得到的回覆是說很困難。（於設技再進行檢討） | T40: 要 | U40: =IF($D40="ADT","1","") | V40: =IF(T40="要","1","") -> 1 | W40: =U40+V40 -> #VALUE! | X40: 要 | Y40: =IF($D40="ADT","1","") | Z40: =IF(X40="要","1","") -> 1 | AA40: =Y40+Z40 -> #VALUE! | AB40: 要 | AC40: =IF($D40="ADT","1","") | AD40: =IF(AB40="要","1","") -> 1 | AE40: =AC40+AD40 -> #VALUE! | AF40: 要 | AG40: =IF($D40="ADT","1","") | AH40: =IF(AF40="要","1","") -> 1 | AI40: =AG40+AH40 -> #VALUE! | AJ40: 要 | AK40: =IF($D40="ADT","1","") | AL40: =IF(AJ40="要","1","") -> 1 | AM40: =AK40+AL40 -> #VALUE! | AN40: 要 | AO40: =IF($D40="ADT","1","") | AP40: =IF(AN40="要","1","") -> 1 | AQ40: =AO40+AP40 -> #VALUE! | AR40: 要 | AS40: =IF($D40="ADT","1","") | AT40: =IF(AR40="要","1","") -> 1 | AU40: =AS40+AT40 -> #VALUE! | AV40: 要 | AW40: =IF($D40="ADT","1","") | AX40: =IF(AV40="要","1","") -> 1 | AY40: =AW40+AX40 -> #VALUE! | AZ40: 重要的設備的電源供應器。 計劃地更新。 協議設技決定。 ※橫(側)展開連決定在擔當者會議上協議電G更新哪個設備。 2014/10/8 各設備のDC電源装置について、「優先順位」・「交換頻度」のリストを各ライン毎に電気Gが作成中。 | BB40: 完了 | BC40: =IF($D40="ADT","1","") | BD40: =IF(BB40="完了","1","") -> 1 | BE40: =BC40+BD40 -> #VALUE! | BF40: 完了 | BG40: =IF($D40="ADT","1","") | BH40: =IF(BF40="完了","1","") -> 1 | BI40: =BG40+BH40 -> #VALUE! | BJ40: 完了 | BK40: =IF($D40="ADT","1","") | BL40: =IF(BJ40="完了","1","") -> 1 | BM40: =BK40+BL40 -> #VALUE! | BN40: 完了 | BO40: =IF($D40="ADT","1","") | BP40: =IF(BN40="完了","1","") -> 1 | BQ40: =BO40+BP40 -> #VALUE! | BR40: 完了 | BS40: =IF($D40="ADT","1","") | BT40: =IF(BR40="完了","1","") -> 1 | BU40: =BS40+BT40 -> #VALUE! | BV40: 完了 | BW40: =IF($D40="ADT","1","") | BX40: =IF(BV40="完了","1","") -> 1 | BY40: =BW40+BX40 -> #VALUE! | BZ40: 完了 | CA40: =IF($D40="ADT","1","") | CB40: =IF(BZ40="完了","1","") -> 1 | CC40: =CA40+CB40 -> #VALUE! | CD40: 完了 | CE40: =IF($D40="ADT","1","") | CF40: =IF(CD40="完了","1","") -> 1 | CG40: =CE40+CF40 -> #VALUE! | CH40: \\172.18.154.189\mfg_public\00 製造一部共通\横展開確認\設備異常報告\異常報告書(日文)\201408以降 | CI40: 0 | CJ40: 異常報告書（中文）共有フォルダ\201408以降\20140731GUT GUT水處理場電源供應器停止異常.xls | CK40: 344 | CM40: =IF(AZ40="","","CLOSE") -> CLOSE | CN40: =IF(F40="","",IF(COUNTIF(BB40:CE40,"未")=0,"CLOSE","")) -> CLOSE | CO40: 0 | CQ40: CLOSE | CR40: CLOSE | CS40: CLOSE | CT40: CLOSE | CU40: CLOSE | CV40: CLOSE | CW40: CLOSE | CX40: CLOSE
A41: 25 | B41: 41857 | C41: =MONTH(B41) -> 8 | D41: AFK | E41: IF | F41: 浅原 | G41: =COUNTIF(T41:AV41,"要") -> 0 | H41: =IF(G41>0,"1","0") -> 0 | I41: =IF(AND(D41="ADT",H41="1"),"1","0") -> 0 | J41: =H41+I41 -> 0 | K41: =IF(CM41="CLOSE",1,"") -> 1 | L41: =J41+K41 -> 1 | M41: =IF(CN41="CLOSE",1,"") -> 1 | N41: =J41+M41 -> 1 | O41: 機械系異常 | P41: 本線C/V | Q41: 巡檢時發現本線増速CV_Roll驅動側防止Sprocket_Key脫落的End_Plate上面的兩支固定螺栓有一支已經脱落了、剩下一支也快要脱落了、Plate呈現不夠穩固的狀態。和上次的Roll同一支。※上午巡檢的部分確認沒有問題。呼出設技、開啟Guillotine H/O捨板處理。這次使用樂泰( LOCTITE) 來固定螺栓。復歸結束後。F1採板開始。 | R41: 上回在8/6發生時、以確實進行螺栓増締鎖緊的對策、 再加上使用的已經是Nord-Lock的華司、但是螺栓還是鬆掉了。 原因調査中。 | S41: 【緊急對策】 使用樂泰( LOCTITE) 來固定螺栓。 （包含同様的發生位置、持續由點檢口進行目視點檢） 【恒久對策】 現段階未決定。原因調査中。 | T41: 情報 | U41: =IF($D41="ADT","1","") | V41: =IF(T41="要","1","") | W41: =U41+V41 -> #VALUE! | X41: 情報 | Y41: =IF($D41="ADT","1","") | Z41: =IF(X41="要","1","") | AA41: =Y41+Z41 -> #VALUE! | AB41: 情報 | AC41: =IF($D41="ADT","1","") | AD41: =IF(AB41="要","1","") | AE41: =AC41+AD41 -> #VALUE! | AF41: 情報 | AG41: =IF($D41="ADT","1","") | AH41: =IF(AF41="要","1","") | AI41: =AG41+AH41 -> #VALUE! | AJ41: 情報 | AK41: =IF($D41="ADT","1","") | AL41: =IF(AJ41="要","1","") | AM41: =AK41+AL41 -> #VALUE! | AN41: 情報 | AO41: =IF($D41="ADT","1","") | AP41: =IF(AN41="要","1","") | AQ41: =AO41+AP41 -> #VALUE! | AR41: 情報 | AS41: =IF($D41="ADT","1","") | AT41: =IF(AR41="要","1","") | AU41: =AS41+AT41 -> #VALUE! | AV41: 情報 | AW41: =IF($D41="ADT","1","") | AX41: =IF(AV41="要","1","") | AY41: =AW41+AX41 -> #VALUE! | AZ41: 再発。原因不明。対策未定。 | BB41: － | BC41: =IF($D41="ADT","1","") | BD41: =IF(BB41="完了","1","") | BE41: =BC41+BD41 -> #VALUE! | BF41: － | BG41: =IF($D41="ADT","1","") | BH41: =IF(BF41="完了","1","") | BI41: =BG41+BH41 -> #VALUE! | BJ41: － | BK41: =IF($D41="ADT","1","") | BL41: =IF(BJ41="完了","1","") | BM41: =BK41+BL41 -> #VALUE! | BN41: － | BO41: =IF($D41="ADT","1","") | BP41: =IF(BN41="完了","1","") | BQ41: =BO41+BP41 -> #VALUE! | BR41: － | BS41: =IF($D41="ADT","1","") | BT41: =IF(BR41="完了","1","") | BU41: =BS41+BT41 -> #VALUE! | BV41: － | BW41: =IF($D41="ADT","1","") | BX41: =IF(BV41="完了","1","") | BY41: =BW41+BX41 -> #VALUE! | BZ41: － | CA41: =IF($D41="ADT","1","") | CB41: =IF(BZ41="完了","1","") | CC41: =CA41+CB41 -> #VALUE! | CD41: － | CE41: =IF($D41="ADT","1","") | CF41: =IF(CD41="完了","1","") | CG41: =CE41+CF41 -> #VALUE! | CH41: \\172.18.154.189\mfg_public\00 製造一部共通\横展開確認\設備異常報告\異常報告書(日文)\201408以降 | CJ41: 異常報告書（中文）共有フォルダ\201408以降\20140806IF 本線CVロールシャフトエンドプレート脱落異常(中文).xls | CM41: =IF(AZ41="","","CLOSE") -> CLOSE | CN41: =IF(F41="","",IF(COUNTIF(BB41:CE41,"未")=0,"CLOSE","")) -> CLOSE | CQ41: CLOSE | CR41: CLOSE | CS41: CLOSE | CT41: CLOSE | CU41: CLOSE | CV41: CLOSE | CW41: CLOSE | CX41: CLOSE
A42: 26 | B42: 41862 | C42: =MONTH(B42) -> 8 | D42: AFK | E42: HF | F42: 浅原 | G42: =COUNTIF(T42:AV42,"要") -> 0 | H42: =IF(G42>0,"1","0") -> 0 | I42: =IF(AND(D42="ADT",H42="1"),"1","0") -> 0 | J42: =H42+I42 -> 0 | K42: =IF(CM42="CLOSE",1,"") -> 1 | L42: =J42+K42 -> 1 | M42: =IF(CN42="CLOSE",1,"") -> 1 | N42: =J42+M42 -> 1 | O42: システム系異常 | P42: ACE | Q42: ACE通信異常 | R42: 懷疑PC內藏LAN CARD的能力不足。 | S42: 擴張型NIC(LAN CARD)變更預定。 | T42: 情報 | U42: =IF($D42="ADT","1","") | V42: =IF(T42="要","1","") | W42: =U42+V42 -> #VALUE! | X42: 情報 | Y42: =IF($D42="ADT","1","") | Z42: =IF(X42="要","1","") | AA42: =Y42+Z42 -> #VALUE! | AB42: 不要 | AC42: =IF($D42="ADT","1","") | AD42: =IF(AB42="要","1","") | AE42: =AC42+AD42 -> #VALUE! | AF42: 不要 | AG42: =IF($D42="ADT","1","") | AH42: =IF(AF42="要","1","") | AI42: =AG42+AH42 -> #VALUE! | AJ42: 不要 | AK42: =IF($D42="ADT","1","") | AL42: =IF(AJ42="要","1","") | AM42: =AK42+AL42 -> #VALUE! | AN42: 不要 | AO42: =IF($D42="ADT","1","") | AP42: =IF(AN42="要","1","") | AQ42: =AO42+AP42 -> #VALUE! | AR42: 不要 | AS42: =IF($D42="ADT","1","") | AT42: =IF(AR42="要","1","") | AU42: =AS42+AT42 -> #VALUE! | AV42: 不要 | AW42: =IF($D42="ADT","1","") | AX42: =IF(AV42="要","1","") | AY42: =AW42+AX42 -> #VALUE! | AZ42: 再発。 AFKの対策としては、擴張型NIC(LAN CARD)變更。 ★ADT内のSiemens製PCでは発生していない事と（個体不良の疑い）、発生原因が特定出来ていない事から、ADTでは「情報」のみとする。（ADT電気） | BB42: － | BC42: =IF($D42="ADT","1","") | BD42: =IF(BB42="完了","1","") | BE42: =BC42+BD42 -> #VALUE! | BF42: － | BG42: =IF($D42="ADT","1","") | BH42: =IF(BF42="完了","1","") | BI42: =BG42+BH42 -> #VALUE! | BJ42: － | BK42: =IF($D42="ADT","1","") | BL42: =IF(BJ42="完了","1","") | BM42: =BK42+BL42 -> #VALUE! | BN42: － | BO42: =IF($D42="ADT","1","") | BP42: =IF(BN42="完了","1","") | BQ42: =BO42+BP42 -> #VALUE! | BR42: － | BS42: =IF($D42="ADT","1","") | BT42: =IF(BR42="完了","1","") | BU42: =BS42+BT42 -> #VALUE! | BV42: － | BW42: =IF($D42="ADT","1","") | BX42: =IF(BV42="完了","1","") | BY42: =BW42+BX42 -> #VALUE! | BZ42: － | CA42: =IF($D42="ADT","1","") | CB42: =IF(BZ42="完了","1","") | CC42: =CA42+CB42 -> #VALUE! | CD42: － | CE42: =IF($D42="ADT","1","") | CF42: =IF(CD42="完了","1","") | CG42: =CE42+CF42 -> #VALUE! | CH42: \\172.18.154.189\mfg_public\00 製造一部共通\横展開確認\設備異常報告\異常報告書(日文)\201408以降 | CI42: 1 | CJ42: 異常報告書（中文）共有フォルダ\201408以降\20140811HF ACE通信異常（再）.xls | CK42: 0 | CM42: =IF(AZ42="","","CLOSE") -> CLOSE | CN42: =IF(F42="","",IF(COUNTIF(BB42:CE42,"未")=0,"CLOSE","")) -> CLOSE | CO42: 0 | CQ42: CLOSE | CR42: CLOSE | CS42: CLOSE | CT42: CLOSE | CU42: CLOSE | CV42: CLOSE | CW42: CLOSE | CX42: CLOSE
A43: 27 | B43: 41849 | C43: =MONTH(B43) -> 7 | D43: AFK | E43: HF | F43: 三路 | G43: =COUNTIF(T43:AV43,"要") -> 0 | H43: =IF(G43>0,"1","0") -> 0 | I43: =IF(AND(D43="ADT",H43="1"),"1","0") -> 0 | J43: =H43+I43 -> 0 | K43: =IF(CM43="CLOSE",1,"") -> 1 | L43: =J43+K43 -> 1 | M43: =IF(CN43="CLOSE",1,"") -> 1 | N43: =J43+M43 -> 1 | O43: 電気系異常 | P43: 紙巻きC/V | Q43: 紙巻C/V因伺服異常（過負荷）而停止。即使更換Motor・Amp・Relay・DC電源装置也沒有良化。※在Motor単体下負荷率低沒有發生異常。將伺服的Tuning模式由AUTO變更為MANUAL後良化。 | R43: 由於Motor単独運転下負荷率低，所以假定是滾輪、惰輪的軸承劣化等機械性的要因。再加上Motor的Tuning模式為AUTO Tuning，所以累積負荷率造成異常。 | S43: Tuning模式由AUTO變更為MANUAL。 | T43: 不要 | U43: =IF($D43="ADT","1","") | V43: =IF(T43="要","1","") | W43: =U43+V43 -> #VALUE! | X43: 不要 | Y43: =IF($D43="ADT","1","") | Z43: =IF(X43="要","1","") | AA43: =Y43+Z43 -> #VALUE! | AB43: 不要 | AC43: =IF($D43="ADT","1","") | AD43: =IF(AB43="要","1","") | AE43: =AC43+AD43 -> #VALUE! | AF43: 不要 | AG43: =IF($D43="ADT","1","") | AH43: =IF(AF43="要","1","") | AI43: =AG43+AH43 -> #VALUE! | AJ43: 不要 | AK43: =IF($D43="ADT","1","") | AL43: =IF(AJ43="要","1","") | AM43: =AK43+AL43 -> #VALUE! | AN43: 不要 | AO43: =IF($D43="ADT","1","") | AP43: =IF(AN43="要","1","") | AQ43: =AO43+AP43 -> #VALUE! | AR43: 不要 | AS43: =IF($D43="ADT","1","") | AT43: =IF(AR43="要","1","") | AU43: =AS43+AT43 -> #VALUE! | AV43: 不要 | AW43: =IF($D43="ADT","1","") | AX43: =IF(AV43="要","1","") | AY43: =AW43+AX43 -> #VALUE! | AZ43: 因為AFK沒有找出根本的原因（為何負荷會變高?），所以ADT的方針就是什麼都不要做。 先看看伺服的AUTO Tuning的負荷状態再來應對。 雖然認為伺服馬達的負荷上好像有什麼大的負荷変動，但最終卻什麼都沒有發現。 擔心同様的事件時做MANUAL的設定是比較有利，但是負荷漸漸加重時AUTO則比較有利。 | BB43: － | BC43: =IF($D43="ADT","1","") | BD43: =IF(BB43="完了","1","") | BE43: =BC43+BD43 -> #VALUE! | BF43: － | BG43: =IF($D43="ADT","1","") | BH43: =IF(BF43="完了","1","") | BI43: =BG43+BH43 -> #VALUE! | BJ43: － | BK43: =IF($D43="ADT","1","") | BL43: =IF(BJ43="完了","1","") | BM43: =BK43+BL43 -> #VALUE! | BN43: － | BO43: =IF($D43="ADT","1","") | BP43: =IF(BN43="完了","1","") | BQ43: =BO43+BP43 -> #VALUE! | BR43: － | BS43: =IF($D43="ADT","1","") | BT43: =IF(BR43="完了","1","") | BU43: =BS43+BT43 -> #VALUE! | BV43: － | BW43: =IF($D43="ADT","1","") | BX43: =IF(BV43="完了","1","") | BY43: =BW43+BX43 -> #VALUE! | BZ43: － | CA43: =IF($D43="ADT","1","") | CB43: =IF(BZ43="完了","1","") | CC43: =CA43+CB43 -> #VALUE! | CD43: － | CE43: =IF($D43="ADT","1","") | CF43: =IF(CD43="完了","1","") | CG43: =CE43+CF43 -> #VALUE! | CH43: \\172.18.154.189\mfg_public\00 製造一部共通\横展開確認\設備異常報告\異常報告書(日文)\201407 | CI43: 0 | CJ43: 異常報告書（中文）共有フォルダ\201407\20140719HF 2Br紙巻CV驅動伺服馬達過負荷停止異常-中文.xls | CK43: 0 | CM43: =IF(AZ43="","","CLOSE") -> CLOSE | CN43: =IF(F43="","",IF(COUNTIF(BB43:CE43,"未")=0,"CLOSE","")) -> CLOSE | CO43: 0 | CQ43: CLOSE | CR43: CLOSE | CS43: CLOSE | CT43: CLOSE | CU43: CLOSE | CV43: CLOSE | CW43: CLOSE | CX43: CLOSE
A44: 28 | B44: 41878 | C44: =MONTH(B44) -> 8 | D44: ADT | E44: JF | F44: 三路 | G44: =COUNTIF(T44:AV44,"要") -> 6 | H44: =IF(G44>0,"1","0") -> 1 | I44: =IF(AND(D44="ADT",H44="1"),"1","0") -> 1 | J44: =H44+I44 -> 2 | K44: =IF(CM44="CLOSE",1,"") -> 1 | L44: =J44+K44 -> 3 | M44: =IF(CN44="CLOSE",1,"") -> 1 | N44: =J44+M44 -> 3 | O44: 電気系異常 | P44: 縦切り機 | Q44: 採板中由於Frame上昇，造成沒有縦切線。另外也無法做TP的操作。 ※沒有發出異常警報 | R44: Frame上昇・無法操作TP的原因 ・由於PLC不知是什麼原因造成停止。 沒有異常警報的原因 ・由於PLC停止造成警報無法出力。 | S44: ・雜訊対策検討中（ADT電気） ・改造成以本線Master PLC來監視縦切機PLC，當PLC異常時由本線Master PLC來發出警報的soft。 | T44: 要 | U44: =IF($D44="ADT","1","") -> 1 | V44: =IF(T44="要","1","") -> 1 | W44: =U44+V44 -> 2 | X44: 要 | Y44: =IF($D44="ADT","1","") -> 1 | Z44: =IF(X44="要","1","") -> 1 | AA44: =Y44+Z44 -> 2 | AB44: 要 | AC44: =IF($D44="ADT","1","") -> 1 | AD44: =IF(AB44="要","1","") -> 1 | AE44: =AC44+AD44 -> 2 | AF44: 要 | AG44: =IF($D44="ADT","1","") -> 1 | AH44: =IF(AF44="要","1","") -> 1 | AI44: =AG44+AH44 -> 2 | AJ44: 要 | AK44: =IF($D44="ADT","1","") -> 1 | AL44: =IF(AJ44="要","1","") -> 1 | AM44: =AK44+AL44 -> 2 | AN44: 要 | AO44: =IF($D44="ADT","1","") -> 1 | AP44: =IF(AN44="要","1","") -> 1 | AQ44: =AO44+AP44 -> 2 | AR44: － | AS44: =IF($D44="ADT","1","") -> 1 | AT44: =IF(AR44="要","1","") | AU44: =AS44+AT44 -> #VALUE! | AV44: － | AW44: =IF($D44="ADT","1","") -> 1 | AX44: =IF(AV44="要","1","") | AY44: =AW44+AX44 -> #VALUE! | AZ44: 改造成即使在縦切機PLC發生異常時也能夠發出警報的soft。 | BB44: 完了 | BC44: =IF($D44="ADT","1","") -> 1 | BD44: =IF(BB44="完了","1","") -> 1 | BE44: =BC44+BD44 -> 2 | BF44: 完了 | BG44: =IF($D44="ADT","1","") -> 1 | BH44: =IF(BF44="完了","1","") -> 1 | BI44: =BG44+BH44 -> 2 | BJ44: 完了 | BK44: =IF($D44="ADT","1","") -> 1 | BL44: =IF(BJ44="完了","1","") -> 1 | BM44: =BK44+BL44 -> 2 | BN44: 完了 | BO44: =IF($D44="ADT","1","") -> 1 | BP44: =IF(BN44="完了","1","") -> 1 | BQ44: =BO44+BP44 -> 2 | BR44: 完了 | BS44: =IF($D44="ADT","1","") -> 1 | BT44: =IF(BR44="完了","1","") -> 1 | BU44: =BS44+BT44 -> 2 | BV44: 完了 | BW44: =IF($D44="ADT","1","") -> 1 | BX44: =IF(BV44="完了","1","") -> 1 | BY44: =BW44+BX44 -> 2 | BZ44: － | CA44: =IF($D44="ADT","1","") -> 1 | CB44: =IF(BZ44="完了","1","") | CC44: =CA44+CB44 -> #VALUE! | CD44: － | CE44: =IF($D44="ADT","1","") -> 1 | CF44: =IF(CD44="完了","1","") | CG44: =CE44+CF44 -> #VALUE! | CH44: 異常報告書（日文）共有フォルダ\201408以降\20140827JF №1縦切機停止異常.xls | CI44: 0 | CJ44: 異常報告書（中文）共有フォルダ\201408以降\20140827JF №1縦切機停止異常.xls | CK44: 172 | CM44: =IF(AZ44="","","CLOSE") -> CLOSE | CN44: =IF(F44="","",IF(COUNTIF(BB44:CE44,"未")=0,"CLOSE","")) -> CLOSE | CO44: 9 | CQ44: CLOSE | CR44: CLOSE | CS44: CLOSE | CT44: CLOSE | CU44: CLOSE | CV44: 10/3已提出設備依賴書(電氣G)！預計12/E導入 12/30完了 CLOSE | CW44: CLOSE | CX44: CLOSE | CY44: 方針CLOSE（KF/冷修中対応）←12/30完了
A45: 29 | B45: 41881 | C45: =MONTH(B45) -> 8 | D45: ADT | E45: CF | F45: 蔵光 | G45: =COUNTIF(T45:AV45,"要") -> 5 | H45: =IF(G45>0,"1","0") -> 1 | I45: =IF(AND(D45="ADT",H45="1"),"1","0") -> 1 | J45: =H45+I45 -> 2 | K45: =IF(CM45="CLOSE",1,"") -> 1 | L45: =J45+K45 -> 3 | M45: =IF(CN45="CLOSE",1,"") -> 1 | N45: =J45+M45 -> 3 | O45: 機械系異常 | P45: SMAP | Q45: 三交代聯絡L側SMAP動作異常。整備進行確認懷疑電磁閥損壞，聯絡電氣機械進行對應。三交代協助耳部拿取，進行電磁閥更換。更換完畢經過動作測試與採板測試異常再發。將氣壓缸32號潤滑油開啟後，進行動作測試。測試OK，恢復SMAP採板。觀察無再發。 | R45: 更換電磁閥後異常再發。進行32號潤滑油的給油調整後，動作異常良化。此處氣壓缸潤滑油平時是關閉沒有使用的狀態。因此造成此次氣壓缸潤滑不足進而造成SMAP動作異常。不使用的理由是在消音器的出風口會有油汙噴濺的可能。會有品質上的疑慮。 | S45: 更換電磁閥與開啟32號潤滑油 (暫時對應-機械、電氣)。改善32號潤滑油使用方式。平時不使用=>1次/2週 (每次開啟8小時) (頻度可再檢討)電磁閥消音器使用吸油棉包覆防止潤滑油噴濺。 | T45: 不要 | U45: =IF($D45="ADT","1","") -> 1 | V45: =IF(T45="要","1","") | W45: =U45+V45 -> #VALUE! | X45: 要 | Y45: =IF($D45="ADT","1","") -> 1 | Z45: =IF(X45="要","1","") -> 1 | AA45: =Y45+Z45 -> 2 | AB45: 要 | AC45: =IF($D45="ADT","1","") -> 1 | AD45: =IF(AB45="要","1","") -> 1 | AE45: =AC45+AD45 -> 2 | AF45: 要 | AG45: =IF($D45="ADT","1","") -> 1 | AH45: =IF(AF45="要","1","") -> 1 | AI45: =AG45+AH45 -> 2 | AJ45: 要 | AK45: =IF($D45="ADT","1","") -> 1 | AL45: =IF(AJ45="要","1","") -> 1 | AM45: =AK45+AL45 -> 2 | AN45: 要 | AO45: =IF($D45="ADT","1","") -> 1 | AP45: =IF(AN45="要","1","") -> 1 | AQ45: =AO45+AP45 -> 2 | AR45: － | AS45: =IF($D45="ADT","1","") -> 1 | AT45: =IF(AR45="要","1","") | AU45: =AS45+AT45 -> #VALUE! | AV45: － | AW45: =IF($D45="ADT","1","") -> 1 | AX45: =IF(AV45="要","1","") | AY45: =AW45+AX45 -> #VALUE! | AZ45: ①於整備日常點檢表追記 Lubricator給油器相關管理項目（Oil殘量、開度Dial數値、給油）。 ②教育整備人員Lubricator給油器的作用。 ③設置Lubricator給油器的設備需全數設置Exhaust Cleaner （油霧回収機器）。（ADT全窯）（對象設備）本線SMAP、本線GATE_Shutter、FT/引入/BB PAD部。 | BB45: － | BC45: =IF($D45="ADT","1","") -> 1 | BD45: =IF(BB45="完了","1","") | BE45: =BC45+BD45 -> #VALUE! | BF45: 完了 | BG45: =IF($D45="ADT","1","") -> 1 | BH45: =IF(BF45="完了","1","") -> 1 | BI45: =BG45+BH45 -> 2 | BJ45: 完了 | BK45: =IF($D45="ADT","1","") -> 1 | BL45: =IF(BJ45="完了","1","") -> 1 | BM45: =BK45+BL45 -> 2 | BN45: 完了 | BO45: =IF($D45="ADT","1","") -> 1 | BP45: =IF(BN45="完了","1","") -> 1 | BQ45: =BO45+BP45 -> 2 | BR45: 完了 | BS45: =IF($D45="ADT","1","") -> 1 | BT45: =IF(BR45="完了","1","") -> 1 | BU45: =BS45+BT45 -> 2 | BV45: 完了 | BW45: =IF($D45="ADT","1","") -> 1 | BX45: =IF(BV45="完了","1","") -> 1 | BY45: =BW45+BX45 -> 2 | BZ45: － | CA45: =IF($D45="ADT","1","") -> 1 | CB45: =IF(BZ45="完了","1","") | CC45: =CA45+CB45 -> #VALUE! | CD45: － | CE45: =IF($D45="ADT","1","") -> 1 | CF45: =IF(CD45="完了","1","") | CG45: =CE45+CF45 -> #VALUE! | CH45: \\172.18.154.189\mfg_public\00 製造一部共通\横展開確認\設備異常報告\異常報告書(日文)\201408以降 | CI45: 0 | CJ45: 異常報告書（中文）共有フォルダ\201408以降\20140830CF L側SMAP動作異常.xls | CK45: 113 | CM45: =IF(AZ45="","","CLOSE") -> CLOSE | CN45: =IF(F45="","",IF(COUNTIF(BB45:CE45,"未")=0,"CLOSE","")) -> CLOSE | CO45: 0 | CQ45: CLOSE | CR45: 已於3/9工事日完成 | CS45: CLOSE | CT45: 12/9 1Br 完了/2Br日程調整中 （12/Eまでに完成させます） | CU45: CLOSE | CV45: CLOSE | CW45: CLOSE | CX45: CLOSE | CY45: Y/Eはどうするの？ →YF確認中。 →EFは2Brのみ残っている。（12月中に完了させます。）
A46: 30 | B46: 41880 | C46: =MONTH(B46) -> 8 | D46: AFK | E46: HF | F46: 三路 | G46: =COUNTIF(T46:AV46,"要") -> 3 | H46: =IF(G46>0,"1","0") -> 1 | I46: =IF(AND(D46="ADT",H46="1"),"1","0") -> 0 | J46: =H46+I46 -> 1 | K46: =IF(CM46="CLOSE",1,"") -> 1 | L46: =J46+K46 -> 2 | M46: =IF(CN46="CLOSE",1,"") -> 1 | N46: =J46+M46 -> 2 | O46: 機械系異常 | P46: 紙巻機 （イズミ） | Q46: 由於Cutter的紙切不良進行點檢時，發現將Cutter的上刀刃固定在LM Guide處的螺栓折損。由於螺栓更換2天後還是發生同様的異常，因此做Cutter Unit的更換。 | R46: 一直以來，上刀刃和下刀刃的上下是以下刀刃側的Liner調整，由於下刀刃的調整量已經用盡，因此在上刀刃側LM Guide處加入Liner做調整，造成Cylinder Piston(汽缸活塞)的負荷。 | S46: ・發現左右Cylinder的昇降時間點有明顯錯開時，就進行Cylinder点検而不要勉強去調整。 ・關於Cutter的紙切，下刀刃的調整量用盡時，就做Cutter Unit本体的更換。 | T46: 不要 | U46: =IF($D46="ADT","1","") | V46: =IF(T46="要","1","") | W46: =U46+V46 -> #VALUE! | X46: 不要 | Y46: =IF($D46="ADT","1","") | Z46: =IF(X46="要","1","") | AA46: =Y46+Z46 -> #VALUE! | AB46: 不要 | AC46: =IF($D46="ADT","1","") | AD46: =IF(AB46="要","1","") | AE46: =AC46+AD46 -> #VALUE! | AF46: 不要 | AG46: =IF($D46="ADT","1","") | AH46: =IF(AF46="要","1","") | AI46: =AG46+AH46 -> #VALUE! | AJ46: 要 | AK46: =IF($D46="ADT","1","") | AL46: =IF(AJ46="要","1","") -> 1 | AM46: =AK46+AL46 -> #VALUE! | AN46: 要 | AO46: =IF($D46="ADT","1","") | AP46: =IF(AN46="要","1","") -> 1 | AQ46: =AO46+AP46 -> #VALUE! | AR46: 要 | AS46: =IF($D46="ADT","1","") | AT46: =IF(AR46="要","1","") -> 1 | AU46: =AS46+AT46 -> #VALUE! | AV46: － | AW46: =IF($D46="ADT","1","") | AX46: =IF(AV46="要","1","") | AY46: =AW46+AX46 -> #VALUE! | AZ46: ・下次工事日進行CYL及LM Guide的点検。 ・点検後Cutter昇降動作如果有異常的話，請依賴機械做CYL的確認，製造方面不要勉強去做調整。 | BB46: － | BC46: =IF($D46="ADT","1","") | BD46: =IF(BB46="完了","1","") | BE46: =BC46+BD46 -> #VALUE! | BF46: － | BG46: =IF($D46="ADT","1","") | BH46: =IF(BF46="完了","1","") | BI46: =BG46+BH46 -> #VALUE! | BJ46: － | BK46: =IF($D46="ADT","1","") | BL46: =IF(BJ46="完了","1","") | BM46: =BK46+BL46 -> #VALUE! | BN46: － | BO46: =IF($D46="ADT","1","") | BP46: =IF(BN46="完了","1","") | BQ46: =BO46+BP46 -> #VALUE! | BR46: 完了 | BS46: =IF($D46="ADT","1","") | BT46: =IF(BR46="完了","1","") -> 1 | BU46: =BS46+BT46 -> #VALUE! | BV46: 完了 | BW46: =IF($D46="ADT","1","") | BX46: =IF(BV46="完了","1","") -> 1 | BY46: =BW46+BX46 -> #VALUE! | BZ46: 完了 | CA46: =IF($D46="ADT","1","") | CB46: =IF(BZ46="完了","1","") -> 1 | CC46: =CA46+CB46 -> #VALUE! | CD46: － | CE46: =IF($D46="ADT","1","") | CF46: =IF(CD46="完了","1","") | CG46: =CE46+CF46 -> #VALUE! | CH46: \\172.18.154.189\mfg_public\00 製造一部共通\横展開確認\設備異常報告\異常報告書(日文)\201408以降 | CI46: 0 | CJ46: 異常報告書（中文）共有フォルダ\201408以降\20140821HF IZUMI産業製 紙巻機切刀上刃LM_Guide固定螺栓折損異常.xls | CK46: 0 | CM46: =IF(AZ46="","","CLOSE") -> CLOSE | CN46: =IF(F46="","",IF(COUNTIF(BB46:CE46,"未")=0,"CLOSE","")) -> CLOSE | CO46: 0 | CQ46: CLOSE | CR46: CLOSE | CS46: CLOSE | CT46: CLOSE | CU46: CLOSE | CV46: CLOSE | CW46: CLOSE | CX46: CLOSE
A47: 31 | B47: 41884 | C47: =MONTH(B47) -> 9 | D47: ADT | E47: EF | F47: 万代 | G47: =COUNTIF(T47:AV47,"要") -> 3 | H47: =IF(G47>0,"1","0") -> 1 | I47: =IF(AND(D47="ADT",H47="1"),"1","0") -> 1 | J47: =H47+I47 -> 2 | K47: =IF(CM47="CLOSE",1,"") -> 1 | L47: =J47+K47 -> 3 | M47: =IF(CN47="CLOSE",1,"") -> 1 | N47: =J47+M47 -> 3 | O47: 機械系異常 | P47: 採板Robot | Q47: 6:24 6POS 採板ROBOT發生紙抓動作異常。6:30 切替2Bｒ全採。6:40 確認到6POS左上紙抓CYL脫落。呼出整備。7:10 6POS左上部 紙抓CYL交換作業開始。7:40 CYL更換後、進行試板流及CYL動作速度調整。8:15 1Bｒ恢復全採 | S47: 壓力設定在0.13Mpa。預定變更CYL型式 MGPL12→MGPM12(額定扭矩up） | T47: 不要 | U47: =IF($D47="ADT","1","") -> 1 | V47: =IF(T47="要","1","") | W47: =U47+V47 -> #VALUE! | X47: 不要 | Y47: =IF($D47="ADT","1","") -> 1 | Z47: =IF(X47="要","1","") | AA47: =Y47+Z47 -> #VALUE! | AB47: 要 | AC47: =IF($D47="ADT","1","") -> 1 | AD47: =IF(AB47="要","1","") -> 1 | AE47: =AC47+AD47 -> 2 | AF47: 要 | AG47: =IF($D47="ADT","1","") -> 1 | AH47: =IF(AF47="要","1","") -> 1 | AI47: =AG47+AH47 -> 2 | AJ47: 不要 | AK47: =IF($D47="ADT","1","") -> 1 | AL47: =IF(AJ47="要","1","") | AM47: =AK47+AL47 -> #VALUE! | AN47: 要 | AO47: =IF($D47="ADT","1","") -> 1 | AP47: =IF(AN47="要","1","") -> 1 | AQ47: =AO47+AP47 -> 2 | AR47: － | AS47: =IF($D47="ADT","1","") -> 1 | AT47: =IF(AR47="要","1","") | AU47: =AS47+AT47 -> #VALUE! | AV47: － | AW47: =IF($D47="ADT","1","") -> 1 | AX47: =IF(AV47="要","1","") | AY47: =AW47+AX47 -> #VALUE! | AZ47: 壓力設定在0.13Mpa。預定變更CYL型式 MGPL12→MGPM12(額定扭矩up）(結論）0.20Mpaで使用することでCLOSE | BB47: － | BC47: =IF($D47="ADT","1","") -> 1 | BD47: =IF(BB47="完了","1","") | BE47: =BC47+BD47 -> #VALUE! | BF47: － | BG47: =IF($D47="ADT","1","") -> 1 | BH47: =IF(BF47="完了","1","") | BI47: =BG47+BH47 -> #VALUE! | BJ47: 完了 | BK47: =IF($D47="ADT","1","") -> 1 | BL47: =IF(BJ47="完了","1","") -> 1 | BM47: =BK47+BL47 -> 2 | BN47: 完了 | BO47: =IF($D47="ADT","1","") -> 1 | BP47: =IF(BN47="完了","1","") -> 1 | BQ47: =BO47+BP47 -> 2 | BR47: － | BS47: =IF($D47="ADT","1","") -> 1 | BT47: =IF(BR47="完了","1","") | BU47: =BS47+BT47 -> #VALUE! | BV47: 完了 | BW47: =IF($D47="ADT","1","") -> 1 | BX47: =IF(BV47="完了","1","") -> 1 | BY47: =BW47+BX47 -> 2 | BZ47: － | CA47: =IF($D47="ADT","1","") -> 1 | CB47: =IF(BZ47="完了","1","") | CC47: =CA47+CB47 -> #VALUE! | CD47: － | CE47: =IF($D47="ADT","1","") -> 1 | CF47: =IF(CD47="完了","1","") | CG47: =CE47+CF47 -> #VALUE! | CH47: \\172.18.154.189\mfg_public\00 製造一部共通\横展開確認\設備異常報告\異常報告書(日文)\201408以降 | CI47: 1 | CJ47: 異常報告書（中文）共有フォルダ\201408以降\20140902EF 6P採板RB紙掴みシリンダー異常rev.1.xls | CK47: 29 | CM47: =IF(AZ47="","","CLOSE") -> CLOSE | CN47: =IF(F47="","",IF(COUNTIF(BB47:CE47,"未")=0,"CLOSE","")) -> CLOSE | CO47: 6 | CQ47: CLOSE | CR47: CLOSE | CS47: CLOSE | CT47: CLOSE | CU47: CLOSE | CV47: CLOSE | CW47: CLOSE | CX47: CLOSE
A48: 32 | B48: 41892 | C48: =MONTH(B48) -> 9 | D48: ADT | E48: YF | F48: 仕明 | G48: =COUNTIF(T48:AV48,"要") -> 5 | H48: =IF(G48>0,"1","0") -> 1 | I48: =IF(AND(D48="ADT",H48="1"),"1","0") -> 1 | J48: =H48+I48 -> 2 | K48: =IF(CM48="CLOSE",1,"") -> 1 | L48: =J48+K48 -> 3 | M48: =IF(CN48="CLOSE",1,"") -> 1 | N48: =J48+M48 -> 3 | O48: 機械系異常 | P48: SMAP | Q48: 時規皮帶劣化，導致作動不良 | S48: 1.進行L側SMAP時規皮帶及調速閥點檢(橫展開)。2.平時SMAP作動速度發生變化時立即進行調整，若無法調整連絡機械人員進行確認 3.CYLINDER交換時連同調速閥也一倂更換 | T48: 要 | U48: =IF($D48="ADT","1","") -> 1 | V48: =IF(T48="要","1","") -> 1 | W48: =U48+V48 -> 2 | X48: － | Y48: =IF($D48="ADT","1","") -> 1 | Z48: =IF(X48="要","1","") | AA48: =Y48+Z48 -> #VALUE! | AB48: 要 | AC48: =IF($D48="ADT","1","") -> 1 | AD48: =IF(AB48="要","1","") -> 1 | AE48: =AC48+AD48 -> 2 | AF48: 要 | AG48: =IF($D48="ADT","1","") -> 1 | AH48: =IF(AF48="要","1","") -> 1 | AI48: =AG48+AH48 -> 2 | AJ48: 要 | AK48: =IF($D48="ADT","1","") -> 1 | AL48: =IF(AJ48="要","1","") -> 1 | AM48: =AK48+AL48 -> 2 | AN48: 要 | AO48: =IF($D48="ADT","1","") -> 1 | AP48: =IF(AN48="要","1","") -> 1 | AQ48: =AO48+AP48 -> 2 | AR48: － | AS48: =IF($D48="ADT","1","") -> 1 | AT48: =IF(AR48="要","1","") | AU48: =AS48+AT48 -> #VALUE! | AV48: － | AW48: =IF($D48="ADT","1","") -> 1 | AX48: =IF(AV48="要","1","") | AY48: =AW48+AX48 -> #VALUE! | AZ48: 1.進行L側SMAP時規皮帶及調速閥點檢(橫展開)。2.平時SMAP作動速度發生變化時立即進行調整，若無法調整連絡機械人員進行確認 3.CYLINDER更換時連同調速閥也一倂更換 | BB48: 完了 | BC48: =IF($D48="ADT","1","") -> 1 | BD48: =IF(BB48="完了","1","") -> 1 | BE48: =BC48+BD48 -> 2 | BF48: － | BG48: =IF($D48="ADT","1","") -> 1 | BH48: =IF(BF48="完了","1","") | BI48: =BG48+BH48 -> #VALUE! | BJ48: 完了 | BK48: =IF($D48="ADT","1","") -> 1 | BL48: =IF(BJ48="完了","1","") -> 1 | BM48: =BK48+BL48 -> 2 | BN48: 完了 | BO48: =IF($D48="ADT","1","") -> 1 | BP48: =IF(BN48="完了","1","") -> 1 | BQ48: =BO48+BP48 -> 2 | BR48: 完了 | BS48: =IF($D48="ADT","1","") -> 1 | BT48: =IF(BR48="完了","1","") -> 1 | BU48: =BS48+BT48 -> 2 | BV48: 完了 | BW48: =IF($D48="ADT","1","") -> 1 | BX48: =IF(BV48="完了","1","") -> 1 | BY48: =BW48+BX48 -> 2 | BZ48: － | CA48: =IF($D48="ADT","1","") -> 1 | CB48: =IF(BZ48="完了","1","") | CC48: =CA48+CB48 -> #VALUE! | CD48: － | CE48: =IF($D48="ADT","1","") -> 1 | CF48: =IF(CD48="完了","1","") | CG48: =CE48+CF48 -> #VALUE! | CH48: \\172.18.154.189\mfg_public\00 製造一部共通\横展開確認\設備異常報告\異常報告書(日文)\201408以降 | CI48: 0 | CJ48: 異常報告書（中文）共有フォルダ\201408以降\20140910 YF 包裝 R側 SMAP異常報告書.xls | CK48: 92 | CM48: =IF(AZ48="","","CLOSE") -> CLOSE | CN48: =IF(F48="","",IF(COUNTIF(BB48:CE48,"未")=0,"CLOSE","")) -> CLOSE | CO48: 3 | CQ48: CLOSE | CR48: CLOSE | CS48: CLOSE | CT48: CLOSE | CU48: CLOSE | CV48: CLOSE | CW48: CLOSE | CX48: CLOSE
A49: 33 | B49: 41889 | C49: =MONTH(B49) -> 9 | D49: 高砂 | E49: TDSⅡ | F49: 三路 | G49: =COUNTIF(T49:AV49,"要") -> 1 | H49: =IF(G49>0,"1","0") -> 1 | I49: =IF(AND(D49="ADT",H49="1"),"1","0") -> 0 | J49: =H49+I49 -> 1 | K49: =IF(CM49="CLOSE",1,"") -> 1 | L49: =J49+K49 -> 2 | M49: =IF(CN49="CLOSE",1,"") -> 1 | N49: =J49+M49 -> 2 | O49: 機械系異常 | P49: 搬送CV | Q49: 由於皮帶摩耗 導致鐵絲呈現外露状態 因此進行皮帶更換。由於搬送皮帶偏移到Pulley突出部位的上方、因接觸而摩耗 | S49: 做為預防措置、確認皮帶摩耗状態時若發現偏移狀況、需隨時進行Pulley的對芯調整 | T49: 不要 | U49: =IF($D49="ADT","1","") | V49: =IF(T49="要","1","") | W49: =U49+V49 -> #VALUE! | X49: 不要 | Y49: =IF($D49="ADT","1","") | Z49: =IF(X49="要","1","") | AA49: =Y49+Z49 -> #VALUE! | AB49: 不要 | AC49: =IF($D49="ADT","1","") | AD49: =IF(AB49="要","1","") | AE49: =AC49+AD49 -> #VALUE! | AF49: 不要 | AG49: =IF($D49="ADT","1","") | AH49: =IF(AF49="要","1","") | AI49: =AG49+AH49 -> #VALUE! | AJ49: 不要 | AK49: =IF($D49="ADT","1","") | AL49: =IF(AJ49="要","1","") | AM49: =AK49+AL49 -> #VALUE! | AN49: 不要 | AO49: =IF($D49="ADT","1","") | AP49: =IF(AN49="要","1","") | AQ49: =AO49+AP49 -> #VALUE! | AR49: 不要 | AS49: =IF($D49="ADT","1","") | AT49: =IF(AR49="要","1","") | AU49: =AS49+AT49 -> #VALUE! | AV49: 要 | AW49: =IF($D49="ADT","1","") | AX49: =IF(AV49="要","1","") -> 1 | AY49: =AW49+AX49 -> #VALUE! | AZ49: 做為預防措置、確認皮帶摩耗状態時若發現偏移狀況、需隨時進行Pulley的對芯調整 | BB49: － | BC49: =IF($D49="ADT","1","") | BD49: =IF(BB49="完了","1","") | BE49: =BC49+BD49 -> #VALUE! | BF49: － | BG49: =IF($D49="ADT","1","") | BH49: =IF(BF49="完了","1","") | BI49: =BG49+BH49 -> #VALUE! | BJ49: － | BK49: =IF($D49="ADT","1","") | BL49: =IF(BJ49="完了","1","") | BM49: =BK49+BL49 -> #VALUE! | BN49: － | BO49: =IF($D49="ADT","1","") | BP49: =IF(BN49="完了","1","") | BQ49: =BO49+BP49 -> #VALUE! | BR49: － | BS49: =IF($D49="ADT","1","") | BT49: =IF(BR49="完了","1","") | BU49: =BS49+BT49 -> #VALUE! | BV49: － | BW49: =IF($D49="ADT","1","") | BX49: =IF(BV49="完了","1","") | BY49: =BW49+BX49 -> #VALUE! | BZ49: － | CA49: =IF($D49="ADT","1","") | CB49: =IF(BZ49="完了","1","") | CC49: =CA49+CB49 -> #VALUE! | CD49: 完了 | CE49: =IF($D49="ADT","1","") | CF49: =IF(CD49="完了","1","") -> 1 | CG49: =CE49+CF49 -> #VALUE! | CH49: O:\00 製造一部共通\横展開確認\設備異常報告\異常報告書(日文)\201408以降\20140907TDS2 搬送ベルト異常Trouble報告.xlsx | CI49: 0 | CJ49: 異常報告書（中文）共有フォルダ\201408以降\20140907TDS2 搬送異常Trouble報告.xls | CK49: 0 | CL49: O:\00 製造一部共通\横展開確認\設備異常報告\異常報告書(日文)\201408以降\ADT OFF切機擴出CV驅動惰輪.xls | CM49: =IF(AZ49="","","CLOSE") -> CLOSE | CN49: =IF(F49="","",IF(COUNTIF(BB49:CE49,"未")=0,"CLOSE","")) -> CLOSE | CO49: 180 | CQ49: CLOSE | CR49: CLOSE | CS49: CLOSE | CT49: CLOSE | CU49: CLOSE | CV49: CLOSE | CW49: CLOSE | CX49: CLOSE
A50: 34 | B50: 41875 | C50: =MONTH(B50) -> 8 | D50: 高砂 | E50: GUT | F50: 三路 | G50: =COUNTIF(T50:AV50,"要") -> 3 | H50: =IF(G50>0,"1","0") -> 1 | I50: =IF(AND(D50="ADT",H50="1"),"1","0") -> 0 | J50: =H50+I50 -> 1 | K50: =IF(CM50="CLOSE",1,"") -> 1 | L50: =J50+K50 -> 2 | M50: =IF(CN50="CLOSE",1,"") -> 1 | N50: =J50+M50 -> 2 | O50: 機械系異常 | P50: 紙巻機出紙皮帶 | Q50: 因出紙皮帶Servo Amp（過負荷）而發生異常停止。確認驅動部時發現馬達温度異常升高。 | R50: 確認到№1、№7 皮帶（兩端）偏移並接觸到側邊的護蓋、引起馬達過負載。 | S50: 與設技檢討中 | T50: － | U50: =IF($D50="ADT","1","") | V50: =IF(T50="要","1","") | W50: =U50+V50 -> #VALUE! | X50: － | Y50: =IF($D50="ADT","1","") | Z50: =IF(X50="要","1","") | AA50: =Y50+Z50 -> #VALUE! | AB50: － | AC50: =IF($D50="ADT","1","") | AD50: =IF(AB50="要","1","") | AE50: =AC50+AD50 -> #VALUE! | AF50: － | AG50: =IF($D50="ADT","1","") | AH50: =IF(AF50="要","1","") | AI50: =AG50+AH50 -> #VALUE! | AJ50: 要 | AK50: =IF($D50="ADT","1","") | AL50: =IF(AJ50="要","1","") -> 1 | AM50: =AK50+AL50 -> #VALUE! | AN50: 要 | AO50: =IF($D50="ADT","1","") | AP50: =IF(AN50="要","1","") -> 1 | AQ50: =AO50+AP50 -> #VALUE! | AR50: 要 | AS50: =IF($D50="ADT","1","") | AT50: =IF(AR50="要","1","") -> 1 | AU50: =AS50+AT50 -> #VALUE! | AV50: － | AW50: =IF($D50="ADT","1","") | AX50: =IF(AV50="要","1","") | AY50: =AW50+AX50 -> #VALUE! | AZ50: 進行異常報告書的互閱，並針對紙排出Belt的伺服有過負荷異常時及紙有傾斜被捲的状況時，教育現場人員可能是送紙Belt發生偏移。 | BB50: － | BC50: =IF($D50="ADT","1","") | BD50: =IF(BB50="完了","1","") | BE50: =BC50+BD50 -> #VALUE! | BF50: － | BG50: =IF($D50="ADT","1","") | BH50: =IF(BF50="完了","1","") | BI50: =BG50+BH50 -> #VALUE! | BJ50: － | BK50: =IF($D50="ADT","1","") | BL50: =IF(BJ50="完了","1","") | BM50: =BK50+BL50 -> #VALUE! | BN50: － | BO50: =IF($D50="ADT","1","") | BP50: =IF(BN50="完了","1","") | BQ50: =BO50+BP50 -> #VALUE! | BR50: 完了 | BS50: =IF($D50="ADT","1","") | BT50: =IF(BR50="完了","1","") -> 1 | BU50: =BS50+BT50 -> #VALUE! | BV50: 完了 | BW50: =IF($D50="ADT","1","") | BX50: =IF(BV50="完了","1","") -> 1 | BY50: =BW50+BX50 -> #VALUE! | BZ50: 完了 | CA50: =IF($D50="ADT","1","") | CB50: =IF(BZ50="完了","1","") -> 1 | CC50: =CA50+CB50 -> #VALUE! | CD50: － | CE50: =IF($D50="ADT","1","") | CF50: =IF(CD50="完了","1","") | CG50: =CE50+CF50 -> #VALUE! | CH50: \\172.18.154.189\mfg_public\00 製造一部共通\横展開確認\設備異常報告\異常報告書(日文)\201408以降 | CI50: 0 | CJ50: 異常報告書（中文）共有フォルダ\201408以降\20140824GUT GUT3紙機送紙偏移異常.xls | CK50: 2697 | CM50: =IF(AZ50="","","CLOSE") -> CLOSE | CN50: =IF(F50="","",IF(COUNTIF(BB50:CE50,"未")=0,"CLOSE","")) -> CLOSE | CO50: 160 | CQ50: CLOSE | CR50: CLOSE | CS50: CLOSE | CT50: CLOSE | CU50: CLOSE | CV50: CLOSE | CW50: CLOSE | CX50: CLOSE
A51: 35 | B51: 41877 | C51: =MONTH(B51) -> 8 | D51: AFK | E51: GUT | F51: 三路 | G51: =COUNTIF(T51:AV51,"要") -> 0 | H51: =IF(G51>0,"1","0") -> 0 | I51: =IF(AND(D51="ADT",H51="1"),"1","0") -> 0 | J51: =H51+I51 -> 0 | K51: =IF(CM51="CLOSE",1,"") -> 1 | L51: =J51+K51 -> 1 | M51: =IF(CN51="CLOSE",1,"") -> 1 | N51: =J51+M51 -> 1 | O51: 電気系異常 | P51: 移載機 | Q51: 中班在進行事前準備時, 進行設備運轉, 並投入刮傷檢查用的樣品, 此時, 上流側№1移載機（Master、Slave兩者）Servo發生異常無法復歸, 因此呼出設技（電氣T）。 | R51: 計畫於OFF切№1～№3『搬送C/V相關參數變更』並進行作業。由於OFF切№1及2是在生産中實施的, 變更後也無設備上的異常。原本打算№3也同様要重寫『搬送C/V參數』,但是誤操作變更了上流№1移載機（Splave側）的參數。此重寫作業並未事先聯絡製造, 另外因為產線計畫停止中,所以沒有確認動作就結束此作業。 | S51: 因為PLC Soft裡面有同様的回路, 導致誤操作, 變更了移載機的參數, 為了防止弄錯 軸No.的位置, 會直接在PLC Soft内進行軸№表示以防止失誤。 | T51: 情報 | U51: =IF($D51="ADT","1","") | V51: =IF(T51="要","1","") | W51: =U51+V51 -> #VALUE! | X51: 情報 | Y51: =IF($D51="ADT","1","") | Z51: =IF(X51="要","1","") | AA51: =Y51+Z51 -> #VALUE! | AB51: 情報 | AC51: =IF($D51="ADT","1","") | AD51: =IF(AB51="要","1","") | AE51: =AC51+AD51 -> #VALUE! | AF51: 情報 | AG51: =IF($D51="ADT","1","") | AH51: =IF(AF51="要","1","") | AI51: =AG51+AH51 -> #VALUE! | AJ51: 情報 | AK51: =IF($D51="ADT","1","") | AL51: =IF(AJ51="要","1","") | AM51: =AK51+AL51 -> #VALUE! | AN51: 情報 | AO51: =IF($D51="ADT","1","") | AP51: =IF(AN51="要","1","") | AQ51: =AO51+AP51 -> #VALUE! | AR51: 情報 | AS51: =IF($D51="ADT","1","") | AT51: =IF(AR51="要","1","") | AU51: =AS51+AT51 -> #VALUE! | AV51: 情報 | AW51: =IF($D51="ADT","1","") | AX51: =IF(AV51="要","1","") | AY51: =AW51+AX51 -> #VALUE! | AZ51: Soft變更時製造的立會及不要忘記聯絡的事項，已向ADT設技再次依賴完畢。 | BB51: － | BC51: =IF($D51="ADT","1","") | BD51: =IF(BB51="完了","1","") | BE51: =BC51+BD51 -> #VALUE! | BF51: － | BG51: =IF($D51="ADT","1","") | BH51: =IF(BF51="完了","1","") | BI51: =BG51+BH51 -> #VALUE! | BJ51: － | BK51: =IF($D51="ADT","1","") | BL51: =IF(BJ51="完了","1","") | BM51: =BK51+BL51 -> #VALUE! | BN51: － | BO51: =IF($D51="ADT","1","") | BP51: =IF(BN51="完了","1","") | BQ51: =BO51+BP51 -> #VALUE! | BR51: － | BS51: =IF($D51="ADT","1","") | BT51: =IF(BR51="完了","1","") | BU51: =BS51+BT51 -> #VALUE! | BV51: － | BW51: =IF($D51="ADT","1","") | BX51: =IF(BV51="完了","1","") | BY51: =BW51+BX51 -> #VALUE! | BZ51: － | CA51: =IF($D51="ADT","1","") | CB51: =IF(BZ51="完了","1","") | CC51: =CA51+CB51 -> #VALUE! | CD51: － | CE51: =IF($D51="ADT","1","") | CF51: =IF(CD51="完了","1","") | CG51: =CE51+CF51 -> #VALUE! | CH51: \\172.18.154.189\mfg_public\00 製造一部共通\横展開確認\設備異常報告\異常報告書(日文)\201408以降 | CI51: 0 | CJ51: 異常報告書（中文）共有フォルダ\201408以降\20140826GUT OFF切3上流移載機異常.xls | CK51: 0 | CM51: =IF(AZ51="","","CLOSE") -> CLOSE | CN51: =IF(F51="","",IF(COUNTIF(BB51:CE51,"未")=0,"CLOSE","")) -> CLOSE | CO51: 0 | CQ51: CLOSE | CR51: CLOSE | CS51: CLOSE | CT51: CLOSE | CU51: CLOSE | CV51: CLOSE | CW51: CLOSE | CX51: CLOSE
A52: 36 | B52: 41894 | C52: =MONTH(B52) -> 9 | D52: 高砂 | E52: ＷＩＴ | F52: 三路 | G52: =COUNTIF(T52:AV52,"要") -> 2 | H52: =IF(G52>0,"1","0") -> 1 | I52: =IF(AND(D52="ADT",H52="1"),"1","0") -> 0 | J52: =H52+I52 -> 1 | K52: =IF(CM52="CLOSE",1,"") -> 1 | L52: =J52+K52 -> 2 | M52: =IF(CN52="CLOSE",1,"") -> 1 | N52: =J52+M52 -> 2 | O52: 機械系異常 | P52: 移載機 | Q52: G8→G7.5JC之後, 上流移載機發生吸著異常。在無板裂、基板亦無異常的狀態下, 移載機旋回之後, 未停在原本應該停止的位置上確認過旋回位置的指令之後, 「90度」的設定沒有問題, 但是旋回不足, 只有回轉了約87度左右 | R52: 原因不明 | S52: 強調mark標示方式, 即使從旋回部的安全柵外面也可看到旋回位置並定時確認 （每小時） | T52: － | U52: =IF($D52="ADT","1","") | V52: =IF(T52="要","1","") | W52: =U52+V52 -> #VALUE! | X52: － | Y52: =IF($D52="ADT","1","") | Z52: =IF(X52="要","1","") | AA52: =Y52+Z52 -> #VALUE! | AB52: 不要 | AC52: =IF($D52="ADT","1","") | AD52: =IF(AB52="要","1","") | AE52: =AC52+AD52 -> #VALUE! | AF52: 不要 | AG52: =IF($D52="ADT","1","") | AH52: =IF(AF52="要","1","") | AI52: =AG52+AH52 -> #VALUE! | AJ52: 不要 | AK52: =IF($D52="ADT","1","") | AL52: =IF(AJ52="要","1","") | AM52: =AK52+AL52 -> #VALUE! | AN52: 不要 | AO52: =IF($D52="ADT","1","") | AP52: =IF(AN52="要","1","") | AQ52: =AO52+AP52 -> #VALUE! | AR52: 要 | AS52: =IF($D52="ADT","1","") | AT52: =IF(AR52="要","1","") -> 1 | AU52: =AS52+AT52 -> #VALUE! | AV52: 要 | AW52: =IF($D52="ADT","1","") | AX52: =IF(AV52="要","1","") -> 1 | AY52: =AW52+AX52 -> #VALUE! | AZ52: 雖然原因不明，但要確認Robot Hand裝設處是否有Mark標示。 | BB52: － | BC52: =IF($D52="ADT","1","") | BD52: =IF(BB52="完了","1","") | BE52: =BC52+BD52 -> #VALUE! | BF52: － | BG52: =IF($D52="ADT","1","") | BH52: =IF(BF52="完了","1","") | BI52: =BG52+BH52 -> #VALUE! | BJ52: － | BK52: =IF($D52="ADT","1","") | BL52: =IF(BJ52="完了","1","") | BM52: =BK52+BL52 -> #VALUE! | BN52: － | BO52: =IF($D52="ADT","1","") | BP52: =IF(BN52="完了","1","") | BQ52: =BO52+BP52 -> #VALUE! | BR52: － | BS52: =IF($D52="ADT","1","") | BT52: =IF(BR52="完了","1","") | BU52: =BS52+BT52 -> #VALUE! | BV52: － | BW52: =IF($D52="ADT","1","") | BX52: =IF(BV52="完了","1","") | BY52: =BW52+BX52 -> #VALUE! | BZ52: 完了 | CA52: =IF($D52="ADT","1","") | CB52: =IF(BZ52="完了","1","") -> 1 | CC52: =CA52+CB52 -> #VALUE! | CD52: 完了 | CE52: =IF($D52="ADT","1","") | CF52: =IF(CD52="完了","1","") -> 1 | CG52: =CE52+CF52 -> #VALUE! | CH52: \\172.18.154.189\mfg_public\00 製造一部共通\横展開確認\設備異常報告\異常報告書(日文)\201409以降 | CI52: 0 | CJ52: 異常報告書（中文）共有フォルダ\201408以降\20140912 WIT1 上流移載機旋回異常.xls | CK52: 1086 | CL52: 異常報告書（中文）共有フォルダ\201408以降\TAS 自動線移載機固定螺絲寫真及OFF原點標示寫真.xlsx | CM52: =IF(AZ52="","","CLOSE") -> CLOSE | CN52: =IF(F52="","",IF(COUNTIF(BB52:CE52,"未")=0,"CLOSE","")) -> CLOSE | CO52: 60 | CQ52: CLOSE | CR52: CLOSE | CS52: CLOSE | CT52: CLOSE | CU52: CLOSE | CV52: CLOSE | CW52: CLOSE | CX52: CLOSE
A53: 37 | B53: 41890 | C53: =MONTH(B53) -> 9 | D53: 高砂 | E53: GF | F53: 三路 | G53: =COUNTIF(T53:AV53,"要") -> 6 | H53: =IF(G53>0,"1","0") -> 1 | I53: =IF(AND(D53="ADT",H53="1"),"1","0") -> 0 | J53: =H53+I53 -> 1 | K53: =IF(CM53="CLOSE",1,"") -> 1 | L53: =J53+K53 -> 2 | M53: =IF(CN53="CLOSE",1,"") -> 1 | N53: =J53+M53 -> 2 | O53: 機械系異常 | P53: №2循環C/V | Q53: 循環巡檢時，發現#2CV Tail pully的Shaft斷裂狀況下在進行C/V回転。利用設技(工作)呼出対応進行予備Pully的更換 | R53: 推測是Belt張力過緊造成疲乏破壊。 | S53: Belt張力調整一斉做修正及實施Shaft和Drum接合部分的目視点検。 但是此次断裂的部分是Drum内部，所以無法做同一處的点検，因此變成只點檢外側。 | T53: 要 | U53: =IF($D53="ADT","1","") | V53: =IF(T53="要","1","") -> 1 | W53: =U53+V53 -> #VALUE! | X53: 要 | Y53: =IF($D53="ADT","1","") | Z53: =IF(X53="要","1","") -> 1 | AA53: =Y53+Z53 -> #VALUE! | AB53: 要 | AC53: =IF($D53="ADT","1","") | AD53: =IF(AB53="要","1","") -> 1 | AE53: =AC53+AD53 -> #VALUE! | AF53: 要 | AG53: =IF($D53="ADT","1","") | AH53: =IF(AF53="要","1","") -> 1 | AI53: =AG53+AH53 -> #VALUE! | AJ53: 要 | AK53: =IF($D53="ADT","1","") | AL53: =IF(AJ53="要","1","") -> 1 | AM53: =AK53+AL53 -> #VALUE! | AN53: 要 | AO53: =IF($D53="ADT","1","") | AP53: =IF(AN53="要","1","") -> 1 | AQ53: =AO53+AP53 -> #VALUE! | AR53: － | AS53: =IF($D53="ADT","1","") | AT53: =IF(AR53="要","1","") | AU53: =AS53+AT53 -> #VALUE! | AV53: － | AW53: =IF($D53="ADT","1","") | AX53: =IF(AV53="要","1","") | AY53: =AW53+AX53 -> #VALUE! | AZ53: ・在工事日等點檢各Belt的張力是否過緊。 | BB53: 完了 | BC53: =IF($D53="ADT","1","") | BD53: =IF(BB53="完了","1","") -> 1 | BE53: =BC53+BD53 -> #VALUE! | BF53: 完了 | BG53: =IF($D53="ADT","1","") | BH53: =IF(BF53="完了","1","") -> 1 | BI53: =BG53+BH53 -> #VALUE! | BJ53: 完了 | BK53: =IF($D53="ADT","1","") | BL53: =IF(BJ53="完了","1","") -> 1 | BM53: =BK53+BL53 -> #VALUE! | BN53: 完了 | BO53: =IF($D53="ADT","1","") | BP53: =IF(BN53="完了","1","") -> 1 | BQ53: =BO53+BP53 -> #VALUE! | BR53: 完了 | BS53: =IF($D53="ADT","1","") | BT53: =IF(BR53="完了","1","") -> 1 | BU53: =BS53+BT53 -> #VALUE! | BV53: 完了 | BW53: =IF($D53="ADT","1","") | BX53: =IF(BV53="完了","1","") -> 1 | BY53: =BW53+BX53 -> #VALUE! | BZ53: － | CA53: =IF($D53="ADT","1","") | CB53: =IF(BZ53="完了","1","") | CC53: =CA53+CB53 -> #VALUE! | CD53: － | CE53: =IF($D53="ADT","1","") | CF53: =IF(CD53="完了","1","") | CG53: =CE53+CF53 -> #VALUE! | CH53: O:\00 製造一部共通\横展開確認\設備異常報告\異常報告書(日文)\201408以降\20140908GF No.2循環CV(クラッシャー前)プーリシャフト破断.xls | CI53: 0 | CJ53: O:\00 製造一部共通\横展開確認\設備異常報告\異常報告書(中文)\201408以降\20140908GF No.2循環CV(Crusher前)Pully Shaft斷裂.xls | CK53: 0 | CM53: =IF(AZ53="","","CLOSE") -> CLOSE | CN53: =IF(F53="","",IF(COUNTIF(BB53:CE53,"未")=0,"CLOSE","")) -> CLOSE | CO53: 0 | CQ53: CLOSE | CR53: CLOSE | CS53: CLOSE | CT53: CLOSE | CU53: CLOSE | CV53: CLOSE | CW53: CLOSE | CX53: CLOSE
A54: 38 | B54: 41906 | C54: =MONTH(B54) -> 9 | D54: ADT | E54: ZF | F54: 佐倉 | G54: =COUNTIF(T54:AV54,"要") -> 4 | H54: =IF(G54>0,"1","0") -> 1 | I54: =IF(AND(D54="ADT",H54="1"),"1","0") -> 1 | J54: =H54+I54 -> 2 | K54: =IF(CM54="CLOSE",1,"") -> 1 | L54: =J54+K54 -> 3 | M54: =IF(CN54="CLOSE",1,"") -> 1 | N54: =J54+M54 -> 3 | O54: 機械系異常 | P54: 横切り機（BUR) | Q54: BUR Base上裝設的螺母鬆脫掉下。 | R54: 有裝上Nord-Lock washers但鬆脫。原因不明 | S54: 実施鎖緊。 | T54: － | U54: =IF($D54="ADT","1","") -> 1 | V54: =IF(T54="要","1","") | W54: =U54+V54 -> #VALUE! | X54: 要 | Y54: =IF($D54="ADT","1","") -> 1 | Z54: =IF(X54="要","1","") -> 1 | AA54: =Y54+Z54 -> 2 | AB54: 要 | AC54: =IF($D54="ADT","1","") -> 1 | AD54: =IF(AB54="要","1","") -> 1 | AE54: =AC54+AD54 -> 2 | AF54: 要 | AG54: =IF($D54="ADT","1","") -> 1 | AH54: =IF(AF54="要","1","") -> 1 | AI54: =AG54+AH54 -> 2 | AJ54: － | AK54: =IF($D54="ADT","1","") -> 1 | AL54: =IF(AJ54="要","1","") | AM54: =AK54+AL54 -> #VALUE! | AN54: 要 | AO54: =IF($D54="ADT","1","") -> 1 | AP54: =IF(AN54="要","1","") -> 1 | AQ54: =AO54+AP54 -> 2 | AR54: － | AS54: =IF($D54="ADT","1","") -> 1 | AT54: =IF(AR54="要","1","") | AU54: =AS54+AT54 -> #VALUE! | AV54: － | AW54: =IF($D54="ADT","1","") -> 1 | AX54: =IF(AV54="要","1","") | AY54: =AW54+AX54 -> #VALUE! | AZ54: 確認是否鬆脫及鎖緊 | BB54: － | BC54: =IF($D54="ADT","1","") -> 1 | BD54: =IF(BB54="完了","1","") | BE54: =BC54+BD54 -> #VALUE! | BF54: 完了 | BG54: =IF($D54="ADT","1","") -> 1 | BH54: =IF(BF54="完了","1","") -> 1 | BI54: =BG54+BH54 -> 2 | BJ54: 完了 | BK54: =IF($D54="ADT","1","") -> 1 | BL54: =IF(BJ54="完了","1","") -> 1 | BM54: =BK54+BL54 -> 2 | BN54: 完了 | BO54: =IF($D54="ADT","1","") -> 1 | BP54: =IF(BN54="完了","1","") -> 1 | BQ54: =BO54+BP54 -> 2 | BR54: － | BS54: =IF($D54="ADT","1","") -> 1 | BT54: =IF(BR54="完了","1","") | BU54: =BS54+BT54 -> #VALUE! | BV54: 完了 | BW54: =IF($D54="ADT","1","") -> 1 | BX54: =IF(BV54="完了","1","") -> 1 | BY54: =BW54+BX54 -> 2 | BZ54: － | CA54: =IF($D54="ADT","1","") -> 1 | CB54: =IF(BZ54="完了","1","") | CC54: =CA54+CB54 -> #VALUE! | CD54: － | CE54: =IF($D54="ADT","1","") -> 1 | CF54: =IF(CD54="完了","1","") | CG54: =CE54+CF54 -> #VALUE! | CH54: O:\00 製造一部共通\横展開確認\設備異常報告\異常報告書(日文)\201408以降\20140924ZF 横切り機BURベース取り付け用ナットの脱落.xls | CI54: 0 | CK54: 0 | CM54: =IF(AZ54="","","CLOSE") -> CLOSE | CN54: =IF(F54="","",IF(COUNTIF(BB54:CE54,"未")=0,"CLOSE","")) -> CLOSE | CO54: 0 | CQ54: CLOSE | CR54: CLOSE | CS54: CLOSE | CT54: CLOSE | CU54: CLOSE | CV54: CLOSE | CW54: CLOSE | CX54: CLOSE
A55: 39 | B55: 41895 | C55: =MONTH(B55) -> 9 | D55: 高砂 | E55: GF | F55: 鄭吉勝 | G55: =COUNTIF(T55:AV55,"要") -> 0 | H55: =IF(G55>0,"1","0") -> 0 | I55: =IF(AND(D55="ADT",H55="1"),"1","0") -> 0 | J55: =H55+I55 -> 0 | K55: =IF(CM55="CLOSE",1,"") -> 1 | L55: =J55+K55 -> 1 | M55: =IF(CN55="CLOSE",1,"") -> 1 | N55: =J55+M55 -> 1 | O55: 機械系異常 | P55: 洗淨機風刀吹散Blower | Q55: 9/2工事日針對上一回發生的INV異常對策, 由設技進行O/H (Overhaul)的Blower馬達更換，9/13 00:00巡檢時確認到Blower馬達的異音變大，04:55INV異常警報發出, Line停止。 | R55: INV馬達的Impeller (葉片)和Casing的間距調整不足實施O/H (Overhaul)作業時, 用來調整間距的Liner墊片不見了, 所以未經過適當的間距調整（一般設定在1mm左右的間距）。再加上只有O/H作業經歷比較淺的作業者所實施。 | S55: 1.針對本Blower的Overhaul翻修對象零件及其整備要件加以明確化製作整備手順書。 2.向設技(工作)人員針對此異常內容宣導並教育。 3.如果作業人員對於這項整備作業的經驗較淺, 需由主任指示, 與更有經驗的人員一同作業。 | T55: 情報 | U55: =IF($D55="ADT","1","") | V55: =IF(T55="要","1","") | W55: =U55+V55 -> #VALUE! | X55: 情報 | Y55: =IF($D55="ADT","1","") | Z55: =IF(X55="要","1","") | AA55: =Y55+Z55 -> #VALUE! | AB55: 情報 | AC55: =IF($D55="ADT","1","") | AD55: =IF(AB55="要","1","") | AE55: =AC55+AD55 -> #VALUE! | AF55: 情報 | AG55: =IF($D55="ADT","1","") | AH55: =IF(AF55="要","1","") | AI55: =AG55+AH55 -> #VALUE! | AJ55: 情報 | AK55: =IF($D55="ADT","1","") | AL55: =IF(AJ55="要","1","") | AM55: =AK55+AL55 -> #VALUE! | AN55: 情報 | AO55: =IF($D55="ADT","1","") | AP55: =IF(AN55="要","1","") | AQ55: =AO55+AP55 -> #VALUE! | AR55: 情報 | AS55: =IF($D55="ADT","1","") | AT55: =IF(AR55="要","1","") | AU55: =AS55+AT55 -> #VALUE! | AV55: 情報 | AW55: =IF($D55="ADT","1","") | AX55: =IF(AV55="要","1","") | AY55: =AW55+AX55 -> #VALUE! | AZ55: 設備技術O/H (Overhaul)翻修過必須再一次確認安裝後有無異常聲音及奇怪的地方 | BB55: － | BC55: =IF($D55="ADT","1","") | BD55: =IF(BB55="完了","1","") | BE55: =BC55+BD55 -> #VALUE! | BF55: － | BG55: =IF($D55="ADT","1","") | BH55: =IF(BF55="完了","1","") | BI55: =BG55+BH55 -> #VALUE! | BJ55: － | BK55: =IF($D55="ADT","1","") | BL55: =IF(BJ55="完了","1","") | BM55: =BK55+BL55 -> #VALUE! | BN55: － | BO55: =IF($D55="ADT","1","") | BP55: =IF(BN55="完了","1","") | BQ55: =BO55+BP55 -> #VALUE! | BR55: － | BS55: =IF($D55="ADT","1","") | BT55: =IF(BR55="完了","1","") | BU55: =BS55+BT55 -> #VALUE! | BV55: － | BW55: =IF($D55="ADT","1","") | BX55: =IF(BV55="完了","1","") | BY55: =BW55+BX55 -> #VALUE! | BZ55: － | CA55: =IF($D55="ADT","1","") | CB55: =IF(BZ55="完了","1","") | CC55: =CA55+CB55 -> #VALUE! | CD55: － | CE55: =IF($D55="ADT","1","") | CF55: =IF(CD55="完了","1","") | CG55: =CE55+CF55 -> #VALUE! | CH55: 異常報告書（日文）共有フォルダ\201408以降\20140913GF B-LINE洗浄機エアーナイフインバータ異常-1.xlsx | CI55: 1 | CJ55: 異常報告書（中文）共有フォルダ\201408以降\20140913GF B-LINE洗淨機風刀INV異常-1.xls | CK55: 147 | CM55: =IF(AZ55="","","CLOSE") -> CLOSE | CN55: =IF(F55="","",IF(COUNTIF(BB55:CE55,"未")=0,"CLOSE","")) -> CLOSE | CO55: 235 | CQ55: CLOSE | CR55: CLOSE | CS55: CLOSE | CT55: CLOSE | CU55: CLOSE | CV55: CLOSE | CW55: CLOSE | CX55: CLOSE
A56: 40 | B56: 41900 | C56: =MONTH(B56) -> 9 | D56: 高砂 | E56: GF | F56: 鄭吉勝 | G56: =COUNTIF(T56:AV56,"要") -> 0 | H56: =IF(G56>0,"1","0") -> 0 | I56: =IF(AND(D56="ADT",H56="1"),"1","0") -> 0 | J56: =H56+I56 -> 0 | K56: =IF(CM56="CLOSE",1,"") -> 1 | L56: =J56+K56 -> 1 | M56: =IF(CN56="CLOSE",1,"") -> 1 | N56: =J56+M56 -> 1 | O56: 電気系異常 | P56: PAM | Q56: TOM3檢查機PAM通信異常 | R56: ・PAM精査ServerCPU故障 最近GF出現TOM3 WI PAM TOM3 PAM通信異常散發，但是每次會自動復歸 or 重新啟動 HOSTPC、識別PC、畫處PC就能復歸。 ・設技調查後原因不明。 2014/9/2工事日重新啟動PAM精査Server之後, 就沒有再發生過了, 很可能是PAM精査Server故障的前兆。 | S56: ・PAM精査Server故障時的預防對策, 進行了預備PAM精査Server的精査T/P 面板的設定。(因為只要變更Server, 設定就會出現Default。) | T56: 情報 | U56: =IF($D56="ADT","1","") | V56: =IF(T56="要","1","") | W56: =U56+V56 -> #VALUE! | X56: 情報 | Y56: =IF($D56="ADT","1","") | Z56: =IF(X56="要","1","") | AA56: =Y56+Z56 -> #VALUE! | AB56: 情報 | AC56: =IF($D56="ADT","1","") | AD56: =IF(AB56="要","1","") | AE56: =AC56+AD56 -> #VALUE! | AF56: 情報 | AG56: =IF($D56="ADT","1","") | AH56: =IF(AF56="要","1","") | AI56: =AG56+AH56 -> #VALUE! | AJ56: 情報 | AK56: =IF($D56="ADT","1","") | AL56: =IF(AJ56="要","1","") | AM56: =AK56+AL56 -> #VALUE! | AN56: 情報 | AO56: =IF($D56="ADT","1","") | AP56: =IF(AN56="要","1","") | AQ56: =AO56+AP56 -> #VALUE! | AR56: 情報 | AS56: =IF($D56="ADT","1","") | AT56: =IF(AR56="要","1","") | AU56: =AS56+AT56 -> #VALUE! | AV56: 情報 | AW56: =IF($D56="ADT","1","") | AX56: =IF(AV56="要","1","") | AY56: =AW56+AX56 -> #VALUE! | AZ56: ・為硬體上的故障, Server必須要有預備機 ・TOM3精査設定畫面資料保存（生產推進課） | BB56: － | BC56: =IF($D56="ADT","1","") | BD56: =IF(BB56="完了","1","") | BE56: =BC56+BD56 -> #VALUE! | BF56: － | BG56: =IF($D56="ADT","1","") | BH56: =IF(BF56="完了","1","") | BI56: =BG56+BH56 -> #VALUE! | BJ56: － | BK56: =IF($D56="ADT","1","") | BL56: =IF(BJ56="完了","1","") | BM56: =BK56+BL56 -> #VALUE! | BN56: － | BO56: =IF($D56="ADT","1","") | BP56: =IF(BN56="完了","1","") | BQ56: =BO56+BP56 -> #VALUE! | BR56: － | BS56: =IF($D56="ADT","1","") | BT56: =IF(BR56="完了","1","") | BU56: =BS56+BT56 -> #VALUE! | BV56: － | BW56: =IF($D56="ADT","1","") | BX56: =IF(BV56="完了","1","") | BY56: =BW56+BX56 -> #VALUE! | BZ56: － | CA56: =IF($D56="ADT","1","") | CB56: =IF(BZ56="完了","1","") | CC56: =CA56+CB56 -> #VALUE! | CD56: － | CE56: =IF($D56="ADT","1","") | CF56: =IF(CD56="完了","1","") | CG56: =CE56+CF56 -> #VALUE! | CH56: 異常報告書（日文）共有フォルダ\201408以降\20140918GF TOM3-PAM通信異常.xls | CI56: 0 | CJ56: 異常報告書（中文）共有フォルダ\201408以降\20140918GF TOM3-PAM通信異常.xls | CK56: 311 | CM56: =IF(AZ56="","","CLOSE") -> CLOSE | CN56: =IF(F56="","",IF(COUNTIF(BB56:CE56,"未")=0,"CLOSE","")) -> CLOSE | CO56: 170 | CQ56: CLOSE | CR56: CLOSE | CS56: CLOSE | CT56: CLOSE | CU56: CLOSE | CV56: CLOSE | CW56: CLOSE | CX56: CLOSE
A57: 41 | B57: 41919 | C57: =MONTH(B57) -> 10 | D57: ADT | E57: EF | F57: 万代 | G57: =COUNTIF(T57:AV57,"要") -> 2 | H57: =IF(G57>0,"1","0") -> 1 | I57: =IF(AND(D57="ADT",H57="1"),"1","0") -> 1 | J57: =H57+I57 -> 2 | K57: =IF(CM57="CLOSE",1,"") -> 1 | L57: =J57+K57 -> 3 | M57: =IF(CN57="CLOSE",1,"") -> 1 | N57: =J57+M57 -> 3 | O57: 機械系異常 | P57: 引込C/V－№3 | Q57: 2Br引入C/V3?條（Senser檢出Plate部Joint Pin）折損 | R57: 但此折損處的鍊條、Joint Pin, 自從EF建設（2007年）以後為期7年內完全沒有更換過。 | S57: 定期於每次冷修進行更換。針對鍊條生鏽、潤滑油乾掉、震動等狀況 可能會導致 鍊條斷裂的危險性進行教育訓練。 | T57: 情報 | U57: =IF($D57="ADT","1","") -> 1 | V57: =IF(T57="要","1","") | W57: =U57+V57 -> #VALUE! | X57: 情報 | Y57: =IF($D57="ADT","1","") -> 1 | Z57: =IF(X57="要","1","") | AA57: =Y57+Z57 -> #VALUE! | AB57: 要 | AC57: =IF($D57="ADT","1","") -> 1 | AD57: =IF(AB57="要","1","") -> 1 | AE57: =AC57+AD57 -> 2 | AF57: 要 | AG57: =IF($D57="ADT","1","") -> 1 | AH57: =IF(AF57="要","1","") -> 1 | AI57: =AG57+AH57 -> 2 | AJ57: 情報 | AK57: =IF($D57="ADT","1","") -> 1 | AL57: =IF(AJ57="要","1","") | AM57: =AK57+AL57 -> #VALUE! | AN57: 情報 | AO57: =IF($D57="ADT","1","") -> 1 | AP57: =IF(AN57="要","1","") | AQ57: =AO57+AP57 -> #VALUE! | AR57: － | AS57: =IF($D57="ADT","1","") -> 1 | AT57: =IF(AR57="要","1","") | AU57: =AS57+AT57 -> #VALUE! | AV57: － | AW57: =IF($D57="ADT","1","") -> 1 | AX57: =IF(AV57="要","1","") | AY57: =AW57+AX57 -> #VALUE! | AZ57: 確認於每次冷修進行更換。確保予備品。 | BB57: － | BC57: =IF($D57="ADT","1","") -> 1 | BD57: =IF(BB57="完了","1","") | BE57: =BC57+BD57 -> #VALUE! | BF57: － | BG57: =IF($D57="ADT","1","") -> 1 | BH57: =IF(BF57="完了","1","") | BI57: =BG57+BH57 -> #VALUE! | BJ57: 完了 | BK57: =IF($D57="ADT","1","") -> 1 | BL57: =IF(BJ57="完了","1","") -> 1 | BM57: =BK57+BL57 -> 2 | BN57: 完了 | BO57: =IF($D57="ADT","1","") -> 1 | BP57: =IF(BN57="完了","1","") -> 1 | BQ57: =BO57+BP57 -> 2 | BR57: － | BS57: =IF($D57="ADT","1","") -> 1 | BT57: =IF(BR57="完了","1","") | BU57: =BS57+BT57 -> #VALUE! | BV57: － | BW57: =IF($D57="ADT","1","") -> 1 | BX57: =IF(BV57="完了","1","") | BY57: =BW57+BX57 -> #VALUE! | BZ57: － | CA57: =IF($D57="ADT","1","") -> 1 | CB57: =IF(BZ57="完了","1","") | CC57: =CA57+CB57 -> #VALUE! | CD57: － | CE57: =IF($D57="ADT","1","") -> 1 | CF57: =IF(CD57="完了","1","") | CG57: =CE57+CF57 -> #VALUE! | CH57: \\172.18.154.189\mfg_public\00 製造一部共通\横展開確認\設備異常報告\異常報告書(日文)\201408以降 | CI57: 0 | CJ57: 異常報告書（中文）共有フォルダ\201408以降\20141007EF 2Br引込CVﾁｪｰﾝ（ｾﾝｻｰ検出ﾌﾟﾚｰﾄ部ｼﾞｮｲﾝﾄﾋﾟﾝ）折損.xls | CK57: 257 | CM57: =IF(AZ57="","","CLOSE") -> CLOSE | CN57: =IF(F57="","",IF(COUNTIF(BB57:CE57,"未")=0,"CLOSE","")) -> CLOSE | CO57: 10 | CQ57: CLOSE | CR57: CLOSE | CS57: CLOSE | CT57: CLOSE | CU57: CLOSE | CV57: CLOSE | CW57: CLOSE | CX57: CLOSE
A58: 42 | B58: 41914 | C58: =MONTH(B58) -> 10 | D58: AFK | E58: IF | F58: 鄭吉勝 | G58: =COUNTIF(T58:AV58,"要") -> 0 | H58: =IF(G58>0,"1","0") -> 0 | I58: =IF(AND(D58="ADT",H58="1"),"1","0") -> 0 | J58: =H58+I58 -> 0 | K58: =IF(CM58="CLOSE",1,"") -> 1 | L58: =J58+K58 -> 1 | M58: =IF(CN58="CLOSE",1,"") -> 1 | N58: =J58+M58 -> 1 | O58: 検査機系異常 | P58: TOM3 | Q58: TOM3画像処理PC Freeze散発異常 | R58: 6chBOX異常的可能性很高 | S58: 因為還未掌握到確切的原因, 預定下回工事日將拆下來的6chBOX連接到目前未使用的NET外的畫像處理PC, 以確認並重現當時的現象 | T58: 情報 | U58: =IF($D58="ADT","1","") | V58: =IF(T58="要","1","") | W58: =U58+V58 -> #VALUE! | X58: 情報 | Y58: =IF($D58="ADT","1","") | Z58: =IF(X58="要","1","") | AA58: =Y58+Z58 -> #VALUE! | AB58: 情報 | AC58: =IF($D58="ADT","1","") | AD58: =IF(AB58="要","1","") | AE58: =AC58+AD58 -> #VALUE! | AF58: 情報 | AG58: =IF($D58="ADT","1","") | AH58: =IF(AF58="要","1","") | AI58: =AG58+AH58 -> #VALUE! | AJ58: 情報 | AK58: =IF($D58="ADT","1","") | AL58: =IF(AJ58="要","1","") | AM58: =AK58+AL58 -> #VALUE! | AN58: 情報 | AO58: =IF($D58="ADT","1","") | AP58: =IF(AN58="要","1","") | AQ58: =AO58+AP58 -> #VALUE! | AR58: － | AS58: =IF($D58="ADT","1","") | AT58: =IF(AR58="要","1","") | AU58: =AS58+AT58 -> #VALUE! | AV58: － | AW58: =IF($D58="ADT","1","") | AX58: =IF(AV58="要","1","") | AY58: =AW58+AX58 -> #VALUE! | AZ58: 待ENG原因調查及再現性確認 | BB58: － | BC58: =IF($D58="ADT","1","") | BD58: =IF(BB58="完了","1","") | BE58: =BC58+BD58 -> #VALUE! | BF58: － | BG58: =IF($D58="ADT","1","") | BH58: =IF(BF58="完了","1","") | BI58: =BG58+BH58 -> #VALUE! | BJ58: － | BK58: =IF($D58="ADT","1","") | BL58: =IF(BJ58="完了","1","") | BM58: =BK58+BL58 -> #VALUE! | BN58: － | BO58: =IF($D58="ADT","1","") | BP58: =IF(BN58="完了","1","") | BQ58: =BO58+BP58 -> #VALUE! | BR58: － | BS58: =IF($D58="ADT","1","") | BT58: =IF(BR58="完了","1","") | BU58: =BS58+BT58 -> #VALUE! | BV58: － | BW58: =IF($D58="ADT","1","") | BX58: =IF(BV58="完了","1","") | BY58: =BW58+BX58 -> #VALUE! | BZ58: － | CA58: =IF($D58="ADT","1","") | CB58: =IF(BZ58="完了","1","") | CC58: =CA58+CB58 -> #VALUE! | CD58: － | CE58: =IF($D58="ADT","1","") | CF58: =IF(CD58="完了","1","") | CG58: =CE58+CF58 -> #VALUE! | CH58: 異常報告書（日文）共有フォルダ\201408以降\20141002IF TOM3画像処理PCフリーズ散発異常.xls | CI58: 0 | CJ58: 異常報告書（中文）共有フォルダ\201408以降\20141002IF TOM3畫像處理PC當機散發異常.xls | CK58: 136 | CM58: =IF(AZ58="","","CLOSE") -> CLOSE | CN58: =IF(F58="","",IF(COUNTIF(BB58:CE58,"未")=0,"CLOSE","")) -> CLOSE | CO58: 0 | CQ58: CLOSE | CR58: CLOSE | CS58: CLOSE | CT58: CLOSE | CU58: CLOSE | CV58: CLOSE | CW58: CLOSE | CX58: CLOSE
A59: 43 | B59: 41916 | C59: =MONTH(B59) -> 10 | D59: AFK | E59: FF | F59: 三路 | G59: =COUNTIF(T59:AV59,"要") -> 0 | H59: =IF(G59>0,"1","0") -> 0 | I59: =IF(AND(D59="ADT",H59="1"),"1","0") -> 0 | J59: =H59+I59 -> 0 | K59: =IF(CM59="CLOSE",1,"") -> 1 | L59: =J59+K59 -> 1 | M59: =IF(CN59="CLOSE",1,"") -> 1 | N59: =J59+M59 -> 1 | O59: 検査機系異常 | P59: WI | Q59: ・発生SP-RANK「T」。#15 CAMERA光量波形變異常高的状態。 | R59: ・原因不明 | S59: ・由於原因不明所以沒有対策。 | T59: 情報 | U59: =IF($D59="ADT","1","") | V59: =IF(T59="要","1","") | W59: =U59+V59 -> #VALUE! | X59: 情報 | Y59: =IF($D59="ADT","1","") | Z59: =IF(X59="要","1","") | AA59: =Y59+Z59 -> #VALUE! | AB59: 情報 | AC59: =IF($D59="ADT","1","") | AD59: =IF(AB59="要","1","") | AE59: =AC59+AD59 -> #VALUE! | AF59: 情報 | AG59: =IF($D59="ADT","1","") | AH59: =IF(AF59="要","1","") | AI59: =AG59+AH59 -> #VALUE! | AJ59: 情報 | AK59: =IF($D59="ADT","1","") | AL59: =IF(AJ59="要","1","") | AM59: =AK59+AL59 -> #VALUE! | AN59: 情報 | AO59: =IF($D59="ADT","1","") | AP59: =IF(AN59="要","1","") | AQ59: =AO59+AP59 -> #VALUE! | AR59: － | AS59: =IF($D59="ADT","1","") | AT59: =IF(AR59="要","1","") | AU59: =AS59+AT59 -> #VALUE! | AV59: － | AW59: =IF($D59="ADT","1","") | AX59: =IF(AV59="要","1","") | AY59: =AW59+AX59 -> #VALUE! | AZ59: ・情報共有 ※發生同様事例時，希望能夠利用纜線更換等來找出原因處。 | BB59: － | BC59: =IF($D59="ADT","1","") | BD59: =IF(BB59="完了","1","") | BE59: =BC59+BD59 -> #VALUE! | BF59: － | BG59: =IF($D59="ADT","1","") | BH59: =IF(BF59="完了","1","") | BI59: =BG59+BH59 -> #VALUE! | BJ59: － | BK59: =IF($D59="ADT","1","") | BL59: =IF(BJ59="完了","1","") | BM59: =BK59+BL59 -> #VALUE! | BN59: － | BO59: =IF($D59="ADT","1","") | BP59: =IF(BN59="完了","1","") | BQ59: =BO59+BP59 -> #VALUE! | BR59: － | BS59: =IF($D59="ADT","1","") | BT59: =IF(BR59="完了","1","") | BU59: =BS59+BT59 -> #VALUE! | BV59: － | BW59: =IF($D59="ADT","1","") | BX59: =IF(BV59="完了","1","") | BY59: =BW59+BX59 -> #VALUE! | BZ59: － | CA59: =IF($D59="ADT","1","") | CB59: =IF(BZ59="完了","1","") | CC59: =CA59+CB59 -> #VALUE! | CD59: － | CE59: =IF($D59="ADT","1","") | CF59: =IF(CD59="完了","1","") | CG59: =CE59+CF59 -> #VALUE! | CH59: O:\00 製造一部共通\横展開確認\設備異常報告\異常報告書(日文)\201408以降\20141008_AFK_FF_WI検査機#15Camera異常.xls | CI59: 0 | CJ59: 異常報告書（中文）共有フォルダ\201408以降\20141008_AFK_FF_WI検査機#15Camera異常.xls | CK59: 0 | CM59: =IF(AZ59="","","CLOSE") -> CLOSE | CN59: =IF(F59="","",IF(COUNTIF(BB59:CE59,"未")=0,"CLOSE","")) -> CLOSE | CO59: 0 | CQ59: CLOSE | CR59: CLOSE | CS59: CLOSE | CT59: CLOSE | CU59: CLOSE | CV59: CLOSE | CW59: CLOSE | CX59: CLOSE
A60: 44 | B60: 41925 | C60: =MONTH(B60) -> 10 | D60: AFK | E60: HF | F60: 三路 | G60: =COUNTIF(T60:AV60,"要") -> 0 | H60: =IF(G60>0,"1","0") -> 0 | I60: =IF(AND(D60="ADT",H60="1"),"1","0") -> 0 | J60: =H60+I60 -> 0 | K60: =IF(CM60="CLOSE",1,"") -> 1 | L60: =J60+K60 -> 1 | M60: =IF(CN60="CLOSE",1,"") -> 1 | N60: =J60+M60 -> 1 | O60: 電気系異常 | P60: 反轉移載Robot | Q60: ・Robot Pendant Controller零星發生「1326:R軸編碼器絕對異常」。更換R軸的伺服馬達後就無異常。 | R60: ・推測因經年劣化造成伺服馬達的編碼器異常。 | S60: ・更換伺服馬達 ※再発時予定更換機内的Harness。 | T60: 情報 | U60: =IF($D60="ADT","1","") | V60: =IF(T60="要","1","") | W60: =U60+V60 -> #VALUE! | X60: 情報 | Y60: =IF($D60="ADT","1","") | Z60: =IF(X60="要","1","") | AA60: =Y60+Z60 -> #VALUE! | AB60: 情報 | AC60: =IF($D60="ADT","1","") | AD60: =IF(AB60="要","1","") | AE60: =AC60+AD60 -> #VALUE! | AF60: 情報 | AG60: =IF($D60="ADT","1","") | AH60: =IF(AF60="要","1","") | AI60: =AG60+AH60 -> #VALUE! | AJ60: 情報 | AK60: =IF($D60="ADT","1","") | AL60: =IF(AJ60="要","1","") | AM60: =AK60+AL60 -> #VALUE! | AN60: 情報 | AO60: =IF($D60="ADT","1","") | AP60: =IF(AN60="要","1","") | AQ60: =AO60+AP60 -> #VALUE! | AR60: 情報 | AS60: =IF($D60="ADT","1","") | AT60: =IF(AR60="要","1","") | AU60: =AS60+AT60 -> #VALUE! | AV60: 情報 | AW60: =IF($D60="ADT","1","") | AX60: =IF(AV60="要","1","") | AY60: =AW60+AX60 -> #VALUE! | AZ60: ・情報共有。 ※在Robot異常発生時能夠先行實施異常内容的確認。 | BB60: － | BC60: =IF($D60="ADT","1","") | BD60: =IF(BB60="完了","1","") | BE60: =BC60+BD60 -> #VALUE! | BF60: － | BG60: =IF($D60="ADT","1","") | BH60: =IF(BF60="完了","1","") | BI60: =BG60+BH60 -> #VALUE! | BJ60: － | BK60: =IF($D60="ADT","1","") | BL60: =IF(BJ60="完了","1","") | BM60: =BK60+BL60 -> #VALUE! | BN60: － | BO60: =IF($D60="ADT","1","") | BP60: =IF(BN60="完了","1","") | BQ60: =BO60+BP60 -> #VALUE! | BR60: － | BS60: =IF($D60="ADT","1","") | BT60: =IF(BR60="完了","1","") | BU60: =BS60+BT60 -> #VALUE! | BV60: － | BW60: =IF($D60="ADT","1","") | BX60: =IF(BV60="完了","1","") | BY60: =BW60+BX60 -> #VALUE! | BZ60: － | CA60: =IF($D60="ADT","1","") | CB60: =IF(BZ60="完了","1","") | CC60: =CA60+CB60 -> #VALUE! | CD60: － | CE60: =IF($D60="ADT","1","") | CF60: =IF(CD60="完了","1","") | CG60: =CE60+CF60 -> #VALUE! | CH60: O:\00 製造一部共通\横展開確認\設備異常報告\異常報告書(日文)\201408以降\20141012HF 2Br反転移載ロボット_サーボエンコーダ異常と思われる停止.xlsx | CI60: 0 | CJ60: 異常報告書（中文）共有フォルダ\201408以降\20141012 HF 2Br反轉移載Robot停止 疑似Servo Encorder異常.xls | CK60: 0 | CM60: =IF(AZ60="","","CLOSE") -> CLOSE | CN60: =IF(F60="","",IF(COUNTIF(BB60:CE60,"未")=0,"CLOSE","")) -> CLOSE | CO60: 0 | CQ60: CLOSE | CR60: CLOSE | CS60: CLOSE | CT60: CLOSE | CU60: CLOSE | CV60: CLOSE | CW60: CLOSE | CX60: CLOSE
A61: 45 | B61: 41920 | C61: =MONTH(B61) -> 10 | D61: 高砂 | E61: ＷＩＴ | F61: 三路 | G61: =COUNTIF(T61:AV61,"要") -> 0 | H61: =IF(G61>0,"1","0") -> 0 | I61: =IF(AND(D61="ADT",H61="1"),"1","0") -> 0 | J61: =H61+I61 -> 0 | K61: =IF(CM61="CLOSE",1,"") -> 1 | L61: =J61+K61 -> 1 | M61: =IF(CN61="CLOSE",1,"") -> 1 | N61: =J61+M61 -> 1 | O61: 電気系異常 | P61: 採板Robot | Q61: ・定修後第1枚基板積載至PL時，Robot-Hand和PL碰撞造成Hand破損。 | R61: ・使用Pendant Controller來操作Robot時，錯將T軸的補正値寫入。 | S61: ・實施T軸補正値不會被代入的程式変更。 | T61: 情報 | U61: =IF($D61="ADT","1","") | V61: =IF(T61="要","1","") | W61: =U61+V61 -> #VALUE! | X61: 情報 | Y61: =IF($D61="ADT","1","") | Z61: =IF(X61="要","1","") | AA61: =Y61+Z61 -> #VALUE! | AB61: 情報 | AC61: =IF($D61="ADT","1","") | AD61: =IF(AB61="要","1","") | AE61: =AC61+AD61 -> #VALUE! | AF61: 情報 | AG61: =IF($D61="ADT","1","") | AH61: =IF(AF61="要","1","") | AI61: =AG61+AH61 -> #VALUE! | AJ61: 情報 | AK61: =IF($D61="ADT","1","") | AL61: =IF(AJ61="要","1","") | AM61: =AK61+AL61 -> #VALUE! | AN61: 情報 | AO61: =IF($D61="ADT","1","") | AP61: =IF(AN61="要","1","") | AQ61: =AO61+AP61 -> #VALUE! | AR61: 情報 | AS61: =IF($D61="ADT","1","") | AT61: =IF(AR61="要","1","") | AU61: =AS61+AT61 -> #VALUE! | AV61: 情報 | AW61: =IF($D61="ADT","1","") | AX61: =IF(AV61="要","1","") | AY61: =AW61+AX61 -> #VALUE! | AZ61: ・情報共有。 ※製造不使用Pendant Controller來進行操作，但在電気G等操作後有必要以低速模式等來確認是否正常的作動。 | BB61: － | BC61: =IF($D61="ADT","1","") | BD61: =IF(BB61="完了","1","") | BE61: =BC61+BD61 -> #VALUE! | BF61: － | BG61: =IF($D61="ADT","1","") | BH61: =IF(BF61="完了","1","") | BI61: =BG61+BH61 -> #VALUE! | BJ61: － | BK61: =IF($D61="ADT","1","") | BL61: =IF(BJ61="完了","1","") | BM61: =BK61+BL61 -> #VALUE! | BN61: － | BO61: =IF($D61="ADT","1","") | BP61: =IF(BN61="完了","1","") | BQ61: =BO61+BP61 -> #VALUE! | BR61: － | BS61: =IF($D61="ADT","1","") | BT61: =IF(BR61="完了","1","") | BU61: =BS61+BT61 -> #VALUE! | BV61: － | BW61: =IF($D61="ADT","1","") | BX61: =IF(BV61="完了","1","") | BY61: =BW61+BX61 -> #VALUE! | BZ61: － | CA61: =IF($D61="ADT","1","") | CB61: =IF(BZ61="完了","1","") | CC61: =CA61+CB61 -> #VALUE! | CD61: － | CE61: =IF($D61="ADT","1","") | CF61: =IF(CD61="完了","1","") | CG61: =CE61+CF61 -> #VALUE! | CH61: 異常報告書（日文）共有フォルダ\201408以降\20141008 WIT NO1 Robot採板機衝突破損.xlsx | CI61: 0 | CJ61: 異常報告書（中文）共有フォルダ\201408以降\20141008 WIT NO1 Robot採板機衝突破損.xlsx | CK61: 0 | CM61: =IF(AZ61="","","CLOSE") -> CLOSE | CN61: =IF(F61="","",IF(COUNTIF(BB61:CE61,"未")=0,"CLOSE","")) -> CLOSE | CO61: 0 | CQ61: CLOSE | CR61: CLOSE | CS61: CLOSE | CT61: CLOSE | CU61: CLOSE | CV61: CLOSE | CW61: CLOSE | CX61: CLOSE
